Workbook
Name ___SH2: #REF!
Name ___SH2: #REF!
Name ___SH2: #REF!
Name ___SH2: #REF!
Name ___SH2: #REF!
Name ___SH2: #REF!
Name ___SH2: #REF!
Name ___SH2: #REF!
Name ___SH2: #REF!
Name ___SH2: #REF!
Name ___SH2: #REF!
Name ___SH2: #REF!
Name ___SH2: #REF!
Name ___SH2: #REF!
Name ___SH2: #REF!
Name ___SH2: #REF!
Name ___SH2: #REF!
Name ___SH2: #REF!
Name ___SH2: #REF!
Name ___SH2: #REF!
Name __SH2: #REF!
Name __SH2: #REF!
Name __SH2: #REF!
Name __SH2: #REF!
Name __SH2: #REF!
Name __SH2: #REF!
Name __SH2: #REF!
Name __SH2: #REF!
Name __SH2: #REF!
Name __SH2: #REF!
Name __SH2: #REF!
Name __SH2: #REF!
Name __SH2: #REF!
Name __SH2: #REF!
Name __SH2: #REF!
Name __SH2: #REF!
Name __SH2: #REF!
Name __SH2: #REF!
Name __SH2: #REF!
Name __SH2: #REF!
Name _SH2: #REF!
Name _SH2: #REF!
Name _SH2: #REF!
Name _SH2: #REF!
Name _SH2: #REF!
Name _SH2: #REF!
Name _SH2: #REF!
Name _SH2: #REF!
Name _SH2: #REF!
Name _SH2: #REF!
Name _SH2: #REF!
Name _SH2: #REF!
Name _SH2: #REF!
Name _SH2: #REF!
Name _SH2: #REF!
Name _SH2: #REF!
Name _SH2: #REF!
Name _SH2: #REF!
Name _SH2: #REF!
Name _SH2: #REF!

Sheet COVER
E2: GHANA STATISTICAL SERVICE
E3: Statistics for Development and Progress
H6: Quarterly GDP Bullletin
C10: SEPTEMBER 2026 EDITION
B35: Ghana Statistical Service (GSS)
B36: P.O. Box GP 1098, Accra
B37: www.statsghana.gov.gh

Sheet Table of Content
B3: Table of Content
B4: Notes………...……………………………………………………………………………………………………….... 1
B5: Appendix discription..…..………………………………………………………………………………………. 2
B6: Appendices ………………………………………………………………………………………………………….. 3

Sheet Notes
A1: NOTES
A3: Forthcoming issues
B4: Issue | C4: Expected Date of Publication
B5: Second Quarter of 2026 | C5: 46274
B6: Third Quarter of 2026 | C6: 46365
B7: Fourth Quarter of 2026 | C7: 46456
A9: Explanatory notes
A11: Introduction
A12: This publication contains final rebased quarterly GDP estimates for 2006 Q1 to 2023Q4, revised estimates for
A13: 2024Q1 to 2026Q1 and provisional estimates for 2026Q2.
A15: Gross Domestic Product (GDP) is Ghana’s official measure of economic growth.There are three different approaches for calculating GDP. These are the production approach, the expenditure approach and the income approach. The production and expenditure approaches are used to calculate Ghana’s GDP on a quarterly basis.
A16: The bulletin contains 30 Tables: Appendix 1 to 4: Quarterly GDP at Current Prices by Economic Activity and respective Sectoral Distribution; Appendix 5: Quarterly Deflators by Economi Activity; Appendix 6 to 15: Quarterly GDP at Constant 2013 prices by Economic Activity and Sectoral Growth rates; Appendix 16 to 25: Seasonally Adjusted Quarterly GDP at Constant 2013 Prices by Economic Activity and Sectoral growth rates. Appendix 26: Distribtion of GDP, Appendix 27: Contribution to Growth. Appendix 28 to 30: Half Year Current GDP, Constant GDP and Contribution to Growth.
A17: For more information about GDP and the national accounts, go to Ghana Statistical Service website (www.statsghana.gov.gh).
A19: Sources and Methods
A20: This Statistical Release contains independently compiled quarterly estimates of the Gross Domestic Product (GDP) from the first quarter of 2013 onwards. The estimates are based on the 2008 System of National Accounts (SNA), International Standard Industrial Classification Revision 4 published by the United Nations and Quarterly National Accounts Manual: Concepts, Data Sources and Compilation by International Monetary Fund (IMF). This means that the methodology, concepts and classifications are in accordance with the guidelines and recommendations of an internationally agreed system of national accounts. The estimates of real GDP use 2013 as the base year.
A22: Methodology
A24: Short-term indicators are used to estimate the quarterly GDP (See IMF's Quarterly National Accounts Manual: Concepts, Data sources, and Compilation) from which annual GDP estimates are calculated independently from the quarterly estimates. Alternatively, annual GDP estimates are derived as the sum of the GDP for the four quarters of the year.
A26: Seasonal adjustment
... A35: Irregular: Irregular revisions occur for example, as a result of methodological changes. Note that, as far as possible, revisions of this nature are incorporated to coincide with the annual cycle of revisions outlined above.

Sheet Table Description
B3: Appendix description
B4: Appendix 1- Quarterly Value Added and Gross Domestic Product at Current Prices by Economic Activity and Respective Sectoral Distribution
B5: Appendix 2 - Agriculture: Value Added by activity at Current Prices
B6: Appendix 3- Industry: Value Added by Activity at Current Prices
B7: Appendix 4 - Services: Value Added by Activity at Current Prices
B8: Appendix 5 - Quarterly Deflators by Economic Activity
B9: Appendix 6 - Quarterly Value Added and Gross Domestic Product at Constant 2013 Prices by Economic Activity
B10: Appendix 7 - Agriculture: Quarterly Value Added at Constant 2013 Prices by Economic Activity
B11: Appendix 8 - Agriculture: Quarterly Value Added at Constant 2013 Prices by Economic Activity (Quarter-on-Quarter Change)
B12: Appendix 9 - Agriculture: Quarterly Value dded at Constant 2013 Prices by Economic Activity (Year-on-Year Change)
B13: Appendix 10 - Industry: Quarterly Value Added at Constant 2013 Prices by Economic Activity
B14: Appendix 11 - Industry: Quarterly Value Added at Constant 2013 Prices by Economic Activity (Quarter-on-Quarter Change)
... B33: Appendix 30: Half Year Contribution to Growth

Sheet tables
A4: Tables
A7: ='T1'!B1 -> Table 1 - Quarterly Value Added by Activity and Gross Domestic Product at Constant 2006 Prices (GHc Million)
A9: ='T2'!B1 -> Table 2 - Percentage change (quarter-on-quarter) in the quarterly value added by Activity at 2006 constant prices
A11: ='T3'!B1 -> Table 3 - Percentage Changes (Year-on-Year) in the Quarterly Value Added by Activity and Gross Domestic Product at Constant 2006 Prices
A13: ='T4'!B1 -> Table 4 - Seasonal Adjusted Quarterly Gross Value Added by Activity at Constant 2006 Prices (GHc Million)
A15: ='T5'!B1 -> Table 5 - Percentage change (quarter-on-quarter) Seasonal Adjusted Quarterly Gross Value Added by Activity at Constant 2006 Prices
A17: ='T6'!B1 -> Table 6 - Percentage Changes (Year-on-Year) in the Seasonal Adjusted Quarterly Value Added by Activity and Gross Domestic Product at Constant 2006 Prices
A19: ='Current GDP_All'!A1 -> Appendix 1- Quarterly Value Added and Gross Domestic Product at Current Prices by Economic Activity and Respective Sectoral Distribution
A21: =Tsum2!B1 -> Table 2 - Seasonal Adjusted Quarterly Gross Domestic Product at Constant 2006 Prices
B40: 5

Sheet T1
B1: Table 1 - Quarterly Value Added by Activity and Gross Domestic Product at Constant 2006 Prices (GHc Million)
D2: Agriculture Sector | H2: Industry Sector | M2: Services Sector
B3: Year | C3: Quarter | D3: Crops & Cocoa | E3: Livestock | F3: Forestry | G3: Fishing | H3: Mining and Quarrying | I3: Manufacturing | J3: Electricity | K3: Water & Sewerage | L3: Construction | M3: Trade; Repair Of Vehicles, Household Goods | N3: Hotels And Restaurants | O3: Transport & Storage | P3: Information & Communication | Q3: Financial & Insurance Activities | R3: Real Estate Activities | S3: Business & other Services Activities | T3: Public Administration | U3: Education | V3: Health | W3: Other Personal Service Activities | X3: Total Value Added at Basis Prices | Y3: Net Taxes | Z3: GDP at Constant Prices | AC3: Agric | AD3: Ind | AE3: Serv | AF3: controle
B4: 2006 | D4: 3793.682 | E4: 437.09725 | F4: 736.00309 | G4: 448.25153 | H4: 497.4452 | I4: 1823.4833 | J4: 142.71912 | K4: 224.36136 | L4: 1016.2744 | M4: 1140.6992 | N4: 894.08203 | O4: 2357.2217 | P4: 483.03723 | Q4: 472.8561 | R4: 391.4 | S4: 522.52707 | T4: 862.13807 | U4: 654.95995 | V4: 249.83921 | W4: 661.61553 | X4: =D4+E4+F4+G4+H4+I4+J4+K4+L4+M4+N4+O4+P4+Q4+R4+S4+T4+U4+V4+W4 -> 17809.693 | Y4: 895.36021 | Z4: 18705.054 | AC4: =D4+E4+F4+G4 -> 5415.0338 | AD4: =H4+I4+J4+K4+L4 -> 3704.2834 | AE4: =I4+J4+K4+L4+M4 -> 4347.5374 | AF4: =AC4+AD4+AE4 -> 13466.855
B5: 2007 | D5: 3742.596 | E5: 457.77915 | F5: 705.88127 | G5: 415.76563 | H5: 531.5803 | I5: 1801.3123 | J5: 118.15348 | K5: 226.96637 | L5: 1251.5619 | M5: 1202.6217 | N5: 916.59233 | O5: 2573.4037 | P5: 502.84176 | Q5: 559.76897 | R5: 400.7936 | S5: 542.72237 | T5: 959.55967 | U5: 720.45595 | V5: 259.27272 | W5: 720.31678 | X5: =D5+E5+F5+G5+H5+I5+J5+K5+L5+M5+N5+O5+P5+Q5+R5+S5+T5+U5+V5+W5 -> 18609.946 | Y5: 1303.4106 | Z5: 19913.357 | AC5: =D5+E5+F5+G5 -> 5322.0221 | AD5: =H5+I5+J5+K5+L5 -> 3929.5743 | AE5: =I5+J5+K5+L5+M5 -> 4600.6157 | AF5: =AC5+AD5+AE5 -> 13852.212
B6: 2008 | D6: 4064.4593 | E6: 481.14404 | F6: 682.44508 | G6: 488.02892 | H6: 544.44121 | I6: 1867.9694 | J6: 141.10302 | K6: 228.8878 | L6: 1739.4644 | M6: 1316.9257 | N6: 999.77813 | O6: 2671.91 | P6: 600.8959 | Q6: 620.12127 | R6: 410.41265 | S6: 532.78696 | T6: 1081.751 | U6: 814.29858 | V6: 270.78237 | W6: 786.30765 | X6: =D6+E6+F6+G6+H6+I6+J6+K6+L6+M6+N6+O6+P6+Q6+R6+S6+T6+U6+V6+W6 -> 20343.913 | Y6: 1248.2662 | Z6: 21592.18 | AC6: =D6+E6+F6+G6 -> 5716.0774 | AD6: =H6+I6+J6+K6+L6 -> 4521.8658 | AE6: =I6+J6+K6+L6+M6 -> 5294.3503 | AF6: =AC6+AD6+AE6 -> 15532.294
B7: 2009 | D7: 4479.4263 | E7: 502.15329 | F7: 687.36015 | G7: 460.15533 | H7: 581.2 | I7: 1843.5799 | J7: 151.69194 | K7: 246.39795 | L7: 1901.8527 | M7: 1387.931 | N7: 962.00084 | O7: 2790.1363 | P7: 624.16472 | Q7: 677.93817 | R7: 420.26255 | S7: 524.52844 | T7: 1208.1799 | U7: 914.89016 | V7: 311.81225 | W7: 845.05032 | X7: =D7+E7+F7+G7+H7+I7+J7+K7+L7+M7+N7+O7+P7+Q7+R7+S7+T7+U7+V7+W7 -> 21520.712 | Y7: 933.77662 | Z7: 22454.489 | AC7: =D7+E7+F7+G7 -> 6129.095 | AD7: =H7+I7+J7+K7+L7 -> 4724.7225 | AE7: =I7+J7+K7+L7+M7 -> 5531.4535 | AF7: =AC7+AD7+AE7 -> 16385.271
B8: 2010 | D8: 4703.4 | E8: 525.5 | F8: 756.58618 | G8: 467.01505 | H8: 625.61986 | I8: 1983.7 | J8: 170.28972 | K8: 259.36777 | L8: 1949.3991 | M8: 1573.0945 | N8: 987.85721 | O8: 3014.308 | P8: 776.90602 | Q8: 791.49056 | R8: 430.34885 | S8: 645.7 | T8: 1248.9614 | U8: 963.21808 | V8: 346.86159 | W8: 935.5 | X8: =D8+E8+F8+G8+H8+I8+J8+K8+L8+M8+N8+O8+P8+Q8+R8+S8+T8+U8+V8+W8 -> 23155.124 | Y8: 1032.2005 | Z8: 24187.324 | AC8: =D8+E8+F8+G8 -> 6452.5012 | AD8: =H8+I8+J8+K8+L8 -> 4988.3764 | AE8: =I8+J8+K8+L8+M8 -> 5935.8511 | AF8: =AC8+AD8+AE8 -> 17376.729
B10: 2006 | C10: 1 | D10: =#REF! -> #REF! | E10: =#REF! -> #REF! | F10: =#REF! -> #REF! | G10: =#REF! -> #REF! | H10: =#REF! -> #REF! | I10: =#REF! -> #REF! | J10: =#REF! -> #REF! | K10: =#REF! -> #REF! | ... W10: =#REF! -> #REF! | X10: =D10+E10+F10+G10+H10+I10+J10+K10+L10+M10+N10+O10+P10+Q10+R10+S10+T10+U10+V10+W10 -> #REF! | Y10: =#REF! -> #REF! | Z10: =X10+Y10 -> #REF! | AC10: =D10+E10+F10+G10 -> #REF! | AD10: =H10+I10+J10+K10+L10 -> #REF! | AE10: =I10+J10+K10+L10+M10 -> #REF! | AF10: =AC10+AD10+AE10 -> #REF! | AG10: =AF10-X10 -> #REF!
C11: 2 | D11: =#REF! -> #REF! | E11: =#REF! -> #REF! | F11: =#REF! -> #REF! | G11: =#REF! -> #REF! | H11: =#REF! -> #REF! | I11: =#REF! -> #REF! | J11: =#REF! -> #REF! | K11: =#REF! -> #REF! | ... W11: =#REF! -> #REF! | X11: =D11+E11+F11+G11+H11+I11+J11+K11+L11+M11+N11+O11+P11+Q11+R11+S11+T11+U11+V11+W11 -> #REF! | Y11: =#REF! -> #REF! | Z11: =X11+Y11 -> #REF! | AC11: =D11+E11+F11+G11 -> #REF! | AD11: =H11+I11+J11+K11+L11 -> #REF! | AE11: =M11+N11+O11+P11+Q11+R11+S11+T11+U11+V11+W11 -> #REF! | AF11: =AC11+AD11+AE11 -> #REF! | AG11: =AF11-X11 -> #REF!
C12: 3 | D12: =#REF! -> #REF! | E12: =#REF! -> #REF! | F12: =#REF! -> #REF! | G12: =#REF! -> #REF! | H12: =#REF! -> #REF! | I12: =#REF! -> #REF! | J12: =#REF! -> #REF! | K12: =#REF! -> #REF! | ... W12: =#REF! -> #REF! | X12: =D12+E12+F12+G12+H12+I12+J12+K12+L12+M12+N12+O12+P12+Q12+R12+S12+T12+U12+V12+W12 -> #REF! | Y12: =#REF! -> #REF! | Z12: =X12+Y12 -> #REF! | AC12: =D12+E12+F12+G12 -> #REF! | AD12: =H12+I12+J12+K12+L12 -> #REF! | AE12: =M12+N12+O12+P12+Q12+R12+S12+T12+U12+V12+W12 -> #REF! | AF12: =AC12+AD12+AE12 -> #REF! | AG12: =AF12-X12 -> #REF!
C13: 4 | D13: =#REF! -> #REF! | E13: =#REF! -> #REF! | F13: =#REF! -> #REF! | G13: =#REF! -> #REF! | H13: =#REF! -> #REF! | I13: =#REF! -> #REF! | J13: =#REF! -> #REF! | K13: =#REF! -> #REF! | ... W13: =#REF! -> #REF! | X13: =D13+E13+F13+G13+H13+I13+J13+K13+L13+M13+N13+O13+P13+Q13+R13+S13+T13+U13+V13+W13 -> #REF! | Y13: =#REF! -> #REF! | Z13: =X13+Y13 -> #REF! | AC13: =D13+E13+F13+G13 -> #REF! | AD13: =H13+I13+J13+K13+L13 -> #REF! | AE13: =M13+N13+O13+P13+Q13+R13+S13+T13+U13+V13+W13 -> #REF! | AF13: =AC13+AD13+AE13 -> #REF! | AG13: =AF13-X13 -> #REF!
B14: 2007 | C14: 1 | D14: =#REF! -> #REF! | E14: =#REF! -> #REF! | F14: =#REF! -> #REF! | G14: =#REF! -> #REF! | H14: =#REF! -> #REF! | I14: =#REF! -> #REF! | J14: =#REF! -> #REF! | K14: =#REF! -> #REF! | ... W14: =#REF! -> #REF! | X14: =D14+E14+F14+G14+H14+I14+J14+K14+L14+M14+N14+O14+P14+Q14+R14+S14+T14+U14+V14+W14 -> #REF! | Y14: =#REF! -> #REF! | Z14: =X14+Y14 -> #REF! | AC14: =D14+E14+F14+G14 -> #REF! | AD14: =H14+I14+J14+K14+L14 -> #REF! | AE14: =M14+N14+O14+P14+Q14+R14+S14+T14+U14+V14+W14 -> #REF! | AF14: =AC14+AD14+AE14 -> #REF! | AG14: =AF14-X14 -> #REF!
C15: 2 | D15: =#REF! -> #REF! | E15: =#REF! -> #REF! | F15: =#REF! -> #REF! | G15: =#REF! -> #REF! | H15: =#REF! -> #REF! | I15: =#REF! -> #REF! | J15: =#REF! -> #REF! | K15: =#REF! -> #REF! | ... W15: =#REF! -> #REF! | X15: =D15+E15+F15+G15+H15+I15+J15+K15+L15+M15+N15+O15+P15+Q15+R15+S15+T15+U15+V15+W15 -> #REF! | Y15: =#REF! -> #REF! | Z15: =X15+Y15 -> #REF! | AC15: =D15+E15+F15+G15 -> #REF! | AD15: =H15+I15+J15+K15+L15 -> #REF! | AE15: =M15+N15+O15+P15+Q15+R15+S15+T15+U15+V15+W15 -> #REF! | AF15: =AC15+AD15+AE15 -> #REF! | AG15: =AF15-X15 -> #REF!
C16: 3 | D16: =#REF! -> #REF! | E16: =#REF! -> #REF! | F16: =#REF! -> #REF! | G16: =#REF! -> #REF! | H16: =#REF! -> #REF! | I16: =#REF! -> #REF! | J16: =#REF! -> #REF! | K16: =#REF! -> #REF! | ... W16: =#REF! -> #REF! | X16: =D16+E16+F16+G16+H16+I16+J16+K16+L16+M16+N16+O16+P16+Q16+R16+S16+T16+U16+V16+W16 -> #REF! | Y16: =#REF! -> #REF! | Z16: =X16+Y16 -> #REF! | AC16: =D16+E16+F16+G16 -> #REF! | AD16: =H16+I16+J16+K16+L16 -> #REF! | AE16: =M16+N16+O16+P16+Q16+R16+S16+T16+U16+V16+W16 -> #REF! | AF16: =AC16+AD16+AE16 -> #REF! | AG16: =AF16-X16 -> #REF!
C17: 4 | D17: =#REF! -> #REF! | E17: =#REF! -> #REF! | F17: =#REF! -> #REF! | G17: =#REF! -> #REF! | H17: =#REF! -> #REF! | I17: =#REF! -> #REF! | J17: =#REF! -> #REF! | K17: =#REF! -> #REF! | ... W17: =#REF! -> #REF! | X17: =D17+E17+F17+G17+H17+I17+J17+K17+L17+M17+N17+O17+P17+Q17+R17+S17+T17+U17+V17+W17 -> #REF! | Y17: =#REF! -> #REF! | Z17: =X17+Y17 -> #REF! | AC17: =D17+E17+F17+G17 -> #REF! | AD17: =H17+I17+J17+K17+L17 -> #REF! | AE17: =M17+N17+O17+P17+Q17+R17+S17+T17+U17+V17+W17 -> #REF! | AF17: =AC17+AD17+AE17 -> #REF! | AG17: =AF17-X17 -> #REF!
B18: 2008 | C18: 1 | D18: =#REF! -> #REF! | E18: =#REF! -> #REF! | F18: =#REF! -> #REF! | G18: =#REF! -> #REF! | H18: =#REF! -> #REF! | I18: =#REF! -> #REF! | J18: =#REF! -> #REF! | K18: =#REF! -> #REF! | ... W18: =#REF! -> #REF! | X18: =D18+E18+F18+G18+H18+I18+J18+K18+L18+M18+N18+O18+P18+Q18+R18+S18+T18+U18+V18+W18 -> #REF! | Y18: =#REF! -> #REF! | Z18: =X18+Y18 -> #REF! | AC18: =D18+E18+F18+G18 -> #REF! | AD18: =H18+I18+J18+K18+L18 -> #REF! | AE18: =M18+N18+O18+P18+Q18+R18+S18+T18+U18+V18+W18 -> #REF! | AF18: =AC18+AD18+AE18 -> #REF! | AG18: =AF18-X18 -> #REF!
C19: 2 | D19: =#REF! -> #REF! | E19: =#REF! -> #REF! | F19: =#REF! -> #REF! | G19: =#REF! -> #REF! | H19: =#REF! -> #REF! | I19: =#REF! -> #REF! | J19: =#REF! -> #REF! | K19: =#REF! -> #REF! | ... W19: =#REF! -> #REF! | X19: =D19+E19+F19+G19+H19+I19+J19+K19+L19+M19+N19+O19+P19+Q19+R19+S19+T19+U19+V19+W19 -> #REF! | Y19: =#REF! -> #REF! | Z19: =X19+Y19 -> #REF! | AC19: =D19+E19+F19+G19 -> #REF! | AD19: =H19+I19+J19+K19+L19 -> #REF! | AE19: =M19+N19+O19+P19+Q19+R19+S19+T19+U19+V19+W19 -> #REF! | AF19: =AC19+AD19+AE19 -> #REF! | AG19: =AF19-X19 -> #REF!
C20: 3 | D20: =#REF! -> #REF! | E20: =#REF! -> #REF! | F20: =#REF! -> #REF! | G20: =#REF! -> #REF! | H20: =#REF! -> #REF! | I20: =#REF! -> #REF! | J20: =#REF! -> #REF! | K20: =#REF! -> #REF! | ... W20: =#REF! -> #REF! | X20: =D20+E20+F20+G20+H20+I20+J20+K20+L20+M20+N20+O20+P20+Q20+R20+S20+T20+U20+V20+W20 -> #REF! | Y20: =#REF! -> #REF! | Z20: =X20+Y20 -> #REF! | AC20: =D20+E20+F20+G20 -> #REF! | AD20: =H20+I20+J20+K20+L20 -> #REF! | AE20: =M20+N20+O20+P20+Q20+R20+S20+T20+U20+V20+W20 -> #REF! | AF20: =AC20+AD20+AE20 -> #REF! | AG20: =AF20-X20 -> #REF!
C21: 4 | D21: =#REF! -> #REF! | E21: =#REF! -> #REF! | F21: =#REF! -> #REF! | G21: =#REF! -> #REF! | H21: =#REF! -> #REF! | I21: =#REF! -> #REF! | J21: =#REF! -> #REF! | K21: =#REF! -> #REF! | ... W21: =#REF! -> #REF! | X21: =D21+E21+F21+G21+H21+I21+J21+K21+L21+M21+N21+O21+P21+Q21+R21+S21+T21+U21+V21+W21 -> #REF! | Y21: =#REF! -> #REF! | Z21: =X21+Y21 -> #REF! | AC21: =D21+E21+F21+G21 -> #REF! | AD21: =H21+I21+J21+K21+L21 -> #REF! | AE21: =M21+N21+O21+P21+Q21+R21+S21+T21+U21+V21+W21 -> #REF! | AF21: =AC21+AD21+AE21 -> #REF! | AG21: =AF21-X21 -> #REF!
B22: 2009 | C22: 1 | D22: =#REF! -> #REF! | E22: =#REF! -> #REF! | F22: =#REF! -> #REF! | G22: =#REF! -> #REF! | H22: =#REF! -> #REF! | I22: =#REF! -> #REF! | J22: =#REF! -> #REF! | K22: =#REF! -> #REF! | ... W22: =#REF! -> #REF! | X22: =D22+E22+F22+G22+H22+I22+J22+K22+L22+M22+N22+O22+P22+Q22+R22+S22+T22+U22+V22+W22 -> #REF! | Y22: =#REF! -> #REF! | Z22: =X22+Y22 -> #REF! | AC22: =D22+E22+F22+G22 -> #REF! | AD22: =H22+I22+J22+K22+L22 -> #REF! | AE22: =M22+N22+O22+P22+Q22+R22+S22+T22+U22+V22+W22 -> #REF! | AF22: =AC22+AD22+AE22 -> #REF! | AG22: =AF22-X22 -> #REF!
C23: 2 | D23: =#REF! -> #REF! | E23: =#REF! -> #REF! | F23: =#REF! -> #REF! | G23: =#REF! -> #REF! | H23: =#REF! -> #REF! | I23: =#REF! -> #REF! | J23: =#REF! -> #REF! | K23: =#REF! -> #REF! | ... W23: =#REF! -> #REF! | X23: =D23+E23+F23+G23+H23+I23+J23+K23+L23+M23+N23+O23+P23+Q23+R23+S23+T23+U23+V23+W23 -> #REF! | Y23: =#REF! -> #REF! | Z23: =X23+Y23 -> #REF! | AC23: =D23+E23+F23+G23 -> #REF! | AD23: =H23+I23+J23+K23+L23 -> #REF! | AE23: =M23+N23+O23+P23+Q23+R23+S23+T23+U23+V23+W23 -> #REF! | AF23: =AC23+AD23+AE23 -> #REF! | AG23: =AF23-X23 -> #REF!
C24: 3 | D24: =#REF! -> #REF! | E24: =#REF! -> #REF! | F24: =#REF! -> #REF! | G24: =#REF! -> #REF! | H24: =#REF! -> #REF! | I24: =#REF! -> #REF! | J24: =#REF! -> #REF! | K24: =#REF! -> #REF! | ... W24: =#REF! -> #REF! | X24: =D24+E24+F24+G24+H24+I24+J24+K24+L24+M24+N24+O24+P24+Q24+R24+S24+T24+U24+V24+W24 -> #REF! | Y24: =#REF! -> #REF! | Z24: =X24+Y24 -> #REF! | AC24: =D24+E24+F24+G24 -> #REF! | AD24: =H24+I24+J24+K24+L24 -> #REF! | AE24: =M24+N24+O24+P24+Q24+R24+S24+T24+U24+V24+W24 -> #REF! | AF24: =AC24+AD24+AE24 -> #REF! | AG24: =AF24-X24 -> #REF!
C25: 4 | D25: =#REF! -> #REF! | E25: =#REF! -> #REF! | F25: =#REF! -> #REF! | G25: =#REF! -> #REF! | H25: =#REF! -> #REF! | I25: =#REF! -> #REF! | J25: =#REF! -> #REF! | K25: =#REF! -> #REF! | ... W25: =#REF! -> #REF! | X25: =D25+E25+F25+G25+H25+I25+J25+K25+L25+M25+N25+O25+P25+Q25+R25+S25+T25+U25+V25+W25 -> #REF! | Y25: =#REF! -> #REF! | Z25: =X25+Y25 -> #REF! | AC25: =D25+E25+F25+G25 -> #REF! | AD25: =H25+I25+J25+K25+L25 -> #REF! | AE25: =M25+N25+O25+P25+Q25+R25+S25+T25+U25+V25+W25 -> #REF! | AF25: =AC25+AD25+AE25 -> #REF! | AG25: =AF25-X25 -> #REF!
B26: 2010 | C26: 1 | D26: =#REF! -> #REF! | E26: =#REF! -> #REF! | F26: =#REF! -> #REF! | G26: =#REF! -> #REF! | H26: =#REF! -> #REF! | I26: =#REF! -> #REF! | J26: =#REF! -> #REF! | K26: =#REF! -> #REF! | ... W26: =#REF! -> #REF! | X26: =D26+E26+F26+G26+H26+I26+J26+K26+L26+M26+N26+O26+P26+Q26+R26+S26+T26+U26+V26+W26 -> #REF! | Y26: =#REF! -> #REF! | Z26: =X26+Y26 -> #REF! | AC26: =D26+E26+F26+G26 -> #REF! | AD26: =H26+I26+J26+K26+L26 -> #REF! | AE26: =M26+N26+O26+P26+Q26+R26+S26+T26+U26+V26+W26 -> #REF! | AF26: =AC26+AD26+AE26 -> #REF! | AG26: =AF26-X26 -> #REF!
C27: 2 | D27: =#REF! -> #REF! | E27: =#REF! -> #REF! | F27: =#REF! -> #REF! | G27: =#REF! -> #REF! | H27: =#REF! -> #REF! | I27: =#REF! -> #REF! | J27: =#REF! -> #REF! | K27: =#REF! -> #REF! | ... W27: =#REF! -> #REF! | X27: =D27+E27+F27+G27+H27+I27+J27+K27+L27+M27+N27+O27+P27+Q27+R27+S27+T27+U27+V27+W27 -> #REF! | Y27: =#REF! -> #REF! | Z27: =X27+Y27 -> #REF! | AC27: =D27+E27+F27+G27 -> #REF! | AD27: =H27+I27+J27+K27+L27 -> #REF! | AE27: =M27+N27+O27+P27+Q27+R27+S27+T27+U27+V27+W27 -> #REF! | AF27: =AC27+AD27+AE27 -> #REF! | AG27: =AF27-X27 -> #REF!
C28: 3 | D28: =#REF! -> #REF! | E28: =#REF! -> #REF! | F28: =#REF! -> #REF! | G28: =#REF! -> #REF! | H28: =#REF! -> #REF! | I28: =#REF! -> #REF! | J28: =#REF! -> #REF! | K28: =#REF! -> #REF! | ... W28: =#REF! -> #REF! | X28: =D28+E28+F28+G28+H28+I28+J28+K28+L28+M28+N28+O28+P28+Q28+R28+S28+T28+U28+V28+W28 -> #REF! | Y28: =#REF! -> #REF! | Z28: =X28+Y28 -> #REF! | AC28: =D28+E28+F28+G28 -> #REF! | AD28: =H28+I28+J28+K28+L28 -> #REF! | AE28: =M28+N28+O28+P28+Q28+R28+S28+T28+U28+V28+W28 -> #REF! | AF28: =AC28+AD28+AE28 -> #REF! | AG28: =AF28-X28 -> #REF!
C29: 4 | D29: =#REF! -> #REF! | E29: =#REF! -> #REF! | F29: =#REF! -> #REF! | G29: =#REF! -> #REF! | H29: =#REF! -> #REF! | I29: =#REF! -> #REF! | J29: =#REF! -> #REF! | K29: =#REF! -> #REF! | ... W29: =#REF! -> #REF! | X29: =D29+E29+F29+G29+H29+I29+J29+K29+L29+M29+N29+O29+P29+Q29+R29+S29+T29+U29+V29+W29 -> #REF! | Y29: =#REF! -> #REF! | Z29: =X29+Y29 -> #REF! | AC29: =D29+E29+F29+G29 -> #REF! | AD29: =H29+I29+J29+K29+L29 -> #REF! | AE29: =M29+N29+O29+P29+Q29+R29+S29+T29+U29+V29+W29 -> #REF! | AF29: =AC29+AD29+AE29 -> #REF! | AG29: =AF29-X29 -> #REF!
B30: 2011 | C30: 1 | D30: =#REF! -> #REF! | E30: =#REF! -> #REF! | F30: =#REF! -> #REF! | G30: =#REF! -> #REF! | H30: =#REF! -> #REF! | I30: =#REF! -> #REF! | J30: =#REF! -> #REF! | K30: =#REF! -> #REF! | ... W30: =#REF! -> #REF! | X30: =D30+E30+F30+G30+H30+I30+J30+K30+L30+M30+N30+O30+P30+Q30+R30+S30+T30+U30+V30+W30 -> #REF! | Y30: =#REF! -> #REF! | Z30: =X30+Y30 -> #REF! | AC30: =D30+E30+F30+G30 -> #REF! | AD30: =H30+I30+J30+K30+L30 -> #REF! | AE30: =M30+N30+O30+P30+Q30+R30+S30+T30+U30+V30+W30 -> #REF! | AF30: =AC30+AD30+AE30 -> #REF! | AG30: =AF30-X30 -> #REF!
C31: 2 | D31: =#REF! -> #REF! | E31: =#REF! -> #REF! | F31: =#REF! -> #REF! | G31: =#REF! -> #REF! | H31: =#REF! -> #REF! | I31: =#REF! -> #REF! | J31: =#REF! -> #REF! | K31: =#REF! -> #REF! | ... W31: =#REF! -> #REF! | X31: =D31+E31+F31+G31+H31+I31+J31+K31+L31+M31+N31+O31+P31+Q31+R31+S31+T31+U31+V31+W31 -> #REF! | Y31: =#REF! -> #REF! | Z31: =X31+Y31 -> #REF! | AC31: =D31+E31+F31+G31 -> #REF! | AD31: =H31+I31+J31+K31+L31 -> #REF! | AE31: =M31+N31+O31+P31+Q31+R31+S31+T31+U31+V31+W31 -> #REF! | AF31: =AC31+AD31+AE31 -> #REF! | AG31: =AF31-X31 -> #REF!
C32: 3* | D32: =#REF! -> #REF! | E32: =#REF! -> #REF! | F32: =#REF! -> #REF! | G32: =#REF! -> #REF! | H32: =#REF! -> #REF! | I32: =#REF! -> #REF! | J32: =#REF! -> #REF! | K32: =#REF! -> #REF! | ... W32: =#REF! -> #REF! | X32: =D32+E32+F32+G32+H32+I32+J32+K32+L32+M32+N32+O32+P32+Q32+R32+S32+T32+U32+V32+W32 -> #REF! | Y32: =#REF! -> #REF! | Z32: =X32+Y32 -> #REF! | AC32: =D32+E32+F32+G32 -> #REF! | AD32: =H32+I32+J32+K32+L32 -> #REF!
C33: 4* | D33: =#REF! -> #REF! | E33: =#REF! -> #REF! | F33: =#REF! -> #REF! | G33: =#REF! -> #REF! | H33: =#REF! -> #REF! | I33: =#REF! -> #REF! | J33: =#REF! -> #REF! | K33: =#REF! -> #REF! | ... W33: =#REF! -> #REF! | X33: =D33+E33+F33+G33+H33+I33+J33+K33+L33+M33+N33+O33+P33+Q33+R33+S33+T33+U33+V33+W33 -> #REF! | Y33: =#REF! -> #REF! | Z33: =X33+Y33 -> #REF!
B34: 2012 | C34: 1* | D34: =#REF! -> #REF! | E34: =#REF! -> #REF! | F34: =#REF! -> #REF! | G34: =#REF! -> #REF! | H34: =#REF! -> #REF! | I34: =#REF! -> #REF! | J34: =#REF! -> #REF! | K34: =#REF! -> #REF! | ... W34: =#REF! -> #REF! | X34: =D34+E34+F34+G34+H34+I34+J34+K34+L34+M34+N34+O34+P34+Q34+R34+S34+T34+U34+V34+W34 -> #REF! | Y34: =#REF! -> #REF! | Z34: =X34+Y34 -> #REF!
B36: * provisional

Sheet T2
B1: Table 2 - Percentage change (quarter-on-quarter) in the quarterly value added by Activity at 2006 constant prices
D2: Agriculture Sector | H2: Industry Sector | M2: Services Sector
B3: Year | C3: Quarter | D3: Crops & Cocoa | E3: Livestock | F3: Forestry | G3: Fishing | H3: Mining and Quarrying | I3: Manufacturing | J3: Electricity | K3: Water & Sewerage | L3: Construction | M3: Trade; Repair Of Vehicles, Household Goods | N3: Hotels And Restaurants | O3: Transport & Storage | P3: Information & Communication | Q3: Financial & Insurance Activities | R3: Real Estate Activities | S3: Business & other Services Activities | T3: Public Administration | U3: Education | V3: Health | W3: Other Personal Service Activities | X3: Total Value Added | Y3: Net Taxes | Z3: GDP at Constant Prices | AC3: Agric | AD3: Ind | AE3: Serv
B4: 2006
B5: 2007 | D5: ='T1'!D5/'T1'!D4*100-100 -> -1.346605 | E5: ='T1'!E5/'T1'!E4*100-100 -> 4.7316467 | F5: ='T1'!F5/'T1'!F4*100-100 -> -4.0926214 | G5: ='T1'!G5/'T1'!G4*100-100 -> -7.2472487 | H5: ='T1'!H5/'T1'!H4*100-100 -> 6.8620818 | I5: ='T1'!I5/'T1'!I4*100-100 -> -1.2158585 | J5: ='T1'!J5/'T1'!J4*100-100 -> -17.212572 | K5: ='T1'!K5/'T1'!K4*100-100 -> 1.161077 | ... Z5: ='T1'!Z5/'T1'!Z4*100-100 -> 6.459768
B6: 2008 | D6: ='T1'!D6/'T1'!D5*100-100 -> 8.6 | E6: ='T1'!E6/'T1'!E5*100-100 -> 5.1039655 | F6: ='T1'!F6/'T1'!F5*100-100 -> -3.3201314 | G6: ='T1'!G6/'T1'!G5*100-100 -> 17.380777 | H6: ='T1'!H6/'T1'!H5*100-100 -> 2.4193735 | I6: ='T1'!I6/'T1'!I5*100-100 -> 3.7004754 | J6: ='T1'!J6/'T1'!J5*100-100 -> 19.423493 | K6: ='T1'!K6/'T1'!K5*100-100 -> 0.84657122 | ... Z6: ='T1'!Z6/'T1'!Z5*100-100 -> 8.430638
B7: 2009 | D7: ='T1'!D7/'T1'!D6*100-100 -> 10.209647 | E7: ='T1'!E7/'T1'!E6*100-100 -> 4.3665196 | F7: ='T1'!F7/'T1'!F6*100-100 -> 0.72021485 | G7: ='T1'!G7/'T1'!G6*100-100 -> -5.711463 | H7: ='T1'!H7/'T1'!H6*100-100 -> 6.751655 | I7: ='T1'!I7/'T1'!I6*100-100 -> -1.3056694 | J7: ='T1'!J7/'T1'!J6*100-100 -> 7.5043898 | K7: ='T1'!K7/'T1'!K6*100-100 -> 7.6501012 | ... Z7: ='T1'!Z7/'T1'!Z6*100-100 -> 3.9936182
B8: 2010 | D8: ='T1'!D8/'T1'!D7*100-100 -> 5.0000539 | E8: ='T1'!E8/'T1'!E7*100-100 -> 4.6493195 | F8: ='T1'!F8/'T1'!F7*100-100 -> 10.071289 | G8: ='T1'!G8/'T1'!G7*100-100 -> 1.4907404 | H8: ='T1'!H8/'T1'!H7*100-100 -> 7.642783 | I8: ='T1'!I8/'T1'!I7*100-100 -> 7.6004356 | J8: ='T1'!J8/'T1'!J7*100-100 -> 12.260229 | K8: ='T1'!K8/'T1'!K7*100-100 -> 5.2637697 | ... Z8: ='T1'!Z8/'T1'!Z7*100-100 -> 7.7171007
B10: 2006 | C10: 1 | AC10: =D10+E10+F10+G10 -> 0 | AD10: =H10+I10+J10+K10+L10 -> 0 | AE10: =M10+N10+O10+P10+Q10+R10+S10+T10+U10+V10+W10 -> 0
C11: 2 | D11: ='qly growth rates'!C6 -> #REF! | E11: ='qly growth rates'!D6 -> #REF! | F11: ='qly growth rates'!E6 -> #REF! | G11: ='qly growth rates'!F6 -> #REF! | H11: ='qly growth rates'!G6 -> #REF! | I11: ='qly growth rates'!H6 -> #REF! | J11: ='qly growth rates'!I6 -> #REF! | K11: ='qly growth rates'!J6 -> #REF! | ... Z11: ='qly growth rates'!Y6 -> #REF! | AC11: ='T1'!AC11/'T1'!AC10*100-100 -> #REF! | AD11: ='T1'!AD11/'T1'!AD10*100-100 -> #REF! | AE11: ='T1'!AE11/'T1'!AE10*100-100 -> #REF!
C12: 3 | D12: ='qly growth rates'!C7 -> #REF! | E12: ='qly growth rates'!D7 -> #REF! | F12: ='qly growth rates'!E7 -> #REF! | G12: ='qly growth rates'!F7 -> #REF! | H12: ='qly growth rates'!G7 -> #REF! | I12: ='qly growth rates'!H7 -> #REF! | J12: ='qly growth rates'!I7 -> #REF! | K12: ='qly growth rates'!J7 -> #REF! | ... Z12: ='qly growth rates'!Y7 -> #REF! | AC12: ='T1'!AC12/'T1'!AC11*100-100 -> #REF! | AD12: ='T1'!AD12/'T1'!AD11*100-100 -> #REF! | AE12: ='T1'!AE12/'T1'!AE11*100-100 -> #REF!
C13: 4 | D13: ='qly growth rates'!C8 -> #REF! | E13: ='qly growth rates'!D8 -> #REF! | F13: ='qly growth rates'!E8 -> #REF! | G13: ='qly growth rates'!F8 -> #REF! | H13: ='qly growth rates'!G8 -> #REF! | I13: ='qly growth rates'!H8 -> #REF! | J13: ='qly growth rates'!I8 -> #REF! | K13: ='qly growth rates'!J8 -> #REF! | ... Z13: ='qly growth rates'!Y8 -> #REF! | AC13: ='T1'!AC13/'T1'!AC12*100-100 -> #REF! | AD13: ='T1'!AD13/'T1'!AD12*100-100 -> #REF! | AE13: ='T1'!AE13/'T1'!AE12*100-100 -> #REF!
B14: 2007 | C14: 1 | D14: ='qly growth rates'!C9 -> #REF! | E14: ='qly growth rates'!D9 -> #REF! | F14: ='qly growth rates'!E9 -> #REF! | G14: ='qly growth rates'!F9 -> #REF! | H14: ='qly growth rates'!G9 -> #REF! | I14: ='qly growth rates'!H9 -> #REF! | J14: ='qly growth rates'!I9 -> #REF! | K14: ='qly growth rates'!J9 -> #REF! | ... Z14: ='qly growth rates'!Y9 -> #REF! | AC14: ='T1'!AC14/'T1'!AC13*100-100 -> #REF! | AD14: ='T1'!AD14/'T1'!AD13*100-100 -> #REF! | AE14: ='T1'!AE14/'T1'!AE13*100-100 -> #REF!
C15: 2 | D15: ='qly growth rates'!C10 -> #REF! | E15: ='qly growth rates'!D10 -> #REF! | F15: ='qly growth rates'!E10 -> #REF! | G15: ='qly growth rates'!F10 -> #REF! | H15: ='qly growth rates'!G10 -> #REF! | I15: ='qly growth rates'!H10 -> #REF! | J15: ='qly growth rates'!I10 -> #REF! | K15: ='qly growth rates'!J10 -> #REF! | ... Z15: ='qly growth rates'!Y10 -> #REF! | AC15: ='T1'!AC15/'T1'!AC14*100-100 -> #REF! | AD15: ='T1'!AD15/'T1'!AD14*100-100 -> #REF! | AE15: ='T1'!AE15/'T1'!AE14*100-100 -> #REF!
C16: 3 | D16: ='qly growth rates'!C11 -> #REF! | E16: ='qly growth rates'!D11 -> #REF! | F16: ='qly growth rates'!E11 -> #REF! | G16: ='qly growth rates'!F11 -> #REF! | H16: ='qly growth rates'!G11 -> #REF! | I16: ='qly growth rates'!H11 -> #REF! | J16: ='qly growth rates'!I11 -> #REF! | K16: ='qly growth rates'!J11 -> #REF! | ... Z16: ='qly growth rates'!Y11 -> #REF! | AC16: ='T1'!AC16/'T1'!AC15*100-100 -> #REF! | AD16: ='T1'!AD16/'T1'!AD15*100-100 -> #REF! | AE16: ='T1'!AE16/'T1'!AE15*100-100 -> #REF!
C17: 4 | D17: ='qly growth rates'!C12 -> #REF! | E17: ='qly growth rates'!D12 -> #REF! | F17: ='qly growth rates'!E12 -> #REF! | G17: ='qly growth rates'!F12 -> #REF! | H17: ='qly growth rates'!G12 -> #REF! | I17: ='qly growth rates'!H12 -> #REF! | J17: ='qly growth rates'!I12 -> #REF! | K17: ='qly growth rates'!J12 -> #REF! | ... Z17: ='qly growth rates'!Y12 -> #REF! | AC17: ='T1'!AC17/'T1'!AC16*100-100 -> #REF! | AD17: ='T1'!AD17/'T1'!AD16*100-100 -> #REF! | AE17: ='T1'!AE17/'T1'!AE16*100-100 -> #REF!
B18: 2008 | C18: 1 | D18: ='qly growth rates'!C13 -> #REF! | E18: ='qly growth rates'!D13 -> #REF! | F18: ='qly growth rates'!E13 -> #REF! | G18: ='qly growth rates'!F13 -> #REF! | H18: ='qly growth rates'!G13 -> #REF! | I18: ='qly growth rates'!H13 -> #REF! | J18: ='qly growth rates'!I13 -> #REF! | K18: ='qly growth rates'!J13 -> #REF! | ... Z18: ='qly growth rates'!Y13 -> #REF! | AC18: ='T1'!AC18/'T1'!AC17*100-100 -> #REF! | AD18: ='T1'!AD18/'T1'!AD17*100-100 -> #REF! | AE18: ='T1'!AE18/'T1'!AE17*100-100 -> #REF!
C19: 2 | D19: ='qly growth rates'!C14 -> #REF! | E19: ='qly growth rates'!D14 -> #REF! | F19: ='qly growth rates'!E14 -> #REF! | G19: ='qly growth rates'!F14 -> #REF! | H19: ='qly growth rates'!G14 -> #REF! | I19: ='qly growth rates'!H14 -> #REF! | J19: ='qly growth rates'!I14 -> #REF! | K19: ='qly growth rates'!J14 -> #REF! | ... Z19: ='qly growth rates'!Y14 -> #REF! | AC19: ='T1'!AC19/'T1'!AC18*100-100 -> #REF! | AD19: ='T1'!AD19/'T1'!AD18*100-100 -> #REF! | AE19: ='T1'!AE19/'T1'!AE18*100-100 -> #REF!
C20: 3 | D20: ='qly growth rates'!C15 -> #REF! | E20: ='qly growth rates'!D15 -> #REF! | F20: ='qly growth rates'!E15 -> #REF! | G20: ='qly growth rates'!F15 -> #REF! | H20: ='qly growth rates'!G15 -> #REF! | I20: ='qly growth rates'!H15 -> #REF! | J20: ='qly growth rates'!I15 -> #REF! | K20: ='qly growth rates'!J15 -> #REF! | ... Z20: ='qly growth rates'!Y15 -> #REF! | AC20: ='T1'!AC20/'T1'!AC19*100-100 -> #REF! | AD20: ='T1'!AD20/'T1'!AD19*100-100 -> #REF! | AE20: ='T1'!AE20/'T1'!AE19*100-100 -> #REF!
C21: 4 | D21: ='qly growth rates'!C16 -> #REF! | E21: ='qly growth rates'!D16 -> #REF! | F21: ='qly growth rates'!E16 -> #REF! | G21: ='qly growth rates'!F16 -> #REF! | H21: ='qly growth rates'!G16 -> #REF! | I21: ='qly growth rates'!H16 -> #REF! | J21: ='qly growth rates'!I16 -> #REF! | K21: ='qly growth rates'!J16 -> #REF! | ... Z21: ='qly growth rates'!Y16 -> #REF! | AC21: ='T1'!AC21/'T1'!AC20*100-100 -> #REF! | AD21: ='T1'!AD21/'T1'!AD20*100-100 -> #REF! | AE21: ='T1'!AE21/'T1'!AE20*100-100 -> #REF!
B22: 2009 | C22: 1 | D22: ='qly growth rates'!C17 -> #REF! | E22: ='qly growth rates'!D17 -> #REF! | F22: ='qly growth rates'!E17 -> #REF! | G22: ='qly growth rates'!F17 -> #REF! | H22: ='qly growth rates'!G17 -> #REF! | I22: ='qly growth rates'!H17 -> #REF! | J22: ='qly growth rates'!I17 -> #REF! | K22: ='qly growth rates'!J17 -> #REF! | ... Z22: ='qly growth rates'!Y17 -> #REF! | AC22: ='T1'!AC22/'T1'!AC21*100-100 -> #REF! | AD22: ='T1'!AD22/'T1'!AD21*100-100 -> #REF! | AE22: ='T1'!AE22/'T1'!AE21*100-100 -> #REF!
C23: 2 | D23: ='qly growth rates'!C18 -> #REF! | E23: ='qly growth rates'!D18 -> #REF! | F23: ='qly growth rates'!E18 -> #REF! | G23: ='qly growth rates'!F18 -> #REF! | H23: ='qly growth rates'!G18 -> #REF! | I23: ='qly growth rates'!H18 -> #REF! | J23: ='qly growth rates'!I18 -> #REF! | K23: ='qly growth rates'!J18 -> #REF! | ... Z23: ='qly growth rates'!Y18 -> #REF! | AC23: ='T1'!AC23/'T1'!AC22*100-100 -> #REF! | AD23: ='T1'!AD23/'T1'!AD22*100-100 -> #REF! | AE23: ='T1'!AE23/'T1'!AE22*100-100 -> #REF!
C24: 3 | D24: ='qly growth rates'!C19 -> #REF! | E24: ='qly growth rates'!D19 -> #REF! | F24: ='qly growth rates'!E19 -> #REF! | G24: ='qly growth rates'!F19 -> #REF! | H24: ='qly growth rates'!G19 -> #REF! | I24: ='qly growth rates'!H19 -> #REF! | J24: ='qly growth rates'!I19 -> #REF! | K24: ='qly growth rates'!J19 -> #REF! | ... Z24: ='qly growth rates'!Y19 -> #REF! | AC24: ='T1'!AC24/'T1'!AC23*100-100 -> #REF! | AD24: ='T1'!AD24/'T1'!AD23*100-100 -> #REF! | AE24: ='T1'!AE24/'T1'!AE23*100-100 -> #REF!
C25: 4 | D25: ='qly growth rates'!C20 -> #REF! | E25: ='qly growth rates'!D20 -> #REF! | F25: ='qly growth rates'!E20 -> #REF! | G25: ='qly growth rates'!F20 -> #REF! | H25: ='qly growth rates'!G20 -> #REF! | I25: ='qly growth rates'!H20 -> #REF! | J25: ='qly growth rates'!I20 -> #REF! | K25: ='qly growth rates'!J20 -> #REF! | ... Z25: ='qly growth rates'!Y20 -> #REF! | AC25: ='T1'!AC25/'T1'!AC24*100-100 -> #REF! | AD25: ='T1'!AD25/'T1'!AD24*100-100 -> #REF! | AE25: ='T1'!AE25/'T1'!AE24*100-100 -> #REF!
B26: 2010 | C26: 1 | D26: ='qly growth rates'!C21 -> #REF! | E26: ='qly growth rates'!D21 -> #REF! | F26: ='qly growth rates'!E21 -> #REF! | G26: ='qly growth rates'!F21 -> #REF! | H26: ='qly growth rates'!G21 -> #REF! | I26: ='qly growth rates'!H21 -> #REF! | J26: ='qly growth rates'!I21 -> #REF! | K26: ='qly growth rates'!J21 -> #REF! | ... Z26: ='qly growth rates'!Y21 -> #REF! | AC26: ='T1'!AC26/'T1'!AC25*100-100 -> #REF! | AD26: ='T1'!AD26/'T1'!AD25*100-100 -> #REF! | AE26: ='T1'!AE26/'T1'!AE25*100-100 -> #REF!
C27: 2 | D27: ='qly growth rates'!C22 -> #REF! | E27: ='qly growth rates'!D22 -> #REF! | F27: ='qly growth rates'!E22 -> #REF! | G27: ='qly growth rates'!F22 -> #REF! | H27: ='qly growth rates'!G22 -> #REF! | I27: ='qly growth rates'!H22 -> #REF! | J27: ='qly growth rates'!I22 -> #REF! | K27: ='qly growth rates'!J22 -> #REF! | ... Z27: ='qly growth rates'!Y22 -> #REF! | AC27: ='T1'!AC27/'T1'!AC26*100-100 -> #REF! | AD27: ='T1'!AD27/'T1'!AD26*100-100 -> #REF! | AE27: ='T1'!AE27/'T1'!AE26*100-100 -> #REF!
C28: 3 | D28: ='qly growth rates'!C23 -> #REF! | E28: ='qly growth rates'!D23 -> #REF! | F28: ='qly growth rates'!E23 -> #REF! | G28: ='qly growth rates'!F23 -> #REF! | H28: ='qly growth rates'!G23 -> #REF! | I28: ='qly growth rates'!H23 -> #REF! | J28: ='qly growth rates'!I23 -> #REF! | K28: ='qly growth rates'!J23 -> #REF! | ... Z28: ='qly growth rates'!Y23 -> #REF! | AC28: ='T1'!AC28/'T1'!AC27*100-100 -> #REF! | AD28: ='T1'!AD28/'T1'!AD27*100-100 -> #REF! | AE28: ='T1'!AE28/'T1'!AE27*100-100 -> #REF!
C29: 4 | D29: ='qly growth rates'!C24 -> #REF! | E29: ='qly growth rates'!D24 -> #REF! | F29: ='qly growth rates'!E24 -> #REF! | G29: ='qly growth rates'!F24 -> #REF! | H29: ='qly growth rates'!G24 -> #REF! | I29: ='qly growth rates'!H24 -> #REF! | J29: ='qly growth rates'!I24 -> #REF! | K29: ='qly growth rates'!J24 -> #REF! | ... Z29: ='qly growth rates'!Y24 -> #REF! | AC29: ='T1'!AC29/'T1'!AC28*100-100 -> #REF! | AD29: ='T1'!AD29/'T1'!AD28*100-100 -> #REF! | AE29: ='T1'!AE29/'T1'!AE28*100-100 -> #REF!
B30: 2011 | C30: 1 | D30: ='qly growth rates'!C25 -> #REF! | E30: ='qly growth rates'!D25 -> #REF! | F30: ='qly growth rates'!E25 -> #REF! | G30: ='qly growth rates'!F25 -> #REF! | H30: ='qly growth rates'!G25 -> #REF! | I30: ='qly growth rates'!H25 -> #REF! | J30: ='qly growth rates'!I25 -> #REF! | K30: ='qly growth rates'!J25 -> #REF! | ... Z30: ='qly growth rates'!Y25 -> #REF! | AC30: ='T1'!AC30/'T1'!AC29*100-100 -> #REF! | AD30: ='T1'!AD30/'T1'!AD29*100-100 -> #REF! | AE30: ='T1'!AE30/'T1'!AE29*100-100 -> #REF!
C31: 2 | D31: ='qly growth rates'!C26 -> #REF! | E31: ='qly growth rates'!D26 -> #REF! | F31: ='qly growth rates'!E26 -> #REF! | G31: ='qly growth rates'!F26 -> #REF! | H31: ='qly growth rates'!G26 -> #REF! | I31: ='qly growth rates'!H26 -> #REF! | J31: ='qly growth rates'!I26 -> #REF! | K31: ='qly growth rates'!J26 -> #REF! | ... Z31: ='qly growth rates'!Y26 -> #REF! | AC31: ='T1'!AC31/'T1'!AC30*100-100 -> #REF! | AD31: ='T1'!AD31/'T1'!AD30*100-100 -> #REF! | AE31: ='T1'!AE31/'T1'!AE30*100-100 -> #REF!
C32: 3* | D32: ='qly growth rates'!C27 -> #REF! | E32: ='qly growth rates'!D27 -> #REF! | F32: ='qly growth rates'!E27 -> #REF! | G32: ='qly growth rates'!F27 -> #REF! | H32: ='qly growth rates'!G27 -> #REF! | I32: ='qly growth rates'!H27 -> #REF! | J32: ='qly growth rates'!I27 -> #REF! | K32: ='qly growth rates'!J27 -> #REF! | ... Z32: ='qly growth rates'!Y27 -> #REF! | AC32: ='T1'!AC32/'T1'!AC31*100-100 -> #REF! | AD32: ='T1'!AD32/'T1'!AD31*100-100 -> #REF! | AE32: ='T1'!AE32/'T1'!AE31*100-100 -> #REF!
C33: 4* | D33: ='qly growth rates'!C28 -> 0 | E33: ='qly growth rates'!D28 -> 0 | F33: ='qly growth rates'!E28 -> 0 | G33: ='qly growth rates'!F28 -> 0 | H33: ='qly growth rates'!G28 -> 0 | I33: ='qly growth rates'!H28 -> 0 | J33: ='qly growth rates'!I28 -> 0 | K33: ='qly growth rates'!J28 -> 0 | ... Z33: ='qly growth rates'!Y28 -> 0 | AC33: ='T1'!AC33/'T1'!AC32*100-100 -> #REF! | AD33: ='T1'!AD33/'T1'!AD32*100-100 -> #REF! | AE33: ='T1'!AE33/'T1'!AE32*100-100 -> #DIV/0!
B34: 2012 | C34: 1* | D34: ='qly growth rates'!C29 -> 0 | E34: ='qly growth rates'!D29 -> 0 | F34: ='qly growth rates'!E29 -> 0 | G34: ='qly growth rates'!F29 -> 0 | H34: ='qly growth rates'!G29 -> 0 | I34: ='qly growth rates'!H29 -> 0 | J34: ='qly growth rates'!I29 -> 0 | K34: ='qly growth rates'!J29 -> 0 | ... Z34: ='qly growth rates'!Y29 -> 0
B36: * provisional

Sheet T1 (2)
B1: Table 1 - Quarterly Value Added by Activity and Gross Domestic Product at Constant 2006 Prices (GHc Million)
D2: Agriculture Sector | I2: Industry Sector | O2: Services Sector | AA2: Total Value Added at Basis Prices
B3: Year | C3: Quarter | D3: Crops & Cocoa | E3: Livestock | F3: Forestry | G3: Fishing | H3: Total Value Added | I3: Mining and Quarrying | J3: Manufacturing | K3: Electricity | L3: Water & Sewerage | M3: Construction | N3: Total Value Added | O3: Trade; Repair Of Vehicles, Household Goods | P3: Hotels And Restaurants | Q3: Transport & Storage | R3: Information & Communication | S3: Financial & Insurance Activities | T3: Real Estate Activities | U3: Business & other Services Activities | V3: Public Administration | W3: Education | X3: Health | Y3: Other Personal Service Activities | Z3: Total Value Added
D4: 1 | E4: 2 | F4: 3 | G4: 4 | H4: 5=1+2+3+4 | I4: 6 | J4: 7 | K4: 8 | L4: 9 | M4: 10 | N4: 11=6+...+10 | O4: 11 | P4: 12 | Q4: 13 | R4: 14 | S4: 15 | T4: 16 | U4: 17 | V4: 18 | W4: 19 | X4: 20 | Y4: 21 | Z4: 22=11+...21 | AA4: 23=5+11+23
AG5: =D3 -> Crops & Cocoa | AH5: =E3 -> Livestock | AI5: =F3 -> Forestry | AJ5: =G3 -> Fishing | AL5: =I3 -> Mining and Quarrying | AM5: =J3 -> Manufacturing | AN5: =K3 -> Electricity | AO5: =L3 -> Water & Sewerage | AP5: =M3 -> Construction | AR5: =O3 -> Trade; Repair Of Vehicles, Household Goods | AS5: =P3 -> Hotels And Restaurants | AT5: =Q3 -> Transport & Storage | AU5: =R3 -> Information & Communication | AV5: =S3 -> Financial & Insurance Activities | AW5: =T3 -> Real Estate Activities | AX5: =U3 -> Business & other Services Activities | AY5: =V3 -> Public Administration | ... BB5: =Y3 -> Other Personal Service Activities
B6: 2006 | D6: 3793.682 | E6: 437.09725 | F6: 736.00309 | G6: 448.25153 | H6: =SUM(D6:G6) -> 5415.0338 | I6: 497.4452 | J6: 1823.4833 | K6: 142.71912 | L6: 224.36136 | M6: 1016.2744 | N6: =SUM(I6:M6) -> 3704.2834 | O6: 1140.6992 | P6: 894.08203 | Q6: 2357.2217 | R6: 483.03723 | S6: 472.8561 | T6: 391.4 | U6: 522.52707 | V6: 862.13807 | W6: 654.95995 | X6: 249.83921 | Y6: 661.61553 | Z6: =SUM(O6:Y6) -> 8690.3761 | AA6: =D6+E6+F6+G6+I6+J6+K6+L6+M6+O6+P6+Q6+R6+S6+T6+U6+V6+W6+X6+Y6 -> 17809.693 | AF6: 06q1 | AG6: =D12 -> #REF! | AH6: =E12 -> #REF! | AI6: =F12 -> #REF! | AJ6: =G12 -> #REF! | AL6: =I12 -> #REF! | AM6: =J12 -> #REF! | AN6: =K12 -> #REF! | AO6: =L12 -> #REF! | AP6: =M12 -> #REF! | AR6: =O12 -> #REF! | AS6: =P12 -> #REF! | AT6: =Q12 -> #REF! | AU6: =R12 -> #REF! | AV6: =S12 -> #REF! | AW6: =T12 -> #REF! | AX6: =U12 -> #REF! | AY6: =V12 -> #REF! | ... BB6: =Y12 -> #REF!
B7: 2007 | D7: 3742.596 | E7: 457.77915 | F7: 705.88127 | G7: 415.76563 | H7: =SUM(D7:G7) -> 5322.0221 | I7: 531.5803 | J7: 1801.3123 | K7: 118.15348 | L7: 226.96637 | M7: 1251.5619 | N7: =SUM(I7:M7) -> 3929.5743 | O7: 1202.6217 | P7: 916.59233 | Q7: 2573.4037 | R7: 502.84176 | S7: 559.76897 | T7: 400.7936 | U7: 542.72237 | V7: 959.55967 | W7: 720.45595 | X7: 259.27272 | Y7: 720.31678 | Z7: =SUM(O7:Y7) -> 9358.3495 | AA7: =D7+E7+F7+G7+I7+J7+K7+L7+M7+O7+P7+Q7+R7+S7+T7+U7+V7+W7+X7+Y7 -> 18609.946 | AF7: 06q2 | AG7: =D13 -> #REF! | AH7: =E13 -> #REF! | AI7: =F13 -> #REF! | AJ7: =G13 -> #REF! | AL7: =I13 -> #REF! | AM7: =J13 -> #REF! | AN7: =K13 -> #REF! | AO7: =L13 -> #REF! | AP7: =M13 -> #REF! | AR7: =O13 -> #REF! | AS7: =P13 -> #REF! | AT7: =Q13 -> #REF! | AU7: =R13 -> #REF! | AV7: =S13 -> #REF! | AW7: =T13 -> #REF! | AX7: =U13 -> #REF! | AY7: =V13 -> #REF! | ... BB7: =Y13 -> #REF!
B8: 2008 | D8: 4064.4593 | E8: 481.14404 | F8: 682.44508 | G8: 488.02892 | H8: =SUM(D8:G8) -> 5716.0774 | I8: 544.44121 | J8: 1867.9694 | K8: 141.10302 | L8: 228.8878 | M8: 1739.4644 | N8: =SUM(I8:M8) -> 4521.8658 | O8: 1316.9257 | P8: 999.77813 | Q8: 2671.91 | R8: 600.8959 | S8: 620.12127 | T8: 410.41265 | U8: 532.78696 | V8: 1081.751 | W8: 814.29858 | X8: 270.78237 | Y8: 786.30765 | Z8: =SUM(O8:Y8) -> 10105.97 | AA8: =D8+E8+F8+G8+I8+J8+K8+L8+M8+O8+P8+Q8+R8+S8+T8+U8+V8+W8+X8+Y8 -> 20343.913 | AF8: 06q3 | AG8: =D14 -> #REF! | AH8: =E14 -> #REF! | AI8: =F14 -> #REF! | AJ8: =G14 -> #REF! | AL8: =I14 -> #REF! | AM8: =J14 -> #REF! | AN8: =K14 -> #REF! | AO8: =L14 -> #REF! | AP8: =M14 -> #REF! | AR8: =O14 -> #REF! | AS8: =P14 -> #REF! | AT8: =Q14 -> #REF! | AU8: =R14 -> #REF! | AV8: =S14 -> #REF! | AW8: =T14 -> #REF! | AX8: =U14 -> #REF! | AY8: =V14 -> #REF! | ... BB8: =Y14 -> #REF!
B9: 2009 | D9: 4479.4263 | E9: 502.15329 | F9: 687.36015 | G9: 460.15533 | H9: =SUM(D9:G9) -> 6129.095 | I9: 581.2 | J9: 1843.5799 | K9: 151.69194 | L9: 246.39795 | M9: 1901.8527 | N9: =SUM(I9:M9) -> 4724.7225 | O9: 1387.931 | P9: 962.00084 | Q9: 2790.1363 | R9: 624.16472 | S9: 677.93817 | T9: 420.26255 | U9: 524.52844 | V9: 1208.1799 | W9: 914.89016 | X9: 311.81225 | Y9: 845.05032 | Z9: =SUM(O9:Y9) -> 10666.895 | AA9: =D9+E9+F9+G9+I9+J9+K9+L9+M9+O9+P9+Q9+R9+S9+T9+U9+V9+W9+X9+Y9 -> 21520.712 | AF9: 06q4 | AG9: =D15 -> #REF! | AH9: =E15 -> #REF! | AI9: =F15 -> #REF! | AJ9: =G15 -> #REF! | AL9: =I15 -> #REF! | AM9: =J15 -> #REF! | AN9: =K15 -> #REF! | AO9: =L15 -> #REF! | AP9: =M15 -> #REF! | AR9: =O15 -> #REF! | AS9: =P15 -> #REF! | AT9: =Q15 -> #REF! | AU9: =R15 -> #REF! | AV9: =S15 -> #REF! | AW9: =T15 -> #REF! | AX9: =U15 -> #REF! | AY9: =V15 -> #REF! | ... BB9: =Y15 -> #REF!
B10: 2010 | D10: 4703.4 | E10: 525.5 | F10: 756.58618 | G10: 467.01505 | H10: =SUM(D10:G10) -> 6452.5012 | I10: 625.61986 | J10: 1983.7 | K10: 170.28972 | L10: 259.36777 | M10: 1949.3991 | N10: =SUM(I10:M10) -> 4988.3764 | O10: 1573.0945 | P10: 987.85721 | Q10: 3014.308 | R10: 776.90602 | S10: 791.49056 | T10: 430.34885 | U10: 645.7 | V10: 1248.9614 | W10: 963.21808 | X10: 346.86159 | Y10: 935.5 | Z10: =SUM(O10:Y10) -> 11714.246 | AA10: =D10+E10+F10+G10+I10+J10+K10+L10+M10+O10+P10+Q10+R10+S10+T10+U10+V10+W10+X10+Y10 -> 23155.124 | AF10: 07q1 | AG10: =D16 -> #REF! | AH10: =E16 -> #REF! | AI10: =F16 -> #REF! | AJ10: =G16 -> #REF! | AL10: =I16 -> #REF! | AM10: =J16 -> #REF! | AN10: =K16 -> #REF! | AO10: =L16 -> #REF! | AP10: =M16 -> #REF! | AR10: =O16 -> #REF! | AS10: =P16 -> #REF! | AT10: =Q16 -> #REF! | AU10: =R16 -> #REF! | AV10: =S16 -> #REF! | AW10: =T16 -> #REF! | AX10: =U16 -> #REF! | AY10: =V16 -> #REF! | ... BB10: =Y16 -> #REF!
B11: 2011 | H11: =SUM(D11:G11) -> 0 | N11: =SUM(I11:M11) -> 0 | Z11: =SUM(O11:Y11) -> 0 | AA11: =D11+E11+F11+G11+I11+J11+K11+L11+M11+O11+P11+Q11+R11+S11+T11+U11+V11+W11+X11+Y11 -> 0 | AF11: 07q2 | AG11: =D17 -> #REF! | AH11: =E17 -> #REF! | AI11: =F17 -> #REF! | AJ11: =G17 -> #REF! | AL11: =I17 -> #REF! | AM11: =J17 -> #REF! | AN11: =K17 -> #REF! | AO11: =L17 -> #REF! | AP11: =M17 -> #REF! | AR11: =O17 -> #REF! | AS11: =P17 -> #REF! | AT11: =Q17 -> #REF! | AU11: =R17 -> #REF! | AV11: =S17 -> #REF! | AW11: =T17 -> #REF! | AX11: =U17 -> #REF! | AY11: =V17 -> #REF! | ... BB11: =Y17 -> #REF!
B12: 2006 | C12: Q1 | D12: =#REF! -> #REF! | E12: =#REF! -> #REF! | F12: =#REF! -> #REF! | G12: =#REF! -> #REF! | H12: =SUM(D12:G12) -> #REF! | I12: =#REF! -> #REF! | J12: =#REF! -> #REF! | K12: =#REF! -> #REF! | L12: =#REF! -> #REF! | M12: =#REF! -> #REF! | N12: =SUM(I12:M12) -> #REF! | O12: =#REF! -> #REF! | P12: =#REF! -> #REF! | Q12: =#REF! -> #REF! | R12: =#REF! -> #REF! | S12: =#REF! -> #REF! | T12: =#REF! -> #REF! | U12: =#REF! -> #REF! | V12: =#REF! -> #REF! | ... Y12: =#REF! -> #REF! | Z12: =SUM(O12:Y12) -> #REF! | AA12: =D12+E12+F12+G12+I12+J12+K12+L12+M12+O12+P12+Q12+R12+S12+T12+U12+V12+W12+X12+Y12 -> #REF! | AF12: 07q3 | AG12: =D18 -> #REF! | AH12: =E18 -> #REF! | AI12: =F18 -> #REF! | AJ12: =G18 -> #REF! | AL12: =I18 -> #REF! | AM12: =J18 -> #REF! | AN12: =K18 -> #REF! | AO12: =L18 -> #REF! | AP12: =M18 -> #REF! | AR12: =O18 -> #REF! | AS12: =P18 -> #REF! | AT12: =Q18 -> #REF! | AU12: =R18 -> #REF! | AV12: =S18 -> #REF! | AW12: =T18 -> #REF! | AX12: =U18 -> #REF! | AY12: =V18 -> #REF! | ... BB12: =Y18 -> #REF!
C13: Q2 | D13: =#REF! -> #REF! | E13: =#REF! -> #REF! | F13: =#REF! -> #REF! | G13: =#REF! -> #REF! | H13: =SUM(D13:G13) -> #REF! | I13: =#REF! -> #REF! | J13: =#REF! -> #REF! | K13: =#REF! -> #REF! | L13: =#REF! -> #REF! | M13: =#REF! -> #REF! | N13: =SUM(I13:M13) -> #REF! | O13: =#REF! -> #REF! | P13: =#REF! -> #REF! | Q13: =#REF! -> #REF! | R13: =#REF! -> #REF! | S13: =#REF! -> #REF! | T13: =#REF! -> #REF! | U13: =#REF! -> #REF! | V13: =#REF! -> #REF! | ... Y13: =#REF! -> #REF! | Z13: =SUM(O13:Y13) -> #REF! | AA13: =D13+E13+F13+G13+I13+J13+K13+L13+M13+O13+P13+Q13+R13+S13+T13+U13+V13+W13+X13+Y13 -> #REF! | AF13: 07q4 | AG13: =D19 -> #REF! | AH13: =E19 -> #REF! | AI13: =F19 -> #REF! | AJ13: =G19 -> #REF! | AL13: =I19 -> #REF! | AM13: =J19 -> #REF! | AN13: =K19 -> #REF! | AO13: =L19 -> #REF! | AP13: =M19 -> #REF! | AR13: =O19 -> #REF! | AS13: =P19 -> #REF! | AT13: =Q19 -> #REF! | AU13: =R19 -> #REF! | AV13: =S19 -> #REF! | AW13: =T19 -> #REF! | AX13: =U19 -> #REF! | AY13: =V19 -> #REF! | ... BB13: =Y19 -> #REF!
C14: Q3 | D14: =#REF! -> #REF! | E14: =#REF! -> #REF! | F14: =#REF! -> #REF! | G14: =#REF! -> #REF! | H14: =SUM(D14:G14) -> #REF! | I14: =#REF! -> #REF! | J14: =#REF! -> #REF! | K14: =#REF! -> #REF! | L14: =#REF! -> #REF! | M14: =#REF! -> #REF! | N14: =SUM(I14:M14) -> #REF! | O14: =#REF! -> #REF! | P14: =#REF! -> #REF! | Q14: =#REF! -> #REF! | R14: =#REF! -> #REF! | S14: =#REF! -> #REF! | T14: =#REF! -> #REF! | U14: =#REF! -> #REF! | V14: =#REF! -> #REF! | ... Y14: =#REF! -> #REF! | Z14: =SUM(O14:Y14) -> #REF! | AA14: =D14+E14+F14+G14+I14+J14+K14+L14+M14+O14+P14+Q14+R14+S14+T14+U14+V14+W14+X14+Y14 -> #REF! | AF14: 08q1 | AG14: =D20 -> #REF! | AH14: =E20 -> #REF! | AI14: =F20 -> #REF! | AJ14: =G20 -> #REF! | AL14: =I20 -> #REF! | AM14: =J20 -> #REF! | AN14: =K20 -> #REF! | AO14: =L20 -> #REF! | AP14: =M20 -> #REF! | AR14: =O20 -> #REF! | AS14: =P20 -> #REF! | AT14: =Q20 -> #REF! | AU14: =R20 -> #REF! | AV14: =S20 -> #REF! | AW14: =T20 -> #REF! | AX14: =U20 -> #REF! | AY14: =V20 -> #REF! | ... BB14: =Y20 -> #REF!
C15: Q4 | D15: =#REF! -> #REF! | E15: =#REF! -> #REF! | F15: =#REF! -> #REF! | G15: =#REF! -> #REF! | H15: =SUM(D15:G15) -> #REF! | I15: =#REF! -> #REF! | J15: =#REF! -> #REF! | K15: =#REF! -> #REF! | L15: =#REF! -> #REF! | M15: =#REF! -> #REF! | N15: =SUM(I15:M15) -> #REF! | O15: =#REF! -> #REF! | P15: =#REF! -> #REF! | Q15: =#REF! -> #REF! | R15: =#REF! -> #REF! | S15: =#REF! -> #REF! | T15: =#REF! -> #REF! | U15: =#REF! -> #REF! | V15: =#REF! -> #REF! | ... Y15: =#REF! -> #REF! | Z15: =SUM(O15:Y15) -> #REF! | AA15: =D15+E15+F15+G15+I15+J15+K15+L15+M15+O15+P15+Q15+R15+S15+T15+U15+V15+W15+X15+Y15 -> #REF! | AF15: 08q2 | AG15: =D21 -> #REF! | AH15: =E21 -> #REF! | AI15: =F21 -> #REF! | AJ15: =G21 -> #REF! | AL15: =I21 -> #REF! | AM15: =J21 -> #REF! | AN15: =K21 -> #REF! | AO15: =L21 -> #REF! | AP15: =M21 -> #REF! | AR15: =O21 -> #REF! | AS15: =P21 -> #REF! | AT15: =Q21 -> #REF! | AU15: =R21 -> #REF! | AV15: =S21 -> #REF! | AW15: =T21 -> #REF! | AX15: =U21 -> #REF! | AY15: =V21 -> #REF! | ... BB15: =Y21 -> #REF!
B16: 2007 | C16: Q1 | D16: =#REF! -> #REF! | E16: =#REF! -> #REF! | F16: =#REF! -> #REF! | G16: =#REF! -> #REF! | H16: =SUM(D16:G16) -> #REF! | I16: =#REF! -> #REF! | J16: =#REF! -> #REF! | K16: =#REF! -> #REF! | L16: =#REF! -> #REF! | M16: =#REF! -> #REF! | N16: =SUM(I16:M16) -> #REF! | O16: =#REF! -> #REF! | P16: =#REF! -> #REF! | Q16: =#REF! -> #REF! | R16: =#REF! -> #REF! | S16: =#REF! -> #REF! | T16: =#REF! -> #REF! | U16: =#REF! -> #REF! | V16: =#REF! -> #REF! | ... Y16: =#REF! -> #REF! | Z16: =SUM(O16:Y16) -> #REF! | AA16: =D16+E16+F16+G16+I16+J16+K16+L16+M16+O16+P16+Q16+R16+S16+T16+U16+V16+W16+X16+Y16 -> #REF! | AF16: 08q3 | AG16: =D22 -> #REF! | AH16: =E22 -> #REF! | AI16: =F22 -> #REF! | AJ16: =G22 -> #REF! | AL16: =I22 -> #REF! | AM16: =J22 -> #REF! | AN16: =K22 -> #REF! | AO16: =L22 -> #REF! | AP16: =M22 -> #REF! | AR16: =O22 -> #REF! | AS16: =P22 -> #REF! | AT16: =Q22 -> #REF! | AU16: =R22 -> #REF! | AV16: =S22 -> #REF! | AW16: =T22 -> #REF! | AX16: =U22 -> #REF! | AY16: =V22 -> #REF! | ... BB16: =Y22 -> #REF!
C17: Q2 | D17: =#REF! -> #REF! | E17: =#REF! -> #REF! | F17: =#REF! -> #REF! | G17: =#REF! -> #REF! | H17: =SUM(D17:G17) -> #REF! | I17: =#REF! -> #REF! | J17: =#REF! -> #REF! | K17: =#REF! -> #REF! | L17: =#REF! -> #REF! | M17: =#REF! -> #REF! | N17: =SUM(I17:M17) -> #REF! | O17: =#REF! -> #REF! | P17: =#REF! -> #REF! | Q17: =#REF! -> #REF! | R17: =#REF! -> #REF! | S17: =#REF! -> #REF! | T17: =#REF! -> #REF! | U17: =#REF! -> #REF! | V17: =#REF! -> #REF! | ... Y17: =#REF! -> #REF! | Z17: =SUM(O17:Y17) -> #REF! | AA17: =D17+E17+F17+G17+I17+J17+K17+L17+M17+O17+P17+Q17+R17+S17+T17+U17+V17+W17+X17+Y17 -> #REF! | AF17: 08q4 | AG17: =D23 -> #REF! | AH17: =E23 -> #REF! | AI17: =F23 -> #REF! | AJ17: =G23 -> #REF! | AL17: =I23 -> #REF! | AM17: =J23 -> #REF! | AN17: =K23 -> #REF! | AO17: =L23 -> #REF! | AP17: =M23 -> #REF! | AR17: =O23 -> #REF! | AS17: =P23 -> #REF! | AT17: =Q23 -> #REF! | AU17: =R23 -> #REF! | AV17: =S23 -> #REF! | AW17: =T23 -> #REF! | AX17: =U23 -> #REF! | AY17: =V23 -> #REF! | ... BB17: =Y23 -> #REF!
C18: Q3 | D18: =#REF! -> #REF! | E18: =#REF! -> #REF! | F18: =#REF! -> #REF! | G18: =#REF! -> #REF! | H18: =SUM(D18:G18) -> #REF! | I18: =#REF! -> #REF! | J18: =#REF! -> #REF! | K18: =#REF! -> #REF! | L18: =#REF! -> #REF! | M18: =#REF! -> #REF! | N18: =SUM(I18:M18) -> #REF! | O18: =#REF! -> #REF! | P18: =#REF! -> #REF! | Q18: =#REF! -> #REF! | R18: =#REF! -> #REF! | S18: =#REF! -> #REF! | T18: =#REF! -> #REF! | U18: =#REF! -> #REF! | V18: =#REF! -> #REF! | ... Y18: =#REF! -> #REF! | Z18: =SUM(O18:Y18) -> #REF! | AA18: =D18+E18+F18+G18+I18+J18+K18+L18+M18+O18+P18+Q18+R18+S18+T18+U18+V18+W18+X18+Y18 -> #REF! | AF18: 09q1 | AG18: =D24 -> #REF! | AH18: =E24 -> #REF! | AI18: =F24 -> #REF! | AJ18: =G24 -> #REF! | AL18: =I24 -> #REF! | AM18: =J24 -> #REF! | AN18: =K24 -> #REF! | AO18: =L24 -> #REF! | AP18: =M24 -> #REF! | AR18: =O24 -> #REF! | AS18: =P24 -> #REF! | AT18: =Q24 -> #REF! | AU18: =R24 -> #REF! | AV18: =S24 -> #REF! | AW18: =T24 -> #REF! | AX18: =U24 -> #REF! | AY18: =V24 -> #REF! | ... BB18: =Y24 -> #REF!
C19: Q4 | D19: =#REF! -> #REF! | E19: =#REF! -> #REF! | F19: =#REF! -> #REF! | G19: =#REF! -> #REF! | H19: =SUM(D19:G19) -> #REF! | I19: =#REF! -> #REF! | J19: =#REF! -> #REF! | K19: =#REF! -> #REF! | L19: =#REF! -> #REF! | M19: =#REF! -> #REF! | N19: =SUM(I19:M19) -> #REF! | O19: =#REF! -> #REF! | P19: =#REF! -> #REF! | Q19: =#REF! -> #REF! | R19: =#REF! -> #REF! | S19: =#REF! -> #REF! | T19: =#REF! -> #REF! | U19: =#REF! -> #REF! | V19: =#REF! -> #REF! | ... Y19: =#REF! -> #REF! | Z19: =SUM(O19:Y19) -> #REF! | AA19: =D19+E19+F19+G19+I19+J19+K19+L19+M19+O19+P19+Q19+R19+S19+T19+U19+V19+W19+X19+Y19 -> #REF! | AF19: 09q2 | AG19: =D25 -> #REF! | AH19: =E25 -> #REF! | AI19: =F25 -> #REF! | AJ19: =G25 -> #REF! | AL19: =I25 -> #REF! | AM19: =J25 -> #REF! | AN19: =K25 -> #REF! | AO19: =L25 -> #REF! | AP19: =M25 -> #REF! | AR19: =O25 -> #REF! | AS19: =P25 -> #REF! | AT19: =Q25 -> #REF! | AU19: =R25 -> #REF! | AV19: =S25 -> #REF! | AW19: =T25 -> #REF! | AX19: =U25 -> #REF! | AY19: =V25 -> #REF! | ... BB19: =Y25 -> #REF!
B20: 2008 | C20: Q1 | D20: =#REF! -> #REF! | E20: =#REF! -> #REF! | F20: =#REF! -> #REF! | G20: =#REF! -> #REF! | H20: =SUM(D20:G20) -> #REF! | I20: =#REF! -> #REF! | J20: =#REF! -> #REF! | K20: =#REF! -> #REF! | L20: =#REF! -> #REF! | M20: =#REF! -> #REF! | N20: =SUM(I20:M20) -> #REF! | O20: =#REF! -> #REF! | P20: =#REF! -> #REF! | Q20: =#REF! -> #REF! | R20: =#REF! -> #REF! | S20: =#REF! -> #REF! | T20: =#REF! -> #REF! | U20: =#REF! -> #REF! | V20: =#REF! -> #REF! | ... Y20: =#REF! -> #REF! | Z20: =SUM(O20:Y20) -> #REF! | AA20: =D20+E20+F20+G20+I20+J20+K20+L20+M20+O20+P20+Q20+R20+S20+T20+U20+V20+W20+X20+Y20 -> #REF! | AF20: 09q3 | AG20: =D26 -> #REF! | AH20: =E26 -> #REF! | AI20: =F26 -> #REF! | AJ20: =G26 -> #REF! | AL20: =I26 -> #REF! | AM20: =J26 -> #REF! | AN20: =K26 -> #REF! | AO20: =L26 -> #REF! | AP20: =M26 -> #REF! | AR20: =O26 -> #REF! | AS20: =P26 -> #REF! | AT20: =Q26 -> #REF! | AU20: =R26 -> #REF! | AV20: =S26 -> #REF! | AW20: =T26 -> #REF! | AX20: =U26 -> #REF! | AY20: =V26 -> #REF! | ... BB20: =Y26 -> #REF!
C21: Q2 | D21: =#REF! -> #REF! | E21: =#REF! -> #REF! | F21: =#REF! -> #REF! | G21: =#REF! -> #REF! | H21: =SUM(D21:G21) -> #REF! | I21: =#REF! -> #REF! | J21: =#REF! -> #REF! | K21: =#REF! -> #REF! | L21: =#REF! -> #REF! | M21: =#REF! -> #REF! | N21: =SUM(I21:M21) -> #REF! | O21: =#REF! -> #REF! | P21: =#REF! -> #REF! | Q21: =#REF! -> #REF! | R21: =#REF! -> #REF! | S21: =#REF! -> #REF! | T21: =#REF! -> #REF! | U21: =#REF! -> #REF! | V21: =#REF! -> #REF! | ... Y21: =#REF! -> #REF! | Z21: =SUM(O21:Y21) -> #REF! | AA21: =D21+E21+F21+G21+I21+J21+K21+L21+M21+O21+P21+Q21+R21+S21+T21+U21+V21+W21+X21+Y21 -> #REF! | AF21: 09q4 | AG21: =D27 -> #REF! | AH21: =E27 -> #REF! | AI21: =F27 -> #REF! | AJ21: =G27 -> #REF! | AL21: =I27 -> #REF! | AM21: =J27 -> #REF! | AN21: =K27 -> #REF! | AO21: =L27 -> #REF! | AP21: =M27 -> #REF! | AR21: =O27 -> #REF! | AS21: =P27 -> #REF! | AT21: =Q27 -> #REF! | AU21: =R27 -> #REF! | AV21: =S27 -> #REF! | AW21: =T27 -> #REF! | AX21: =U27 -> #REF! | AY21: =V27 -> #REF! | ... BB21: =Y27 -> #REF!
C22: Q3 | D22: =#REF! -> #REF! | E22: =#REF! -> #REF! | F22: =#REF! -> #REF! | G22: =#REF! -> #REF! | H22: =SUM(D22:G22) -> #REF! | I22: =#REF! -> #REF! | J22: =#REF! -> #REF! | K22: =#REF! -> #REF! | L22: =#REF! -> #REF! | M22: =#REF! -> #REF! | N22: =SUM(I22:M22) -> #REF! | O22: =#REF! -> #REF! | P22: =#REF! -> #REF! | Q22: =#REF! -> #REF! | R22: =#REF! -> #REF! | S22: =#REF! -> #REF! | T22: =#REF! -> #REF! | U22: =#REF! -> #REF! | V22: =#REF! -> #REF! | ... Y22: =#REF! -> #REF! | Z22: =SUM(O22:Y22) -> #REF! | AA22: =D22+E22+F22+G22+I22+J22+K22+L22+M22+O22+P22+Q22+R22+S22+T22+U22+V22+W22+X22+Y22 -> #REF! | AF22: 10q1 | AG22: =D28 -> #REF! | AH22: =E28 -> #REF! | AI22: =F28 -> #REF! | AJ22: =G28 -> #REF! | AL22: =I28 -> #REF! | AM22: =J28 -> #REF! | AN22: =K28 -> #REF! | AO22: =L28 -> #REF! | AP22: =M28 -> #REF! | AR22: =O28 -> #REF! | AS22: =P28 -> #REF! | AT22: =Q28 -> #REF! | AU22: =R28 -> #REF! | AV22: =S28 -> #REF! | AW22: =T28 -> #REF! | AX22: =U28 -> #REF! | AY22: =V28 -> #REF! | ... BB22: =Y28 -> #REF!
C23: Q4 | D23: =#REF! -> #REF! | E23: =#REF! -> #REF! | F23: =#REF! -> #REF! | G23: =#REF! -> #REF! | H23: =SUM(D23:G23) -> #REF! | I23: =#REF! -> #REF! | J23: =#REF! -> #REF! | K23: =#REF! -> #REF! | L23: =#REF! -> #REF! | M23: =#REF! -> #REF! | N23: =SUM(I23:M23) -> #REF! | O23: =#REF! -> #REF! | P23: =#REF! -> #REF! | Q23: =#REF! -> #REF! | R23: =#REF! -> #REF! | S23: =#REF! -> #REF! | T23: =#REF! -> #REF! | U23: =#REF! -> #REF! | V23: =#REF! -> #REF! | ... Y23: =#REF! -> #REF! | Z23: =SUM(O23:Y23) -> #REF! | AA23: =D23+E23+F23+G23+I23+J23+K23+L23+M23+O23+P23+Q23+R23+S23+T23+U23+V23+W23+X23+Y23 -> #REF! | AF23: 10q2 | AG23: =D29 -> #REF! | AH23: =E29 -> #REF! | AI23: =F29 -> #REF! | AJ23: =G29 -> #REF! | AL23: =I29 -> #REF! | AM23: =J29 -> #REF! | AN23: =K29 -> #REF! | AO23: =L29 -> #REF! | AP23: =M29 -> #REF! | AR23: =O29 -> #REF! | AS23: =P29 -> #REF! | AT23: =Q29 -> #REF! | AU23: =R29 -> #REF! | AV23: =S29 -> #REF! | AW23: =T29 -> #REF! | AX23: =U29 -> #REF! | AY23: =V29 -> #REF! | ... BB23: =Y29 -> #REF!
B24: 2009 | C24: Q1 | D24: =#REF! -> #REF! | E24: =#REF! -> #REF! | F24: =#REF! -> #REF! | G24: =#REF! -> #REF! | H24: =SUM(D24:G24) -> #REF! | I24: =#REF! -> #REF! | J24: =#REF! -> #REF! | K24: =#REF! -> #REF! | L24: =#REF! -> #REF! | M24: =#REF! -> #REF! | N24: =SUM(I24:M24) -> #REF! | O24: =#REF! -> #REF! | P24: =#REF! -> #REF! | Q24: =#REF! -> #REF! | R24: =#REF! -> #REF! | S24: =#REF! -> #REF! | T24: =#REF! -> #REF! | U24: =#REF! -> #REF! | V24: =#REF! -> #REF! | ... Y24: =#REF! -> #REF! | Z24: =SUM(O24:Y24) -> #REF! | AA24: =D24+E24+F24+G24+I24+J24+K24+L24+M24+O24+P24+Q24+R24+S24+T24+U24+V24+W24+X24+Y24 -> #REF! | AF24: 10q3 | AG24: =D30 -> #REF! | AH24: =E30 -> #REF! | AI24: =F30 -> #REF! | AJ24: =G30 -> #REF! | AL24: =I30 -> #REF! | AM24: =J30 -> #REF! | AN24: =K30 -> #REF! | AO24: =L30 -> #REF! | AP24: =M30 -> #REF! | AR24: =O30 -> #REF! | AS24: =P30 -> #REF! | AT24: =Q30 -> #REF! | AU24: =R30 -> #REF! | AV24: =S30 -> #REF! | AW24: =T30 -> #REF! | AX24: =U30 -> #REF! | AY24: =V30 -> #REF! | ... BB24: =Y30 -> #REF!
C25: Q2 | D25: =#REF! -> #REF! | E25: =#REF! -> #REF! | F25: =#REF! -> #REF! | G25: =#REF! -> #REF! | H25: =SUM(D25:G25) -> #REF! | I25: =#REF! -> #REF! | J25: =#REF! -> #REF! | K25: =#REF! -> #REF! | L25: =#REF! -> #REF! | M25: =#REF! -> #REF! | N25: =SUM(I25:M25) -> #REF! | O25: =#REF! -> #REF! | P25: =#REF! -> #REF! | Q25: =#REF! -> #REF! | R25: =#REF! -> #REF! | S25: =#REF! -> #REF! | T25: =#REF! -> #REF! | U25: =#REF! -> #REF! | V25: =#REF! -> #REF! | ... Y25: =#REF! -> #REF! | Z25: =SUM(O25:Y25) -> #REF! | AA25: =D25+E25+F25+G25+I25+J25+K25+L25+M25+O25+P25+Q25+R25+S25+T25+U25+V25+W25+X25+Y25 -> #REF! | AF25: 10q4 | AG25: =D31 -> #REF! | AH25: =E31 -> #REF! | AI25: =F31 -> #REF! | AJ25: =G31 -> #REF! | AL25: =I31 -> #REF! | AM25: =J31 -> #REF! | AN25: =K31 -> #REF! | AO25: =L31 -> #REF! | AP25: =M31 -> #REF! | AR25: =O31 -> #REF! | AS25: =P31 -> #REF! | AT25: =Q31 -> #REF! | AU25: =R31 -> #REF! | AV25: =S31 -> #REF! | AW25: =T31 -> #REF! | AX25: =U31 -> #REF! | AY25: =V31 -> #REF! | ... BB25: =Y31 -> #REF!
C26: Q3 | D26: =#REF! -> #REF! | E26: =#REF! -> #REF! | F26: =#REF! -> #REF! | G26: =#REF! -> #REF! | H26: =SUM(D26:G26) -> #REF! | I26: =#REF! -> #REF! | J26: =#REF! -> #REF! | K26: =#REF! -> #REF! | L26: =#REF! -> #REF! | M26: =#REF! -> #REF! | N26: =SUM(I26:M26) -> #REF! | O26: =#REF! -> #REF! | P26: =#REF! -> #REF! | Q26: =#REF! -> #REF! | R26: =#REF! -> #REF! | S26: =#REF! -> #REF! | T26: =#REF! -> #REF! | U26: =#REF! -> #REF! | V26: =#REF! -> #REF! | ... Y26: =#REF! -> #REF! | Z26: =SUM(O26:Y26) -> #REF! | AA26: =D26+E26+F26+G26+I26+J26+K26+L26+M26+O26+P26+Q26+R26+S26+T26+U26+V26+W26+X26+Y26 -> #REF! | AF26: 11q1 | AG26: =D32 -> #REF! | AH26: =E32 -> #REF! | AI26: =F32 -> #REF! | AJ26: =G32 -> #REF! | AL26: =I32 -> #REF! | AM26: =J32 -> #REF! | AN26: =K32 -> #REF! | AO26: =L32 -> #REF! | AP26: =M32 -> #REF! | AR26: =O32 -> #REF! | AS26: =P32 -> #REF! | AT26: =Q32 -> #REF! | AU26: =R32 -> #REF! | AV26: =S32 -> #REF! | AW26: =T32 -> #REF! | AX26: =U32 -> #REF! | AY26: =V32 -> #REF! | ... BB26: =Y32 -> #REF!
C27: Q4 | D27: =#REF! -> #REF! | E27: =#REF! -> #REF! | F27: =#REF! -> #REF! | G27: =#REF! -> #REF! | H27: =SUM(D27:G27) -> #REF! | I27: =#REF! -> #REF! | J27: =#REF! -> #REF! | K27: =#REF! -> #REF! | L27: =#REF! -> #REF! | M27: =#REF! -> #REF! | N27: =SUM(I27:M27) -> #REF! | O27: =#REF! -> #REF! | P27: =#REF! -> #REF! | Q27: =#REF! -> #REF! | R27: =#REF! -> #REF! | S27: =#REF! -> #REF! | T27: =#REF! -> #REF! | U27: =#REF! -> #REF! | V27: =#REF! -> #REF! | ... Y27: =#REF! -> #REF! | Z27: =SUM(O27:Y27) -> #REF! | AA27: =D27+E27+F27+G27+I27+J27+K27+L27+M27+O27+P27+Q27+R27+S27+T27+U27+V27+W27+X27+Y27 -> #REF! | AF27: 11q2 | AG27: =D33 -> #REF! | AH27: =E33 -> #REF! | AI27: =F33 -> #REF! | AJ27: =G33 -> #REF! | AL27: =I33 -> #REF! | AM27: =J33 -> #REF! | AN27: =K33 -> #REF! | AO27: =L33 -> #REF! | AP27: =M33 -> #REF! | AR27: =O33 -> #REF! | AS27: =P33 -> #REF! | AT27: =Q33 -> #REF! | AU27: =R33 -> #REF! | AV27: =S33 -> #REF! | AW27: =T33 -> #REF! | AX27: =U33 -> #REF! | AY27: =V33 -> #REF! | ... BB27: =Y33 -> #REF!
B28: 2010 | C28: Q1 | D28: =#REF! -> #REF! | E28: =#REF! -> #REF! | F28: =#REF! -> #REF! | G28: =#REF! -> #REF! | H28: =SUM(D28:G28) -> #REF! | I28: =#REF! -> #REF! | J28: =#REF! -> #REF! | K28: =#REF! -> #REF! | L28: =#REF! -> #REF! | M28: =#REF! -> #REF! | N28: =SUM(I28:M28) -> #REF! | O28: =#REF! -> #REF! | P28: =#REF! -> #REF! | Q28: =#REF! -> #REF! | R28: =#REF! -> #REF! | S28: =#REF! -> #REF! | T28: =#REF! -> #REF! | U28: =#REF! -> #REF! | V28: =#REF! -> #REF! | ... Y28: =#REF! -> #REF! | Z28: =SUM(O28:Y28) -> #REF! | AA28: =D28+E28+F28+G28+I28+J28+K28+L28+M28+O28+P28+Q28+R28+S28+T28+U28+V28+W28+X28+Y28 -> #REF! | AF28: 11q3 | AG28: =D34 -> #REF! | AH28: =E34 -> #REF! | AI28: =F34 -> #REF! | AJ28: =G34 -> #REF! | AL28: =I34 -> #REF! | AM28: =J34 -> #REF! | AN28: =K34 -> #REF! | AO28: =L34 -> #REF! | AP28: =M34 -> #REF! | AR28: =O34 -> #REF! | AS28: =P34 -> #REF! | AT28: =Q34 -> #REF! | AU28: =R34 -> #REF! | AV28: =S34 -> #REF! | AW28: =T34 -> #REF! | AX28: =U34 -> #REF! | AY28: =V34 -> #REF! | ... BB28: =Y34 -> #REF!
C29: Q2 | D29: =#REF! -> #REF! | E29: =#REF! -> #REF! | F29: =#REF! -> #REF! | G29: =#REF! -> #REF! | H29: =SUM(D29:G29) -> #REF! | I29: =#REF! -> #REF! | J29: =#REF! -> #REF! | K29: =#REF! -> #REF! | L29: =#REF! -> #REF! | M29: =#REF! -> #REF! | N29: =SUM(I29:M29) -> #REF! | O29: =#REF! -> #REF! | P29: =#REF! -> #REF! | Q29: =#REF! -> #REF! | R29: =#REF! -> #REF! | S29: =#REF! -> #REF! | T29: =#REF! -> #REF! | U29: =#REF! -> #REF! | V29: =#REF! -> #REF! | ... Y29: =#REF! -> #REF! | Z29: =SUM(O29:Y29) -> #REF! | AA29: =D29+E29+F29+G29+I29+J29+K29+L29+M29+O29+P29+Q29+R29+S29+T29+U29+V29+W29+X29+Y29 -> #REF!
C30: Q3 | D30: =#REF! -> #REF! | E30: =#REF! -> #REF! | F30: =#REF! -> #REF! | G30: =#REF! -> #REF! | H30: =SUM(D30:G30) -> #REF! | I30: =#REF! -> #REF! | J30: =#REF! -> #REF! | K30: =#REF! -> #REF! | L30: =#REF! -> #REF! | M30: =#REF! -> #REF! | N30: =SUM(I30:M30) -> #REF! | O30: =#REF! -> #REF! | P30: =#REF! -> #REF! | Q30: =#REF! -> #REF! | R30: =#REF! -> #REF! | S30: =#REF! -> #REF! | T30: =#REF! -> #REF! | U30: =#REF! -> #REF! | V30: =#REF! -> #REF! | ... Y30: =#REF! -> #REF! | Z30: =SUM(O30:Y30) -> #REF! | AA30: =D30+E30+F30+G30+I30+J30+K30+L30+M30+O30+P30+Q30+R30+S30+T30+U30+V30+W30+X30+Y30 -> #REF!
C31: Q4 | D31: =#REF! -> #REF! | E31: =#REF! -> #REF! | F31: =#REF! -> #REF! | G31: =#REF! -> #REF! | H31: =SUM(D31:G31) -> #REF! | I31: =#REF! -> #REF! | J31: =#REF! -> #REF! | K31: =#REF! -> #REF! | L31: =#REF! -> #REF! | M31: =#REF! -> #REF! | N31: =SUM(I31:M31) -> #REF! | O31: =#REF! -> #REF! | P31: =#REF! -> #REF! | Q31: =#REF! -> #REF! | R31: =#REF! -> #REF! | S31: =#REF! -> #REF! | T31: =#REF! -> #REF! | U31: =#REF! -> #REF! | V31: =#REF! -> #REF! | ... Y31: =#REF! -> #REF! | Z31: =SUM(O31:Y31) -> #REF! | AA31: =D31+E31+F31+G31+I31+J31+K31+L31+M31+O31+P31+Q31+R31+S31+T31+U31+V31+W31+X31+Y31 -> #REF!
B32: 2011 | C32: Q1 | D32: =#REF! -> #REF! | E32: =#REF! -> #REF! | F32: =#REF! -> #REF! | G32: =#REF! -> #REF! | H32: =SUM(D32:G32) -> #REF! | I32: =#REF! -> #REF! | J32: =#REF! -> #REF! | K32: =#REF! -> #REF! | L32: =#REF! -> #REF! | M32: =#REF! -> #REF! | N32: =SUM(I32:M32) -> #REF! | O32: =#REF! -> #REF! | P32: =#REF! -> #REF! | Q32: =#REF! -> #REF! | R32: =#REF! -> #REF! | S32: =#REF! -> #REF! | T32: =#REF! -> #REF! | U32: =#REF! -> #REF! | V32: =#REF! -> #REF! | ... Y32: =#REF! -> #REF! | Z32: =SUM(O32:Y32) -> #REF! | AA32: =D32+E32+F32+G32+I32+J32+K32+L32+M32+O32+P32+Q32+R32+S32+T32+U32+V32+W32+X32+Y32 -> #REF!
C33: Q2* | D33: =#REF! -> #REF! | E33: =#REF! -> #REF! | F33: =#REF! -> #REF! | G33: =#REF! -> #REF! | H33: =SUM(D33:G33) -> #REF! | I33: =#REF! -> #REF! | J33: =#REF! -> #REF! | K33: =#REF! -> #REF! | L33: =#REF! -> #REF! | M33: =#REF! -> #REF! | N33: =SUM(I33:M33) -> #REF! | O33: =#REF! -> #REF! | P33: =#REF! -> #REF! | Q33: =#REF! -> #REF! | R33: =#REF! -> #REF! | S33: =#REF! -> #REF! | T33: =#REF! -> #REF! | U33: =#REF! -> #REF! | V33: =#REF! -> #REF! | ... Y33: =#REF! -> #REF! | Z33: =SUM(O33:Y33) -> #REF! | AA33: =D33+E33+F33+G33+I33+J33+K33+L33+M33+O33+P33+Q33+R33+S33+T33+U33+V33+W33+X33+Y33 -> #REF!
C34: Q3* | D34: =#REF! -> #REF! | E34: =#REF! -> #REF! | F34: =#REF! -> #REF! | G34: =#REF! -> #REF! | H34: =SUM(D34:G34) -> #REF! | I34: =#REF! -> #REF! | J34: =#REF! -> #REF! | K34: =#REF! -> #REF! | L34: =#REF! -> #REF! | M34: =#REF! -> #REF! | N34: =SUM(I34:M34) -> #REF! | O34: =#REF! -> #REF! | P34: =#REF! -> #REF! | Q34: =#REF! -> #REF! | R34: =#REF! -> #REF! | S34: =#REF! -> #REF! | T34: =#REF! -> #REF! | U34: =#REF! -> #REF! | V34: =#REF! -> #REF! | ... Y34: =#REF! -> #REF! | Z34: =SUM(O34:Y34) -> #REF! | AA34: =D34+E34+F34+G34+I34+J34+K34+L34+M34+O34+P34+Q34+R34+S34+T34+U34+V34+W34+X34+Y34 -> #REF!
C35: Q4* | D35: =#REF! -> #REF! | E35: =#REF! -> #REF! | F35: =#REF! -> #REF! | G35: =#REF! -> #REF! | H35: =SUM(D35:G35) -> #REF! | I35: =#REF! -> #REF! | J35: =#REF! -> #REF! | K35: =#REF! -> #REF! | L35: =#REF! -> #REF! | M35: =#REF! -> #REF! | N35: =SUM(I35:M35) -> #REF! | O35: =#REF! -> #REF! | P35: =#REF! -> #REF! | Q35: =#REF! -> #REF! | R35: =#REF! -> #REF! | S35: =#REF! -> #REF! | T35: =#REF! -> #REF! | U35: =#REF! -> #REF! | V35: =#REF! -> #REF! | ... Y35: =#REF! -> #REF! | Z35: =SUM(O35:Y35) -> #REF! | AA35: =D35+E35+F35+G35+I35+J35+K35+L35+M35+O35+P35+Q35+R35+S35+T35+U35+V35+W35+X35+Y35 -> #REF!
B36: 2012 | C36: Q1* | D36: =#REF! -> #REF! | E36: =#REF! -> #REF! | F36: =#REF! -> #REF! | G36: =#REF! -> #REF! | H36: =SUM(D36:G36) -> #REF! | I36: =#REF! -> #REF! | J36: =#REF! -> #REF! | K36: =#REF! -> #REF! | L36: =#REF! -> #REF! | M36: =#REF! -> #REF! | N36: =SUM(I36:M36) -> #REF! | O36: =#REF! -> #REF! | P36: =#REF! -> #REF! | Q36: =#REF! -> #REF! | R36: =#REF! -> #REF! | S36: =#REF! -> #REF! | T36: =#REF! -> #REF! | U36: =#REF! -> #REF! | V36: =#REF! -> #REF! | ... Y36: =#REF! -> #REF! | Z36: =SUM(O36:Y36) -> #REF! | AA36: =D36+E36+F36+G36+I36+J36+K36+L36+M36+O36+P36+Q36+R36+S36+T36+U36+V36+W36+X36+Y36 -> #REF!
B38: * provisional

Sheet T2 (2)
B1: Table 2 - Percentage change (quarter-on-quarter) in the quarterly value added by Activity at 2006 constant prices
D2: Agriculture Sector | I2: Industry Sector | O2: Services Sector
B3: Year | C3: Quarter | D3: Crops & Cocoa | E3: Livestock | F3: Forestry | G3: Fishing | I3: Mining and Quarrying | J3: Manufacturing | K3: Electricity | L3: Water & Sewerage | M3: Construction | O3: Trade; Repair Of Vehicles, Household Goods | P3: Hotels And Restaurants | Q3: Transport & Storage | R3: Information & Communication | S3: Financial & Insurance Activities | T3: Real Estate Activities | U3: Business & other Services Activities | V3: Public Administration | W3: Education | X3: Health | Y3: Other Personal Service Activities | AA3: Total Value Added | AB3: Net Taxes | AC3: GDP at Constant Prices | AF3: Agric | AG3: Ind | AH3: Serv
B4: 2006
B5: 2007 | D5: ='T1'!D5/'T1'!D4*100-100 -> -1.346605 | E5: ='T1'!E5/'T1'!E4*100-100 -> 4.7316467 | F5: ='T1'!F5/'T1'!F4*100-100 -> -4.0926214 | G5: ='T1'!G5/'T1'!G4*100-100 -> -7.2472487 | I5: ='T1'!H5/'T1'!H4*100-100 -> 6.8620818 | J5: ='T1'!I5/'T1'!I4*100-100 -> -1.2158585 | K5: ='T1'!J5/'T1'!J4*100-100 -> -17.212572 | L5: ='T1'!K5/'T1'!K4*100-100 -> 1.161077 | M5: ='T1'!L5/'T1'!L4*100-100 -> 23.151962 | O5: ='T1'!M5/'T1'!M4*100-100 -> 5.4284631 | P5: ='T1'!N5/'T1'!N4*100-100 -> 2.5176994 | Q5: ='T1'!O5/'T1'!O4*100-100 -> 9.171052 | R5: ='T1'!P5/'T1'!P4*100-100 -> 4.1 | S5: ='T1'!Q5/'T1'!Q4*100-100 -> 18.380405 | T5: ='T1'!R5/'T1'!R4*100-100 -> 2.4 | U5: ='T1'!S5/'T1'!S4*100-100 -> 3.8649273 | V5: ='T1'!T5/'T1'!T4*100-100 -> 11.3 | ... Y5: ='T1'!W5/'T1'!W4*100-100 -> 8.8724113 | AA5: ='T1'!X5/'T1'!X4*100-100 -> 4.4933544 | AB5: ='T1'!Y5/'T1'!Y4*100-100 -> 45.573884 | AC5: ='T1'!Z5/'T1'!Z4*100-100 -> 6.459768
B6: 2008 | D6: ='T1'!D6/'T1'!D5*100-100 -> 8.6 | E6: ='T1'!E6/'T1'!E5*100-100 -> 5.1039655 | F6: ='T1'!F6/'T1'!F5*100-100 -> -3.3201314 | G6: ='T1'!G6/'T1'!G5*100-100 -> 17.380777 | I6: ='T1'!H6/'T1'!H5*100-100 -> 2.4193735 | J6: ='T1'!I6/'T1'!I5*100-100 -> 3.7004754 | K6: ='T1'!J6/'T1'!J5*100-100 -> 19.423493 | L6: ='T1'!K6/'T1'!K5*100-100 -> 0.84657122 | M6: ='T1'!L6/'T1'!L5*100-100 -> 38.98349 | O6: ='T1'!M6/'T1'!M5*100-100 -> 9.5045688 | P6: ='T1'!N6/'T1'!N5*100-100 -> 9.0755497 | Q6: ='T1'!O6/'T1'!O5*100-100 -> 3.82786 | R6: ='T1'!P6/'T1'!P5*100-100 -> 19.5 | S6: ='T1'!Q6/'T1'!Q5*100-100 -> 10.781645 | T6: ='T1'!R6/'T1'!R5*100-100 -> 2.4 | U6: ='T1'!S6/'T1'!S5*100-100 -> -1.8306604 | V6: ='T1'!T6/'T1'!T5*100-100 -> 12.734106 | ... Y6: ='T1'!W6/'T1'!W5*100-100 -> 9.1613688 | AA6: ='T1'!X6/'T1'!X5*100-100 -> 9.3174233 | AB6: ='T1'!Y6/'T1'!Y5*100-100 -> -4.2307798 | AC6: ='T1'!Z6/'T1'!Z5*100-100 -> 8.430638
B7: 2009 | D7: ='T1'!D7/'T1'!D6*100-100 -> 10.209647 | E7: ='T1'!E7/'T1'!E6*100-100 -> 4.3665196 | F7: ='T1'!F7/'T1'!F6*100-100 -> 0.72021485 | G7: ='T1'!G7/'T1'!G6*100-100 -> -5.711463 | I7: ='T1'!H7/'T1'!H6*100-100 -> 6.751655 | J7: ='T1'!I7/'T1'!I6*100-100 -> -1.3056694 | K7: ='T1'!J7/'T1'!J6*100-100 -> 7.5043898 | L7: ='T1'!K7/'T1'!K6*100-100 -> 7.6501012 | M7: ='T1'!L7/'T1'!L6*100-100 -> 9.3355354 | O7: ='T1'!M7/'T1'!M6*100-100 -> 5.3917494 | P7: ='T1'!N7/'T1'!N6*100-100 -> -3.7785668 | Q7: ='T1'!O7/'T1'!O6*100-100 -> 4.4247859 | R7: ='T1'!P7/'T1'!P6*100-100 -> 3.8723543 | S7: ='T1'!Q7/'T1'!Q6*100-100 -> 9.3234826 | T7: ='T1'!R7/'T1'!R6*100-100 -> 2.4 | U7: ='T1'!S7/'T1'!S6*100-100 -> -1.5500616 | V7: ='T1'!T7/'T1'!T6*100-100 -> 11.687427 | ... Y7: ='T1'!W7/'T1'!W6*100-100 -> 7.4706981 | AA7: ='T1'!X7/'T1'!X6*100-100 -> 5.7845252 | AB7: ='T1'!Y7/'T1'!Y6*100-100 -> -25.194112 | AC7: ='T1'!Z7/'T1'!Z6*100-100 -> 3.9936182
B8: 2010 | D8: ='T1'!D8/'T1'!D7*100-100 -> 5.0000539 | E8: ='T1'!E8/'T1'!E7*100-100 -> 4.6493195 | F8: ='T1'!F8/'T1'!F7*100-100 -> 10.071289 | G8: ='T1'!G8/'T1'!G7*100-100 -> 1.4907404 | I8: ='T1'!H8/'T1'!H7*100-100 -> 7.642783 | J8: ='T1'!I8/'T1'!I7*100-100 -> 7.6004356 | K8: ='T1'!J8/'T1'!J7*100-100 -> 12.260229 | L8: ='T1'!K8/'T1'!K7*100-100 -> 5.2637697 | M8: ='T1'!L8/'T1'!L7*100-100 -> 2.5 | O8: ='T1'!M8/'T1'!M7*100-100 -> 13.340974 | P8: ='T1'!N8/'T1'!N7*100-100 -> 2.6877702 | Q8: ='T1'!O8/'T1'!O7*100-100 -> 8.0344345 | R8: ='T1'!P8/'T1'!P7*100-100 -> 24.471313 | S8: ='T1'!Q8/'T1'!Q7*100-100 -> 16.749669 | T8: ='T1'!R8/'T1'!R7*100-100 -> 2.4 | U8: ='T1'!S8/'T1'!S7*100-100 -> 23.101047 | V8: ='T1'!T8/'T1'!T7*100-100 -> 3.375451 | ... Y8: ='T1'!W8/'T1'!W7*100-100 -> 10.703466 | AA8: ='T1'!X8/'T1'!X7*100-100 -> 7.5945983 | AB8: ='T1'!Y8/'T1'!Y7*100-100 -> 10.54041 | AC8: ='T1'!Z8/'T1'!Z7*100-100 -> 7.7171007
B10: 2006 | C10: 1 | AF10: =D10+E10+F10+G10 -> 0 | AG10: =I10+J10+K10+L10+M10 -> 0 | AH10: =O10+P10+Q10+R10+S10+T10+U10+V10+W10+X10+Y10 -> 0
C11: 2 | D11: ='qly growth rates'!C6 -> #REF! | E11: ='qly growth rates'!D6 -> #REF! | F11: ='qly growth rates'!E6 -> #REF! | G11: ='qly growth rates'!F6 -> #REF! | I11: ='qly growth rates'!G6 -> #REF! | J11: ='qly growth rates'!H6 -> #REF! | K11: ='qly growth rates'!I6 -> #REF! | L11: ='qly growth rates'!J6 -> #REF! | M11: ='qly growth rates'!K6 -> #REF! | O11: ='qly growth rates'!L6 -> #REF! | P11: ='qly growth rates'!M6 -> #REF! | Q11: ='qly growth rates'!N6 -> #REF! | R11: ='qly growth rates'!O6 -> #REF! | S11: ='qly growth rates'!P6 -> #REF! | T11: ='qly growth rates'!Q6 -> #REF! | U11: ='qly growth rates'!R6 -> #REF! | V11: ='qly growth rates'!S6 -> #REF! | ... Y11: ='qly growth rates'!V6 -> #REF! | AA11: ='qly growth rates'!W6 -> #REF! | AB11: ='qly growth rates'!X6 -> #REF! | AC11: ='qly growth rates'!Y6 -> #REF! | AF11: ='T1'!AC11/'T1'!AC10*100-100 -> #REF! | AG11: ='T1'!AD11/'T1'!AD10*100-100 -> #REF! | AH11: ='T1'!AE11/'T1'!AE10*100-100 -> #REF!
C12: 3 | D12: ='qly growth rates'!C7 -> #REF! | E12: ='qly growth rates'!D7 -> #REF! | F12: ='qly growth rates'!E7 -> #REF! | G12: ='qly growth rates'!F7 -> #REF! | I12: ='qly growth rates'!G7 -> #REF! | J12: ='qly growth rates'!H7 -> #REF! | K12: ='qly growth rates'!I7 -> #REF! | L12: ='qly growth rates'!J7 -> #REF! | M12: ='qly growth rates'!K7 -> #REF! | O12: ='qly growth rates'!L7 -> #REF! | P12: ='qly growth rates'!M7 -> #REF! | Q12: ='qly growth rates'!N7 -> #REF! | R12: ='qly growth rates'!O7 -> #REF! | S12: ='qly growth rates'!P7 -> #REF! | T12: ='qly growth rates'!Q7 -> #REF! | U12: ='qly growth rates'!R7 -> #REF! | V12: ='qly growth rates'!S7 -> #REF! | ... Y12: ='qly growth rates'!V7 -> #REF! | AA12: ='qly growth rates'!W7 -> #REF! | AB12: ='qly growth rates'!X7 -> #REF! | AC12: ='qly growth rates'!Y7 -> #REF! | AF12: ='T1'!AC12/'T1'!AC11*100-100 -> #REF! | AG12: ='T1'!AD12/'T1'!AD11*100-100 -> #REF! | AH12: ='T1'!AE12/'T1'!AE11*100-100 -> #REF!
C13: 4 | D13: ='qly growth rates'!C8 -> #REF! | E13: ='qly growth rates'!D8 -> #REF! | F13: ='qly growth rates'!E8 -> #REF! | G13: ='qly growth rates'!F8 -> #REF! | I13: ='qly growth rates'!G8 -> #REF! | J13: ='qly growth rates'!H8 -> #REF! | K13: ='qly growth rates'!I8 -> #REF! | L13: ='qly growth rates'!J8 -> #REF! | M13: ='qly growth rates'!K8 -> #REF! | O13: ='qly growth rates'!L8 -> #REF! | P13: ='qly growth rates'!M8 -> #REF! | Q13: ='qly growth rates'!N8 -> #REF! | R13: ='qly growth rates'!O8 -> #REF! | S13: ='qly growth rates'!P8 -> #REF! | T13: ='qly growth rates'!Q8 -> #REF! | U13: ='qly growth rates'!R8 -> #REF! | V13: ='qly growth rates'!S8 -> #REF! | ... Y13: ='qly growth rates'!V8 -> #REF! | AA13: ='qly growth rates'!W8 -> #REF! | AB13: ='qly growth rates'!X8 -> #REF! | AC13: ='qly growth rates'!Y8 -> #REF! | AF13: ='T1'!AC13/'T1'!AC12*100-100 -> #REF! | AG13: ='T1'!AD13/'T1'!AD12*100-100 -> #REF! | AH13: ='T1'!AE13/'T1'!AE12*100-100 -> #REF!
B14: 2007 | C14: 1 | D14: ='qly growth rates'!C9 -> #REF! | E14: ='qly growth rates'!D9 -> #REF! | F14: ='qly growth rates'!E9 -> #REF! | G14: ='qly growth rates'!F9 -> #REF! | I14: ='qly growth rates'!G9 -> #REF! | J14: ='qly growth rates'!H9 -> #REF! | K14: ='qly growth rates'!I9 -> #REF! | L14: ='qly growth rates'!J9 -> #REF! | M14: ='qly growth rates'!K9 -> #REF! | O14: ='qly growth rates'!L9 -> #REF! | P14: ='qly growth rates'!M9 -> #REF! | Q14: ='qly growth rates'!N9 -> #REF! | R14: ='qly growth rates'!O9 -> #REF! | S14: ='qly growth rates'!P9 -> #REF! | T14: ='qly growth rates'!Q9 -> #REF! | U14: ='qly growth rates'!R9 -> #REF! | V14: ='qly growth rates'!S9 -> #REF! | ... Y14: ='qly growth rates'!V9 -> #REF! | AA14: ='qly growth rates'!W9 -> #REF! | AB14: ='qly growth rates'!X9 -> #REF! | AC14: ='qly growth rates'!Y9 -> #REF! | AF14: ='T1'!AC14/'T1'!AC13*100-100 -> #REF! | AG14: ='T1'!AD14/'T1'!AD13*100-100 -> #REF! | AH14: ='T1'!AE14/'T1'!AE13*100-100 -> #REF!
C15: 2 | D15: ='qly growth rates'!C10 -> #REF! | E15: ='qly growth rates'!D10 -> #REF! | F15: ='qly growth rates'!E10 -> #REF! | G15: ='qly growth rates'!F10 -> #REF! | I15: ='qly growth rates'!G10 -> #REF! | J15: ='qly growth rates'!H10 -> #REF! | K15: ='qly growth rates'!I10 -> #REF! | L15: ='qly growth rates'!J10 -> #REF! | M15: ='qly growth rates'!K10 -> #REF! | O15: ='qly growth rates'!L10 -> #REF! | P15: ='qly growth rates'!M10 -> #REF! | Q15: ='qly growth rates'!N10 -> #REF! | R15: ='qly growth rates'!O10 -> #REF! | S15: ='qly growth rates'!P10 -> #REF! | T15: ='qly growth rates'!Q10 -> #REF! | U15: ='qly growth rates'!R10 -> #REF! | V15: ='qly growth rates'!S10 -> #REF! | ... Y15: ='qly growth rates'!V10 -> #REF! | AA15: ='qly growth rates'!W10 -> #REF! | AB15: ='qly growth rates'!X10 -> #REF! | AC15: ='qly growth rates'!Y10 -> #REF! | AF15: ='T1'!AC15/'T1'!AC14*100-100 -> #REF! | AG15: ='T1'!AD15/'T1'!AD14*100-100 -> #REF! | AH15: ='T1'!AE15/'T1'!AE14*100-100 -> #REF!
C16: 3 | D16: ='qly growth rates'!C11 -> #REF! | E16: ='qly growth rates'!D11 -> #REF! | F16: ='qly growth rates'!E11 -> #REF! | G16: ='qly growth rates'!F11 -> #REF! | I16: ='qly growth rates'!G11 -> #REF! | J16: ='qly growth rates'!H11 -> #REF! | K16: ='qly growth rates'!I11 -> #REF! | L16: ='qly growth rates'!J11 -> #REF! | M16: ='qly growth rates'!K11 -> #REF! | O16: ='qly growth rates'!L11 -> #REF! | P16: ='qly growth rates'!M11 -> #REF! | Q16: ='qly growth rates'!N11 -> #REF! | R16: ='qly growth rates'!O11 -> #REF! | S16: ='qly growth rates'!P11 -> #REF! | T16: ='qly growth rates'!Q11 -> #REF! | U16: ='qly growth rates'!R11 -> #REF! | V16: ='qly growth rates'!S11 -> #REF! | ... Y16: ='qly growth rates'!V11 -> #REF! | AA16: ='qly growth rates'!W11 -> #REF! | AB16: ='qly growth rates'!X11 -> #REF! | AC16: ='qly growth rates'!Y11 -> #REF! | AF16: ='T1'!AC16/'T1'!AC15*100-100 -> #REF! | AG16: ='T1'!AD16/'T1'!AD15*100-100 -> #REF! | AH16: ='T1'!AE16/'T1'!AE15*100-100 -> #REF!
C17: 4 | D17: ='qly growth rates'!C12 -> #REF! | E17: ='qly growth rates'!D12 -> #REF! | F17: ='qly growth rates'!E12 -> #REF! | G17: ='qly growth rates'!F12 -> #REF! | I17: ='qly growth rates'!G12 -> #REF! | J17: ='qly growth rates'!H12 -> #REF! | K17: ='qly growth rates'!I12 -> #REF! | L17: ='qly growth rates'!J12 -> #REF! | M17: ='qly growth rates'!K12 -> #REF! | O17: ='qly growth rates'!L12 -> #REF! | P17: ='qly growth rates'!M12 -> #REF! | Q17: ='qly growth rates'!N12 -> #REF! | R17: ='qly growth rates'!O12 -> #REF! | S17: ='qly growth rates'!P12 -> #REF! | T17: ='qly growth rates'!Q12 -> #REF! | U17: ='qly growth rates'!R12 -> #REF! | V17: ='qly growth rates'!S12 -> #REF! | ... Y17: ='qly growth rates'!V12 -> #REF! | AA17: ='qly growth rates'!W12 -> #REF! | AB17: ='qly growth rates'!X12 -> #REF! | AC17: ='qly growth rates'!Y12 -> #REF! | AF17: ='T1'!AC17/'T1'!AC16*100-100 -> #REF! | AG17: ='T1'!AD17/'T1'!AD16*100-100 -> #REF! | AH17: ='T1'!AE17/'T1'!AE16*100-100 -> #REF!
B18: 2008 | C18: 1 | D18: ='qly growth rates'!C13 -> #REF! | E18: ='qly growth rates'!D13 -> #REF! | F18: ='qly growth rates'!E13 -> #REF! | G18: ='qly growth rates'!F13 -> #REF! | I18: ='qly growth rates'!G13 -> #REF! | J18: ='qly growth rates'!H13 -> #REF! | K18: ='qly growth rates'!I13 -> #REF! | L18: ='qly growth rates'!J13 -> #REF! | M18: ='qly growth rates'!K13 -> #REF! | O18: ='qly growth rates'!L13 -> #REF! | P18: ='qly growth rates'!M13 -> #REF! | Q18: ='qly growth rates'!N13 -> #REF! | R18: ='qly growth rates'!O13 -> #REF! | S18: ='qly growth rates'!P13 -> #REF! | T18: ='qly growth rates'!Q13 -> #REF! | U18: ='qly growth rates'!R13 -> #REF! | V18: ='qly growth rates'!S13 -> #REF! | ... Y18: ='qly growth rates'!V13 -> #REF! | AA18: ='qly growth rates'!W13 -> #REF! | AB18: ='qly growth rates'!X13 -> #REF! | AC18: ='qly growth rates'!Y13 -> #REF! | AF18: ='T1'!AC18/'T1'!AC17*100-100 -> #REF! | AG18: ='T1'!AD18/'T1'!AD17*100-100 -> #REF! | AH18: ='T1'!AE18/'T1'!AE17*100-100 -> #REF!
C19: 2 | D19: ='qly growth rates'!C14 -> #REF! | E19: ='qly growth rates'!D14 -> #REF! | F19: ='qly growth rates'!E14 -> #REF! | G19: ='qly growth rates'!F14 -> #REF! | I19: ='qly growth rates'!G14 -> #REF! | J19: ='qly growth rates'!H14 -> #REF! | K19: ='qly growth rates'!I14 -> #REF! | L19: ='qly growth rates'!J14 -> #REF! | M19: ='qly growth rates'!K14 -> #REF! | O19: ='qly growth rates'!L14 -> #REF! | P19: ='qly growth rates'!M14 -> #REF! | Q19: ='qly growth rates'!N14 -> #REF! | R19: ='qly growth rates'!O14 -> #REF! | S19: ='qly growth rates'!P14 -> #REF! | T19: ='qly growth rates'!Q14 -> #REF! | U19: ='qly growth rates'!R14 -> #REF! | V19: ='qly growth rates'!S14 -> #REF! | ... Y19: ='qly growth rates'!V14 -> #REF! | AA19: ='qly growth rates'!W14 -> #REF! | AB19: ='qly growth rates'!X14 -> #REF! | AC19: ='qly growth rates'!Y14 -> #REF! | AF19: ='T1'!AC19/'T1'!AC18*100-100 -> #REF! | AG19: ='T1'!AD19/'T1'!AD18*100-100 -> #REF! | AH19: ='T1'!AE19/'T1'!AE18*100-100 -> #REF!
C20: 3 | D20: ='qly growth rates'!C15 -> #REF! | E20: ='qly growth rates'!D15 -> #REF! | F20: ='qly growth rates'!E15 -> #REF! | G20: ='qly growth rates'!F15 -> #REF! | I20: ='qly growth rates'!G15 -> #REF! | J20: ='qly growth rates'!H15 -> #REF! | K20: ='qly growth rates'!I15 -> #REF! | L20: ='qly growth rates'!J15 -> #REF! | M20: ='qly growth rates'!K15 -> #REF! | O20: ='qly growth rates'!L15 -> #REF! | P20: ='qly growth rates'!M15 -> #REF! | Q20: ='qly growth rates'!N15 -> #REF! | R20: ='qly growth rates'!O15 -> #REF! | S20: ='qly growth rates'!P15 -> #REF! | T20: ='qly growth rates'!Q15 -> #REF! | U20: ='qly growth rates'!R15 -> #REF! | V20: ='qly growth rates'!S15 -> #REF! | ... Y20: ='qly growth rates'!V15 -> #REF! | AA20: ='qly growth rates'!W15 -> #REF! | AB20: ='qly growth rates'!X15 -> #REF! | AC20: ='qly growth rates'!Y15 -> #REF! | AF20: ='T1'!AC20/'T1'!AC19*100-100 -> #REF! | AG20: ='T1'!AD20/'T1'!AD19*100-100 -> #REF! | AH20: ='T1'!AE20/'T1'!AE19*100-100 -> #REF!
C21: 4 | D21: ='qly growth rates'!C16 -> #REF! | E21: ='qly growth rates'!D16 -> #REF! | F21: ='qly growth rates'!E16 -> #REF! | G21: ='qly growth rates'!F16 -> #REF! | I21: ='qly growth rates'!G16 -> #REF! | J21: ='qly growth rates'!H16 -> #REF! | K21: ='qly growth rates'!I16 -> #REF! | L21: ='qly growth rates'!J16 -> #REF! | M21: ='qly growth rates'!K16 -> #REF! | O21: ='qly growth rates'!L16 -> #REF! | P21: ='qly growth rates'!M16 -> #REF! | Q21: ='qly growth rates'!N16 -> #REF! | R21: ='qly growth rates'!O16 -> #REF! | S21: ='qly growth rates'!P16 -> #REF! | T21: ='qly growth rates'!Q16 -> #REF! | U21: ='qly growth rates'!R16 -> #REF! | V21: ='qly growth rates'!S16 -> #REF! | ... Y21: ='qly growth rates'!V16 -> #REF! | AA21: ='qly growth rates'!W16 -> #REF! | AB21: ='qly growth rates'!X16 -> #REF! | AC21: ='qly growth rates'!Y16 -> #REF! | AF21: ='T1'!AC21/'T1'!AC20*100-100 -> #REF! | AG21: ='T1'!AD21/'T1'!AD20*100-100 -> #REF! | AH21: ='T1'!AE21/'T1'!AE20*100-100 -> #REF!
B22: 2009 | C22: 1 | D22: ='qly growth rates'!C17 -> #REF! | E22: ='qly growth rates'!D17 -> #REF! | F22: ='qly growth rates'!E17 -> #REF! | G22: ='qly growth rates'!F17 -> #REF! | I22: ='qly growth rates'!G17 -> #REF! | J22: ='qly growth rates'!H17 -> #REF! | K22: ='qly growth rates'!I17 -> #REF! | L22: ='qly growth rates'!J17 -> #REF! | M22: ='qly growth rates'!K17 -> #REF! | O22: ='qly growth rates'!L17 -> #REF! | P22: ='qly growth rates'!M17 -> #REF! | Q22: ='qly growth rates'!N17 -> #REF! | R22: ='qly growth rates'!O17 -> #REF! | S22: ='qly growth rates'!P17 -> #REF! | T22: ='qly growth rates'!Q17 -> #REF! | U22: ='qly growth rates'!R17 -> #REF! | V22: ='qly growth rates'!S17 -> #REF! | ... Y22: ='qly growth rates'!V17 -> #REF! | AA22: ='qly growth rates'!W17 -> #REF! | AB22: ='qly growth rates'!X17 -> #REF! | AC22: ='qly growth rates'!Y17 -> #REF! | AF22: ='T1'!AC22/'T1'!AC21*100-100 -> #REF! | AG22: ='T1'!AD22/'T1'!AD21*100-100 -> #REF! | AH22: ='T1'!AE22/'T1'!AE21*100-100 -> #REF!
C23: 2 | D23: ='qly growth rates'!C18 -> #REF! | E23: ='qly growth rates'!D18 -> #REF! | F23: ='qly growth rates'!E18 -> #REF! | G23: ='qly growth rates'!F18 -> #REF! | I23: ='qly growth rates'!G18 -> #REF! | J23: ='qly growth rates'!H18 -> #REF! | K23: ='qly growth rates'!I18 -> #REF! | L23: ='qly growth rates'!J18 -> #REF! | M23: ='qly growth rates'!K18 -> #REF! | O23: ='qly growth rates'!L18 -> #REF! | P23: ='qly growth rates'!M18 -> #REF! | Q23: ='qly growth rates'!N18 -> #REF! | R23: ='qly growth rates'!O18 -> #REF! | S23: ='qly growth rates'!P18 -> #REF! | T23: ='qly growth rates'!Q18 -> #REF! | U23: ='qly growth rates'!R18 -> #REF! | V23: ='qly growth rates'!S18 -> #REF! | ... Y23: ='qly growth rates'!V18 -> #REF! | AA23: ='qly growth rates'!W18 -> #REF! | AB23: ='qly growth rates'!X18 -> #REF! | AC23: ='qly growth rates'!Y18 -> #REF! | AF23: ='T1'!AC23/'T1'!AC22*100-100 -> #REF! | AG23: ='T1'!AD23/'T1'!AD22*100-100 -> #REF! | AH23: ='T1'!AE23/'T1'!AE22*100-100 -> #REF!
C24: 3 | D24: ='qly growth rates'!C19 -> #REF! | E24: ='qly growth rates'!D19 -> #REF! | F24: ='qly growth rates'!E19 -> #REF! | G24: ='qly growth rates'!F19 -> #REF! | I24: ='qly growth rates'!G19 -> #REF! | J24: ='qly growth rates'!H19 -> #REF! | K24: ='qly growth rates'!I19 -> #REF! | L24: ='qly growth rates'!J19 -> #REF! | M24: ='qly growth rates'!K19 -> #REF! | O24: ='qly growth rates'!L19 -> #REF! | P24: ='qly growth rates'!M19 -> #REF! | Q24: ='qly growth rates'!N19 -> #REF! | R24: ='qly growth rates'!O19 -> #REF! | S24: ='qly growth rates'!P19 -> #REF! | T24: ='qly growth rates'!Q19 -> #REF! | U24: ='qly growth rates'!R19 -> #REF! | V24: ='qly growth rates'!S19 -> #REF! | ... Y24: ='qly growth rates'!V19 -> #REF! | AA24: ='qly growth rates'!W19 -> #REF! | AB24: ='qly growth rates'!X19 -> #REF! | AC24: ='qly growth rates'!Y19 -> #REF! | AF24: ='T1'!AC24/'T1'!AC23*100-100 -> #REF! | AG24: ='T1'!AD24/'T1'!AD23*100-100 -> #REF! | AH24: ='T1'!AE24/'T1'!AE23*100-100 -> #REF!
C25: 4 | D25: ='qly growth rates'!C20 -> #REF! | E25: ='qly growth rates'!D20 -> #REF! | F25: ='qly growth rates'!E20 -> #REF! | G25: ='qly growth rates'!F20 -> #REF! | I25: ='qly growth rates'!G20 -> #REF! | J25: ='qly growth rates'!H20 -> #REF! | K25: ='qly growth rates'!I20 -> #REF! | L25: ='qly growth rates'!J20 -> #REF! | M25: ='qly growth rates'!K20 -> #REF! | O25: ='qly growth rates'!L20 -> #REF! | P25: ='qly growth rates'!M20 -> #REF! | Q25: ='qly growth rates'!N20 -> #REF! | R25: ='qly growth rates'!O20 -> #REF! | S25: ='qly growth rates'!P20 -> #REF! | T25: ='qly growth rates'!Q20 -> #REF! | U25: ='qly growth rates'!R20 -> #REF! | V25: ='qly growth rates'!S20 -> #REF! | ... Y25: ='qly growth rates'!V20 -> #REF! | AA25: ='qly growth rates'!W20 -> #REF! | AB25: ='qly growth rates'!X20 -> #REF! | AC25: ='qly growth rates'!Y20 -> #REF! | AF25: ='T1'!AC25/'T1'!AC24*100-100 -> #REF! | AG25: ='T1'!AD25/'T1'!AD24*100-100 -> #REF! | AH25: ='T1'!AE25/'T1'!AE24*100-100 -> #REF!
B26: 2010 | C26: 1 | D26: ='qly growth rates'!C21 -> #REF! | E26: ='qly growth rates'!D21 -> #REF! | F26: ='qly growth rates'!E21 -> #REF! | G26: ='qly growth rates'!F21 -> #REF! | I26: ='qly growth rates'!G21 -> #REF! | J26: ='qly growth rates'!H21 -> #REF! | K26: ='qly growth rates'!I21 -> #REF! | L26: ='qly growth rates'!J21 -> #REF! | M26: ='qly growth rates'!K21 -> #REF! | O26: ='qly growth rates'!L21 -> #REF! | P26: ='qly growth rates'!M21 -> #REF! | Q26: ='qly growth rates'!N21 -> #REF! | R26: ='qly growth rates'!O21 -> #REF! | S26: ='qly growth rates'!P21 -> #REF! | T26: ='qly growth rates'!Q21 -> #REF! | U26: ='qly growth rates'!R21 -> #REF! | V26: ='qly growth rates'!S21 -> #REF! | ... Y26: ='qly growth rates'!V21 -> #REF! | AA26: ='qly growth rates'!W21 -> #REF! | AB26: ='qly growth rates'!X21 -> #REF! | AC26: ='qly growth rates'!Y21 -> #REF! | AF26: ='T1'!AC26/'T1'!AC25*100-100 -> #REF! | AG26: ='T1'!AD26/'T1'!AD25*100-100 -> #REF! | AH26: ='T1'!AE26/'T1'!AE25*100-100 -> #REF!
C27: 2 | D27: ='qly growth rates'!C22 -> #REF! | E27: ='qly growth rates'!D22 -> #REF! | F27: ='qly growth rates'!E22 -> #REF! | G27: ='qly growth rates'!F22 -> #REF! | I27: ='qly growth rates'!G22 -> #REF! | J27: ='qly growth rates'!H22 -> #REF! | K27: ='qly growth rates'!I22 -> #REF! | L27: ='qly growth rates'!J22 -> #REF! | M27: ='qly growth rates'!K22 -> #REF! | O27: ='qly growth rates'!L22 -> #REF! | P27: ='qly growth rates'!M22 -> #REF! | Q27: ='qly growth rates'!N22 -> #REF! | R27: ='qly growth rates'!O22 -> #REF! | S27: ='qly growth rates'!P22 -> #REF! | T27: ='qly growth rates'!Q22 -> #REF! | U27: ='qly growth rates'!R22 -> #REF! | V27: ='qly growth rates'!S22 -> #REF! | ... Y27: ='qly growth rates'!V22 -> #REF! | AA27: ='qly growth rates'!W22 -> #REF! | AB27: ='qly growth rates'!X22 -> #REF! | AC27: ='qly growth rates'!Y22 -> #REF! | AF27: ='T1'!AC27/'T1'!AC26*100-100 -> #REF! | AG27: ='T1'!AD27/'T1'!AD26*100-100 -> #REF! | AH27: ='T1'!AE27/'T1'!AE26*100-100 -> #REF!
C28: 3 | D28: ='qly growth rates'!C23 -> #REF! | E28: ='qly growth rates'!D23 -> #REF! | F28: ='qly growth rates'!E23 -> #REF! | G28: ='qly growth rates'!F23 -> #REF! | I28: ='qly growth rates'!G23 -> #REF! | J28: ='qly growth rates'!H23 -> #REF! | K28: ='qly growth rates'!I23 -> #REF! | L28: ='qly growth rates'!J23 -> #REF! | M28: ='qly growth rates'!K23 -> #REF! | O28: ='qly growth rates'!L23 -> #REF! | P28: ='qly growth rates'!M23 -> #REF! | Q28: ='qly growth rates'!N23 -> #REF! | R28: ='qly growth rates'!O23 -> #REF! | S28: ='qly growth rates'!P23 -> #REF! | T28: ='qly growth rates'!Q23 -> #REF! | U28: ='qly growth rates'!R23 -> #REF! | V28: ='qly growth rates'!S23 -> #REF! | ... Y28: ='qly growth rates'!V23 -> #REF! | AA28: ='qly growth rates'!W23 -> #REF! | AB28: ='qly growth rates'!X23 -> #REF! | AC28: ='qly growth rates'!Y23 -> #REF! | AF28: ='T1'!AC28/'T1'!AC27*100-100 -> #REF! | AG28: ='T1'!AD28/'T1'!AD27*100-100 -> #REF! | AH28: ='T1'!AE28/'T1'!AE27*100-100 -> #REF!
C29: 4 | D29: ='qly growth rates'!C24 -> #REF! | E29: ='qly growth rates'!D24 -> #REF! | F29: ='qly growth rates'!E24 -> #REF! | G29: ='qly growth rates'!F24 -> #REF! | I29: ='qly growth rates'!G24 -> #REF! | J29: ='qly growth rates'!H24 -> #REF! | K29: ='qly growth rates'!I24 -> #REF! | L29: ='qly growth rates'!J24 -> #REF! | M29: ='qly growth rates'!K24 -> #REF! | O29: ='qly growth rates'!L24 -> #REF! | P29: ='qly growth rates'!M24 -> #REF! | Q29: ='qly growth rates'!N24 -> #REF! | R29: ='qly growth rates'!O24 -> #REF! | S29: ='qly growth rates'!P24 -> #REF! | T29: ='qly growth rates'!Q24 -> #REF! | U29: ='qly growth rates'!R24 -> #REF! | V29: ='qly growth rates'!S24 -> #REF! | ... Y29: ='qly growth rates'!V24 -> #REF! | AA29: ='qly growth rates'!W24 -> #REF! | AB29: ='qly growth rates'!X24 -> #REF! | AC29: ='qly growth rates'!Y24 -> #REF! | AF29: ='T1'!AC29/'T1'!AC28*100-100 -> #REF! | AG29: ='T1'!AD29/'T1'!AD28*100-100 -> #REF! | AH29: ='T1'!AE29/'T1'!AE28*100-100 -> #REF!
B30: 2011 | C30: 1 | D30: ='qly growth rates'!C25 -> #REF! | E30: ='qly growth rates'!D25 -> #REF! | F30: ='qly growth rates'!E25 -> #REF! | G30: ='qly growth rates'!F25 -> #REF! | I30: ='qly growth rates'!G25 -> #REF! | J30: ='qly growth rates'!H25 -> #REF! | K30: ='qly growth rates'!I25 -> #REF! | L30: ='qly growth rates'!J25 -> #REF! | M30: ='qly growth rates'!K25 -> #REF! | O30: ='qly growth rates'!L25 -> #REF! | P30: ='qly growth rates'!M25 -> #REF! | Q30: ='qly growth rates'!N25 -> #REF! | R30: ='qly growth rates'!O25 -> #REF! | S30: ='qly growth rates'!P25 -> #REF! | T30: ='qly growth rates'!Q25 -> #REF! | U30: ='qly growth rates'!R25 -> #REF! | V30: ='qly growth rates'!S25 -> #REF! | ... Y30: ='qly growth rates'!V25 -> #REF! | AA30: ='qly growth rates'!W25 -> #REF! | AB30: ='qly growth rates'!X25 -> #REF! | AC30: ='qly growth rates'!Y25 -> #REF! | AF30: ='T1'!AC30/'T1'!AC29*100-100 -> #REF! | AG30: ='T1'!AD30/'T1'!AD29*100-100 -> #REF! | AH30: ='T1'!AE30/'T1'!AE29*100-100 -> #REF!
C31: 2 | D31: ='qly growth rates'!C26 -> #REF! | E31: ='qly growth rates'!D26 -> #REF! | F31: ='qly growth rates'!E26 -> #REF! | G31: ='qly growth rates'!F26 -> #REF! | I31: ='qly growth rates'!G26 -> #REF! | J31: ='qly growth rates'!H26 -> #REF! | K31: ='qly growth rates'!I26 -> #REF! | L31: ='qly growth rates'!J26 -> #REF! | M31: ='qly growth rates'!K26 -> #REF! | O31: ='qly growth rates'!L26 -> #REF! | P31: ='qly growth rates'!M26 -> #REF! | Q31: ='qly growth rates'!N26 -> #REF! | R31: ='qly growth rates'!O26 -> #REF! | S31: ='qly growth rates'!P26 -> #REF! | T31: ='qly growth rates'!Q26 -> #REF! | U31: ='qly growth rates'!R26 -> #REF! | V31: ='qly growth rates'!S26 -> #REF! | ... Y31: ='qly growth rates'!V26 -> #REF! | AA31: ='qly growth rates'!W26 -> #REF! | AB31: ='qly growth rates'!X26 -> #REF! | AC31: ='qly growth rates'!Y26 -> #REF! | AF31: ='T1'!AC31/'T1'!AC30*100-100 -> #REF! | AG31: ='T1'!AD31/'T1'!AD30*100-100 -> #REF! | AH31: ='T1'!AE31/'T1'!AE30*100-100 -> #REF!
C32: 3* | D32: ='qly growth rates'!C27 -> #REF! | E32: ='qly growth rates'!D27 -> #REF! | F32: ='qly growth rates'!E27 -> #REF! | G32: ='qly growth rates'!F27 -> #REF! | I32: ='qly growth rates'!G27 -> #REF! | J32: ='qly growth rates'!H27 -> #REF! | K32: ='qly growth rates'!I27 -> #REF! | L32: ='qly growth rates'!J27 -> #REF! | M32: ='qly growth rates'!K27 -> #REF! | O32: ='qly growth rates'!L27 -> #REF! | P32: ='qly growth rates'!M27 -> #REF! | Q32: ='qly growth rates'!N27 -> #REF! | R32: ='qly growth rates'!O27 -> #REF! | S32: ='qly growth rates'!P27 -> #REF! | T32: ='qly growth rates'!Q27 -> #REF! | U32: ='qly growth rates'!R27 -> #REF! | V32: ='qly growth rates'!S27 -> #REF! | ... Y32: ='qly growth rates'!V27 -> #REF! | AA32: ='qly growth rates'!W27 -> #REF! | AB32: ='qly growth rates'!X27 -> #REF! | AC32: ='qly growth rates'!Y27 -> #REF! | AF32: ='T1'!AC32/'T1'!AC31*100-100 -> #REF! | AG32: ='T1'!AD32/'T1'!AD31*100-100 -> #REF! | AH32: ='T1'!AE32/'T1'!AE31*100-100 -> #REF!
C33: 4* | D33: ='qly growth rates'!C28 -> 0 | E33: ='qly growth rates'!D28 -> 0 | F33: ='qly growth rates'!E28 -> 0 | G33: ='qly growth rates'!F28 -> 0 | I33: ='qly growth rates'!G28 -> 0 | J33: ='qly growth rates'!H28 -> 0 | K33: ='qly growth rates'!I28 -> 0 | L33: ='qly growth rates'!J28 -> 0 | M33: ='qly growth rates'!K28 -> 0 | O33: ='qly growth rates'!L28 -> 0 | P33: ='qly growth rates'!M28 -> 0 | Q33: ='qly growth rates'!N28 -> 0 | R33: ='qly growth rates'!O28 -> 0 | S33: ='qly growth rates'!P28 -> 0 | T33: ='qly growth rates'!Q28 -> 0 | U33: ='qly growth rates'!R28 -> 0 | V33: ='qly growth rates'!S28 -> 0 | ... Y33: ='qly growth rates'!V28 -> 0 | AA33: ='qly growth rates'!W28 -> 0 | AB33: ='qly growth rates'!X28 -> 0 | AC33: ='qly growth rates'!Y28 -> 0 | AF33: ='T1'!AC33/'T1'!AC32*100-100 -> #REF! | AG33: ='T1'!AD33/'T1'!AD32*100-100 -> #REF! | AH33: ='T1'!AE33/'T1'!AE32*100-100 -> #DIV/0!
B34: 2012 | C34: 1* | D34: ='qly growth rates'!C29 -> 0 | E34: ='qly growth rates'!D29 -> 0 | F34: ='qly growth rates'!E29 -> 0 | G34: ='qly growth rates'!F29 -> 0 | I34: ='qly growth rates'!G29 -> 0 | J34: ='qly growth rates'!H29 -> 0 | K34: ='qly growth rates'!I29 -> 0 | L34: ='qly growth rates'!J29 -> 0 | M34: ='qly growth rates'!K29 -> 0 | O34: ='qly growth rates'!L29 -> 0 | P34: ='qly growth rates'!M29 -> 0 | Q34: ='qly growth rates'!N29 -> 0 | R34: ='qly growth rates'!O29 -> 0 | S34: ='qly growth rates'!P29 -> 0 | T34: ='qly growth rates'!Q29 -> 0 | U34: ='qly growth rates'!R29 -> 0 | V34: ='qly growth rates'!S29 -> 0 | ... Y34: ='qly growth rates'!V29 -> 0 | AA34: ='qly growth rates'!W29 -> 0 | AB34: ='qly growth rates'!X29 -> 0 | AC34: ='qly growth rates'!Y29 -> 0
B36: * provisional

Sheet T3
B1: Table 3 - Percentage Changes (Year-on-Year) in the Quarterly Value Added by Activity and Gross Domestic Product at Constant 2006 Prices
D2: Agriculture Sector | H2: Industry Sector | M2: Services Sector
B3: Year 1) | C3: Quarter 2) | D3: Crops & Cocoa | E3: Livestock | F3: Forestry | G3: Fishing | H3: Mining and Quarrying | I3: Manufacturing | J3: Electricity | K3: Water & Sewerage | L3: Construction | M3: Trade; Repair Of Vehicles, Household Goods | N3: Hotels And Restaurants | O3: Transport & Storage | P3: Information & Communication | Q3: Financial & Insurance Activities | R3: Real Estate Activities | S3: Business & other Services Activities | T3: Public Administration | U3: Education | V3: Health | W3: Other Personal Service Activities | X3: Total Value Added | Y3: Net Taxes | Z3: GDP at Constant Prices | AC3: Agric | AD3: Ind | AE3: Serv
B4: 2006
B5: 2007 | D5: ='T1'!D5/'T1'!D4*100-100 -> -1.346605 | E5: ='T1'!E5/'T1'!E4*100-100 -> 4.7316467 | F5: ='T1'!F5/'T1'!F4*100-100 -> -4.0926214 | G5: ='T1'!G5/'T1'!G4*100-100 -> -7.2472487 | H5: ='T1'!H5/'T1'!H4*100-100 -> 6.8620818 | I5: ='T1'!I5/'T1'!I4*100-100 -> -1.2158585 | J5: ='T1'!J5/'T1'!J4*100-100 -> -17.212572 | K5: ='T1'!K5/'T1'!K4*100-100 -> 1.161077 | ... Z5: ='T1'!Z5/'T1'!Z4*100-100 -> 6.459768
B6: 2008 | D6: ='T1'!D6/'T1'!D5*100-100 -> 8.6 | E6: ='T1'!E6/'T1'!E5*100-100 -> 5.1039655 | F6: ='T1'!F6/'T1'!F5*100-100 -> -3.3201314 | G6: ='T1'!G6/'T1'!G5*100-100 -> 17.380777 | H6: ='T1'!H6/'T1'!H5*100-100 -> 2.4193735 | I6: ='T1'!I6/'T1'!I5*100-100 -> 3.7004754 | J6: ='T1'!J6/'T1'!J5*100-100 -> 19.423493 | K6: ='T1'!K6/'T1'!K5*100-100 -> 0.84657122 | ... Z6: ='T1'!Z6/'T1'!Z5*100-100 -> 8.430638
B7: 2009 | D7: ='T1'!D7/'T1'!D6*100-100 -> 10.209647 | E7: ='T1'!E7/'T1'!E6*100-100 -> 4.3665196 | F7: ='T1'!F7/'T1'!F6*100-100 -> 0.72021485 | G7: ='T1'!G7/'T1'!G6*100-100 -> -5.711463 | H7: ='T1'!H7/'T1'!H6*100-100 -> 6.751655 | I7: ='T1'!I7/'T1'!I6*100-100 -> -1.3056694 | J7: ='T1'!J7/'T1'!J6*100-100 -> 7.5043898 | K7: ='T1'!K7/'T1'!K6*100-100 -> 7.6501012 | ... Z7: ='T1'!Z7/'T1'!Z6*100-100 -> 3.9936182
B8: 2010 | D8: ='T1'!D8/'T1'!D7*100-100 -> 5.0000539 | E8: ='T1'!E8/'T1'!E7*100-100 -> 4.6493195 | F8: ='T1'!F8/'T1'!F7*100-100 -> 10.071289 | G8: ='T1'!G8/'T1'!G7*100-100 -> 1.4907404 | H8: ='T1'!H8/'T1'!H7*100-100 -> 7.642783 | I8: ='T1'!I8/'T1'!I7*100-100 -> 7.6004356 | J8: ='T1'!J8/'T1'!J7*100-100 -> 12.260229 | K8: ='T1'!K8/'T1'!K7*100-100 -> 5.2637697 | ... Z8: ='T1'!Z8/'T1'!Z7*100-100 -> 7.7171007
B10: 2006 | C10: 1 | AC10: =D10+E10+F10+G10 -> 0 | AD10: =H10+I10+J10+K10+L10 -> 0 | AE10: =M10+N10+O10+P10+Q10+R10+S10+T10+U10+V10+W10 -> 0
C11: 2 | AC11: ='T4'!AC11/'T4'!AC10*100-100 -> #REF! | AD11: ='T4'!AD11/'T4'!AD10*100-100 -> #REF! | AE11: ='T4'!AE11/'T4'!AE10*100-100 -> #REF!
C12: 3
C13: 4
B14: 2007 | C14: 1 | D14: =YYgrowthrates!C9 -> #REF! | E14: =YYgrowthrates!D9 -> #REF! | F14: =YYgrowthrates!E9 -> #REF! | G14: =YYgrowthrates!F9 -> #REF! | H14: =YYgrowthrates!G9 -> #REF! | I14: =YYgrowthrates!H9 -> #REF! | J14: =YYgrowthrates!I9 -> #REF! | K14: =YYgrowthrates!J9 -> #REF! | ... Z14: =YYgrowthrates!Y9 -> #REF! | AC14: ='T1'!AC14/'T1'!AC10*100-100 -> #REF! | AD14: ='T1'!AD14/'T1'!AD10*100-100 -> #REF!
C15: 2 | D15: =YYgrowthrates!C10 -> #REF! | E15: =YYgrowthrates!D10 -> #REF! | F15: =YYgrowthrates!E10 -> #REF! | G15: =YYgrowthrates!F10 -> #REF! | H15: =YYgrowthrates!G10 -> #REF! | I15: =YYgrowthrates!H10 -> #REF! | J15: =YYgrowthrates!I10 -> #REF! | K15: =YYgrowthrates!J10 -> #REF! | ... Z15: =YYgrowthrates!Y10 -> #REF! | AC15: ='T1'!AC15/'T1'!AC11*100-100 -> #REF! | AD15: ='T1'!AD15/'T1'!AD11*100-100 -> #REF! | AE15: ='T1'!AE15/'T1'!AE11*100-100 -> #REF!
C16: 3 | D16: =YYgrowthrates!C11 -> #REF! | E16: =YYgrowthrates!D11 -> #REF! | F16: =YYgrowthrates!E11 -> #REF! | G16: =YYgrowthrates!F11 -> #REF! | H16: =YYgrowthrates!G11 -> #REF! | I16: =YYgrowthrates!H11 -> #REF! | J16: =YYgrowthrates!I11 -> #REF! | K16: =YYgrowthrates!J11 -> #REF! | ... Z16: =YYgrowthrates!Y11 -> #REF! | AC16: ='T1'!AC16/'T1'!AC12*100-100 -> #REF! | AD16: ='T1'!AD16/'T1'!AD12*100-100 -> #REF! | AE16: ='T1'!AE16/'T1'!AE12*100-100 -> #REF!
C17: 4 | D17: =YYgrowthrates!C12 -> #REF! | E17: =YYgrowthrates!D12 -> #REF! | F17: =YYgrowthrates!E12 -> #REF! | G17: =YYgrowthrates!F12 -> #REF! | H17: =YYgrowthrates!G12 -> #REF! | I17: =YYgrowthrates!H12 -> #REF! | J17: =YYgrowthrates!I12 -> #REF! | K17: =YYgrowthrates!J12 -> #REF! | ... Z17: =YYgrowthrates!Y12 -> #REF! | AC17: ='T1'!AC17/'T1'!AC13*100-100 -> #REF! | AD17: ='T1'!AD17/'T1'!AD13*100-100 -> #REF! | AE17: ='T1'!AE17/'T1'!AE13*100-100 -> #REF!
B18: 2008 | C18: 1 | D18: =YYgrowthrates!C13 -> #REF! | E18: =YYgrowthrates!D13 -> #REF! | F18: =YYgrowthrates!E13 -> #REF! | G18: =YYgrowthrates!F13 -> #REF! | H18: =YYgrowthrates!G13 -> #REF! | I18: =YYgrowthrates!H13 -> #REF! | J18: =YYgrowthrates!I13 -> #REF! | K18: =YYgrowthrates!J13 -> #REF! | ... Z18: =YYgrowthrates!Y13 -> #REF! | AC18: ='T1'!AC18/'T1'!AC14*100-100 -> #REF! | AD18: ='T1'!AD18/'T1'!AD14*100-100 -> #REF! | AE18: ='T1'!AE18/'T1'!AE14*100-100 -> #REF!
C19: 2 | D19: =YYgrowthrates!C14 -> #REF! | E19: =YYgrowthrates!D14 -> #REF! | F19: =YYgrowthrates!E14 -> #REF! | G19: =YYgrowthrates!F14 -> #REF! | H19: =YYgrowthrates!G14 -> #REF! | I19: =YYgrowthrates!H14 -> #REF! | J19: =YYgrowthrates!I14 -> #REF! | K19: =YYgrowthrates!J14 -> #REF! | ... Z19: =YYgrowthrates!Y14 -> #REF! | AC19: ='T1'!AC19/'T1'!AC15*100-100 -> #REF! | AD19: ='T1'!AD19/'T1'!AD15*100-100 -> #REF! | AE19: ='T1'!AE19/'T1'!AE15*100-100 -> #REF!
C20: 3 | D20: =YYgrowthrates!C15 -> #REF! | E20: =YYgrowthrates!D15 -> #REF! | F20: =YYgrowthrates!E15 -> #REF! | G20: =YYgrowthrates!F15 -> #REF! | H20: =YYgrowthrates!G15 -> #REF! | I20: =YYgrowthrates!H15 -> #REF! | J20: =YYgrowthrates!I15 -> #REF! | K20: =YYgrowthrates!J15 -> #REF! | ... Z20: =YYgrowthrates!Y15 -> #REF! | AC20: ='T1'!AC20/'T1'!AC16*100-100 -> #REF! | AD20: ='T1'!AD20/'T1'!AD16*100-100 -> #REF! | AE20: ='T1'!AE20/'T1'!AE16*100-100 -> #REF!
C21: 4 | D21: =YYgrowthrates!C16 -> #REF! | E21: =YYgrowthrates!D16 -> #REF! | F21: =YYgrowthrates!E16 -> #REF! | G21: =YYgrowthrates!F16 -> #REF! | H21: =YYgrowthrates!G16 -> #REF! | I21: =YYgrowthrates!H16 -> #REF! | J21: =YYgrowthrates!I16 -> #REF! | K21: =YYgrowthrates!J16 -> #REF! | ... Z21: =YYgrowthrates!Y16 -> #REF! | AC21: ='T1'!AC21/'T1'!AC17*100-100 -> #REF! | AD21: ='T1'!AD21/'T1'!AD17*100-100 -> #REF! | AE21: ='T1'!AE21/'T1'!AE17*100-100 -> #REF!
B22: 2009 | C22: 1 | D22: =YYgrowthrates!C17 -> #REF! | E22: =YYgrowthrates!D17 -> #REF! | F22: =YYgrowthrates!E17 -> #REF! | G22: =YYgrowthrates!F17 -> #REF! | H22: =YYgrowthrates!G17 -> #REF! | I22: =YYgrowthrates!H17 -> #REF! | J22: =YYgrowthrates!I17 -> #REF! | K22: =YYgrowthrates!J17 -> #REF! | ... Z22: =YYgrowthrates!Y17 -> #REF! | AC22: ='T1'!AC22/'T1'!AC18*100-100 -> #REF! | AD22: ='T1'!AD22/'T1'!AD18*100-100 -> #REF! | AE22: ='T1'!AE22/'T1'!AE18*100-100 -> #REF!
C23: 2 | D23: =YYgrowthrates!C18 -> #REF! | E23: =YYgrowthrates!D18 -> #REF! | F23: =YYgrowthrates!E18 -> #REF! | G23: =YYgrowthrates!F18 -> #REF! | H23: =YYgrowthrates!G18 -> #REF! | I23: =YYgrowthrates!H18 -> #REF! | J23: =YYgrowthrates!I18 -> #REF! | K23: =YYgrowthrates!J18 -> #REF! | ... Z23: =YYgrowthrates!Y18 -> #REF! | AC23: ='T1'!AC23/'T1'!AC19*100-100 -> #REF! | AD23: ='T1'!AD23/'T1'!AD19*100-100 -> #REF! | AE23: ='T1'!AE23/'T1'!AE19*100-100 -> #REF!
C24: 3 | D24: =YYgrowthrates!C19 -> #REF! | E24: =YYgrowthrates!D19 -> #REF! | F24: =YYgrowthrates!E19 -> #REF! | G24: =YYgrowthrates!F19 -> #REF! | H24: =YYgrowthrates!G19 -> #REF! | I24: =YYgrowthrates!H19 -> #REF! | J24: =YYgrowthrates!I19 -> #REF! | K24: =YYgrowthrates!J19 -> #REF! | ... Z24: =YYgrowthrates!Y19 -> #REF! | AC24: ='T1'!AC24/'T1'!AC20*100-100 -> #REF! | AD24: ='T1'!AD24/'T1'!AD20*100-100 -> #REF! | AE24: ='T1'!AE24/'T1'!AE20*100-100 -> #REF!
C25: 4 | D25: =YYgrowthrates!C20 -> #REF! | E25: =YYgrowthrates!D20 -> #REF! | F25: =YYgrowthrates!E20 -> #REF! | G25: =YYgrowthrates!F20 -> #REF! | H25: =YYgrowthrates!G20 -> #REF! | I25: =YYgrowthrates!H20 -> #REF! | J25: =YYgrowthrates!I20 -> #REF! | K25: =YYgrowthrates!J20 -> #REF! | ... Z25: =YYgrowthrates!Y20 -> #REF! | AC25: ='T1'!AC25/'T1'!AC21*100-100 -> #REF! | AD25: ='T1'!AD25/'T1'!AD21*100-100 -> #REF! | AE25: ='T1'!AE25/'T1'!AE21*100-100 -> #REF!
B26: 2010 | C26: 1 | D26: =YYgrowthrates!C21 -> #REF! | E26: =YYgrowthrates!D21 -> #REF! | F26: =YYgrowthrates!E21 -> #REF! | G26: =YYgrowthrates!F21 -> #REF! | H26: =YYgrowthrates!G21 -> #REF! | I26: =YYgrowthrates!H21 -> #REF! | J26: =YYgrowthrates!I21 -> #REF! | K26: =YYgrowthrates!J21 -> #REF! | ... Z26: =YYgrowthrates!Y21 -> #REF! | AC26: ='T1'!AC26/'T1'!AC22*100-100 -> #REF! | AD26: ='T1'!AD26/'T1'!AD22*100-100 -> #REF! | AE26: ='T1'!AE26/'T1'!AE22*100-100 -> #REF!
C27: 2 | D27: =YYgrowthrates!C22 -> #REF! | E27: =YYgrowthrates!D22 -> #REF! | F27: =YYgrowthrates!E22 -> #REF! | G27: =YYgrowthrates!F22 -> #REF! | H27: =YYgrowthrates!G22 -> #REF! | I27: =YYgrowthrates!H22 -> #REF! | J27: =YYgrowthrates!I22 -> #REF! | K27: =YYgrowthrates!J22 -> #REF! | ... Z27: =YYgrowthrates!Y22 -> #REF! | AC27: ='T1'!AC27/'T1'!AC23*100-100 -> #REF! | AD27: ='T1'!AD27/'T1'!AD23*100-100 -> #REF! | AE27: ='T1'!AE27/'T1'!AE23*100-100 -> #REF!
C28: 3 | D28: =YYgrowthrates!C23 -> #REF! | E28: =YYgrowthrates!D23 -> #REF! | F28: =YYgrowthrates!E23 -> #REF! | G28: =YYgrowthrates!F23 -> #REF! | H28: =YYgrowthrates!G23 -> #REF! | I28: =YYgrowthrates!H23 -> #REF! | J28: =YYgrowthrates!I23 -> #REF! | K28: =YYgrowthrates!J23 -> #REF! | ... Z28: =YYgrowthrates!Y23 -> #REF! | AC28: ='T1'!AC28/'T1'!AC24*100-100 -> #REF! | AD28: ='T1'!AD28/'T1'!AD24*100-100 -> #REF! | AE28: ='T1'!AE28/'T1'!AE24*100-100 -> #REF!
C29: 4 | D29: =YYgrowthrates!C24 -> #REF! | E29: =YYgrowthrates!D24 -> #REF! | F29: =YYgrowthrates!E24 -> #REF! | G29: =YYgrowthrates!F24 -> #REF! | H29: =YYgrowthrates!G24 -> #REF! | I29: =YYgrowthrates!H24 -> #REF! | J29: =YYgrowthrates!I24 -> #REF! | K29: =YYgrowthrates!J24 -> #REF! | ... Z29: =YYgrowthrates!Y24 -> #REF! | AC29: ='T1'!AC29/'T1'!AC25*100-100 -> #REF! | AD29: ='T1'!AD29/'T1'!AD25*100-100 -> #REF! | AE29: ='T1'!AE29/'T1'!AE25*100-100 -> #REF!
B30: 2011 | C30: 1 | D30: =YYgrowthrates!C25 -> #REF! | E30: =YYgrowthrates!D25 -> #REF! | F30: =YYgrowthrates!E25 -> #REF! | G30: =YYgrowthrates!F25 -> #REF! | H30: =YYgrowthrates!G25 -> #REF! | I30: =YYgrowthrates!H25 -> #REF! | J30: =YYgrowthrates!I25 -> #REF! | K30: =YYgrowthrates!J25 -> #REF! | ... Z30: =YYgrowthrates!Y25 -> #REF! | AC30: ='T1'!AC30/'T1'!AC26*100-100 -> #REF! | AD30: ='T1'!AD30/'T1'!AD26*100-100 -> #REF! | AE30: ='T1'!AE30/'T1'!AE26*100-100 -> #REF!
C31: 2 | D31: =YYgrowthrates!C26 -> #REF! | E31: =YYgrowthrates!D26 -> #REF! | F31: =YYgrowthrates!E26 -> #REF! | G31: =YYgrowthrates!F26 -> #REF! | H31: =YYgrowthrates!G26 -> #REF! | I31: =YYgrowthrates!H26 -> #REF! | J31: =YYgrowthrates!I26 -> #REF! | K31: =YYgrowthrates!J26 -> #REF! | ... Z31: =YYgrowthrates!Y26 -> #REF! | AC31: ='T1'!AC31/'T1'!AC27*100-100 -> #REF! | AD31: ='T1'!AD31/'T1'!AD27*100-100 -> #REF! | AE31: ='T1'!AE31/'T1'!AE27*100-100 -> #REF!
C32: 3* | D32: =YYgrowthrates!C27 -> #REF! | E32: =YYgrowthrates!D27 -> #REF! | F32: =YYgrowthrates!E27 -> #REF! | G32: =YYgrowthrates!F27 -> #REF! | H32: =YYgrowthrates!G27 -> #REF! | I32: =YYgrowthrates!H27 -> #REF! | J32: =YYgrowthrates!I27 -> #REF! | K32: =YYgrowthrates!J27 -> #REF! | ... Z32: =YYgrowthrates!Y27 -> #REF! | AC32: ='T1'!AC32/'T1'!AC28*100-100 -> #REF! | AD32: ='T1'!AD32/'T1'!AD28*100-100 -> #REF! | AE32: ='T1'!AE32/'T1'!AE28*100-100 -> #REF!
C33: 4* | D33: =YYgrowthrates!C28 -> 0 | E33: =YYgrowthrates!D28 -> 0 | F33: =YYgrowthrates!E28 -> 0 | G33: =YYgrowthrates!F28 -> 0 | H33: =YYgrowthrates!G28 -> 0 | I33: =YYgrowthrates!H28 -> 0 | J33: =YYgrowthrates!I28 -> 0 | K33: =YYgrowthrates!J28 -> 0 | ... Z33: =YYgrowthrates!Y28 -> 0 | AC33: ='T1'!AC33/'T1'!AC29*100-100 -> #REF! | AD33: ='T1'!AD33/'T1'!AD29*100-100 -> #REF! | AE33: ='T1'!AE33/'T1'!AE29*100-100 -> #REF!
B34: 2012 | C34: 1* | D34: =YYgrowthrates!C29 -> 0 | E34: =YYgrowthrates!D29 -> 0 | F34: =YYgrowthrates!E29 -> 0 | G34: =YYgrowthrates!F29 -> 0 | H34: =YYgrowthrates!G29 -> 0 | I34: =YYgrowthrates!H29 -> 0 | J34: =YYgrowthrates!I29 -> 0 | K34: =YYgrowthrates!J29 -> 0 | ... Z34: =YYgrowthrates!Y29 -> 0
B36: * provisional
B38: 1) The percentage change is the growth rate for a given year compared with the previous year
B39: 2) The percentage change is the growth rate for a given quarter compared with the same quarter in the previous year

Sheet T4
B1: Table 4 - Seasonal Adjusted Quarterly Gross Value Added by Activity at Constant 2006 Prices (GHc Million)
D2: Agriculture Sector | H2: Industry Sector | M2: Services Sector
B3: Year | C3: Quarter | D3: Crops & Cocoa | E3: Livestock | F3: Forestry | G3: Fishing | H3: Mining and Quarrying | I3: Manufacturing | J3: Electricity | K3: Water & Sewerage | L3: Construction | M3: Trade; Repair Of Vehicles, Household Goods | N3: Hotels And Restaurants | O3: Transport & Storage | P3: Information & Communication | Q3: Financial & Insurance Activities | R3: Real Estate Activities | S3: Business & other Services Activities | T3: Public Administration | U3: Education | V3: Health | W3: Other Personal Service Activities | X3: Total Value Added at Basis Prices | Y3: Net Taxes | Z3: GDP at Constant Prices | AC3: Agric | AD3: Ind | AE3: Serv | AF3: controle
B10: 2006 | C10: 1 | D10: =#REF! -> #REF! | E10: =#REF! -> #REF! | F10: =#REF! -> #REF! | G10: =#REF! -> #REF! | H10: =#REF! -> #REF! | I10: =#REF! -> #REF! | J10: =#REF! -> #REF! | K10: =#REF! -> #REF! | ... Z10: =#REF! -> #REF! | AC10: =D10+E10+F10+G10 -> #REF! | AD10: =H10+I10+J10+K10+L10 -> #REF! | AE10: =M10+N10+O10+P10+Q10+R10+S10+T10+U10+V10+W10 -> #REF! | AF10: =AC10+AD10+AE10 -> #REF! | AG10: =AF10-X10 -> #REF!
C11: 2 | D11: =#REF! -> #REF! | E11: =#REF! -> #REF! | F11: =#REF! -> #REF! | G11: =#REF! -> #REF! | H11: =#REF! -> #REF! | I11: =#REF! -> #REF! | J11: =#REF! -> #REF! | K11: =#REF! -> #REF! | ... Z11: =#REF! -> #REF! | AC11: =D11+E11+F11+G11 -> #REF! | AD11: =H11+I11+J11+K11+L11 -> #REF! | AE11: =M11+N11+O11+P11+Q11+R11+S11+T11+U11+V11+W11 -> #REF! | AF11: =AC11+AD11+AE11 -> #REF! | AG11: =AF11-X11 -> #REF!
C12: 3 | D12: =#REF! -> #REF! | E12: =#REF! -> #REF! | F12: =#REF! -> #REF! | G12: =#REF! -> #REF! | H12: =#REF! -> #REF! | I12: =#REF! -> #REF! | J12: =#REF! -> #REF! | K12: =#REF! -> #REF! | ... Z12: =#REF! -> #REF! | AC12: =D12+E12+F12+G12 -> #REF! | AD12: =H12+I12+J12+K12+L12 -> #REF! | AE12: =M12+N12+O12+P12+Q12+R12+S12+T12+U12+V12+W12 -> #REF! | AF12: =AC12+AD12+AE12 -> #REF! | AG12: =AF12-X12 -> #REF!
C13: 4 | D13: =#REF! -> #REF! | E13: =#REF! -> #REF! | F13: =#REF! -> #REF! | G13: =#REF! -> #REF! | H13: =#REF! -> #REF! | I13: =#REF! -> #REF! | J13: =#REF! -> #REF! | K13: =#REF! -> #REF! | ... Z13: =#REF! -> #REF! | AC13: =D13+E13+F13+G13 -> #REF! | AD13: =H13+I13+J13+K13+L13 -> #REF! | AE13: =M13+N13+O13+P13+Q13+R13+S13+T13+U13+V13+W13 -> #REF! | AF13: =AC13+AD13+AE13 -> #REF! | AG13: =AF13-X13 -> #REF!
B14: 2007 | C14: 1 | D14: =#REF! -> #REF! | E14: =#REF! -> #REF! | F14: =#REF! -> #REF! | G14: =#REF! -> #REF! | H14: =#REF! -> #REF! | I14: =#REF! -> #REF! | J14: =#REF! -> #REF! | K14: =#REF! -> #REF! | ... Z14: =#REF! -> #REF! | AC14: =D14+E14+F14+G14 -> #REF! | AD14: =H14+I14+J14+K14+L14 -> #REF! | AE14: =M14+N14+O14+P14+Q14+R14+S14+T14+U14+V14+W14 -> #REF! | AF14: =AC14+AD14+AE14 -> #REF! | AG14: =AF14-X14 -> #REF!
C15: 2 | D15: =#REF! -> #REF! | E15: =#REF! -> #REF! | F15: =#REF! -> #REF! | G15: =#REF! -> #REF! | H15: =#REF! -> #REF! | I15: =#REF! -> #REF! | J15: =#REF! -> #REF! | K15: =#REF! -> #REF! | ... Z15: =#REF! -> #REF! | AC15: =D15+E15+F15+G15 -> #REF! | AD15: =H15+I15+J15+K15+L15 -> #REF! | AE15: =M15+N15+O15+P15+Q15+R15+S15+T15+U15+V15+W15 -> #REF! | AF15: =AC15+AD15+AE15 -> #REF! | AG15: =AF15-X15 -> #REF!
C16: 3 | D16: =#REF! -> #REF! | E16: =#REF! -> #REF! | F16: =#REF! -> #REF! | G16: =#REF! -> #REF! | H16: =#REF! -> #REF! | I16: =#REF! -> #REF! | J16: =#REF! -> #REF! | K16: =#REF! -> #REF! | ... Z16: =#REF! -> #REF! | AC16: =D16+E16+F16+G16 -> #REF! | AD16: =H16+I16+J16+K16+L16 -> #REF! | AE16: =M16+N16+O16+P16+Q16+R16+S16+T16+U16+V16+W16 -> #REF! | AF16: =AC16+AD16+AE16 -> #REF! | AG16: =AF16-X16 -> #REF!
C17: 4 | D17: =#REF! -> #REF! | E17: =#REF! -> #REF! | F17: =#REF! -> #REF! | G17: =#REF! -> #REF! | H17: =#REF! -> #REF! | I17: =#REF! -> #REF! | J17: =#REF! -> #REF! | K17: =#REF! -> #REF! | ... Z17: =#REF! -> #REF! | AC17: =D17+E17+F17+G17 -> #REF! | AD17: =H17+I17+J17+K17+L17 -> #REF! | AE17: =M17+N17+O17+P17+Q17+R17+S17+T17+U17+V17+W17 -> #REF! | AF17: =AC17+AD17+AE17 -> #REF! | AG17: =AF17-X17 -> #REF!
B18: 2008 | C18: 1 | D18: =#REF! -> #REF! | E18: =#REF! -> #REF! | F18: =#REF! -> #REF! | G18: =#REF! -> #REF! | H18: =#REF! -> #REF! | I18: =#REF! -> #REF! | J18: =#REF! -> #REF! | K18: =#REF! -> #REF! | ... Z18: =#REF! -> #REF! | AC18: =D18+E18+F18+G18 -> #REF! | AD18: =H18+I18+J18+K18+L18 -> #REF! | AE18: =M18+N18+O18+P18+Q18+R18+S18+T18+U18+V18+W18 -> #REF! | AF18: =AC18+AD18+AE18 -> #REF! | AG18: =AF18-X18 -> #REF!
C19: 2 | D19: =#REF! -> #REF! | E19: =#REF! -> #REF! | F19: =#REF! -> #REF! | G19: =#REF! -> #REF! | H19: =#REF! -> #REF! | I19: =#REF! -> #REF! | J19: =#REF! -> #REF! | K19: =#REF! -> #REF! | ... Z19: =#REF! -> #REF! | AC19: =D19+E19+F19+G19 -> #REF! | AD19: =H19+I19+J19+K19+L19 -> #REF! | AE19: =M19+N19+O19+P19+Q19+R19+S19+T19+U19+V19+W19 -> #REF! | AF19: =AC19+AD19+AE19 -> #REF! | AG19: =AF19-X19 -> #REF!
C20: 3 | D20: =#REF! -> #REF! | E20: =#REF! -> #REF! | F20: =#REF! -> #REF! | G20: =#REF! -> #REF! | H20: =#REF! -> #REF! | I20: =#REF! -> #REF! | J20: =#REF! -> #REF! | K20: =#REF! -> #REF! | ... Z20: =#REF! -> #REF! | AC20: =D20+E20+F20+G20 -> #REF! | AD20: =H20+I20+J20+K20+L20 -> #REF! | AE20: =M20+N20+O20+P20+Q20+R20+S20+T20+U20+V20+W20 -> #REF! | AF20: =AC20+AD20+AE20 -> #REF! | AG20: =AF20-X20 -> #REF!
C21: 4 | D21: =#REF! -> #REF! | E21: =#REF! -> #REF! | F21: =#REF! -> #REF! | G21: =#REF! -> #REF! | H21: =#REF! -> #REF! | I21: =#REF! -> #REF! | J21: =#REF! -> #REF! | K21: =#REF! -> #REF! | ... Z21: =#REF! -> #REF! | AC21: =D21+E21+F21+G21 -> #REF! | AD21: =H21+I21+J21+K21+L21 -> #REF! | AE21: =M21+N21+O21+P21+Q21+R21+S21+T21+U21+V21+W21 -> #REF! | AF21: =AC21+AD21+AE21 -> #REF! | AG21: =AF21-X21 -> #REF!
B22: 2009 | C22: 1 | D22: =#REF! -> #REF! | E22: =#REF! -> #REF! | F22: =#REF! -> #REF! | G22: =#REF! -> #REF! | H22: =#REF! -> #REF! | I22: =#REF! -> #REF! | J22: =#REF! -> #REF! | K22: =#REF! -> #REF! | ... Z22: =#REF! -> #REF! | AC22: =D22+E22+F22+G22 -> #REF! | AD22: =H22+I22+J22+K22+L22 -> #REF! | AE22: =M22+N22+O22+P22+Q22+R22+S22+T22+U22+V22+W22 -> #REF! | AF22: =AC22+AD22+AE22 -> #REF! | AG22: =AF22-X22 -> #REF!
C23: 2 | D23: =#REF! -> #REF! | E23: =#REF! -> #REF! | F23: =#REF! -> #REF! | G23: =#REF! -> #REF! | H23: =#REF! -> #REF! | I23: =#REF! -> #REF! | J23: =#REF! -> #REF! | K23: =#REF! -> #REF! | ... Z23: =#REF! -> #REF! | AC23: =D23+E23+F23+G23 -> #REF! | AD23: =H23+I23+J23+K23+L23 -> #REF! | AE23: =M23+N23+O23+P23+Q23+R23+S23+T23+U23+V23+W23 -> #REF! | AF23: =AC23+AD23+AE23 -> #REF! | AG23: =AF23-X23 -> #REF!
C24: 3 | D24: =#REF! -> #REF! | E24: =#REF! -> #REF! | F24: =#REF! -> #REF! | G24: =#REF! -> #REF! | H24: =#REF! -> #REF! | I24: =#REF! -> #REF! | J24: =#REF! -> #REF! | K24: =#REF! -> #REF! | ... Z24: =#REF! -> #REF! | AC24: =D24+E24+F24+G24 -> #REF! | AD24: =H24+I24+J24+K24+L24 -> #REF! | AE24: =M24+N24+O24+P24+Q24+R24+S24+T24+U24+V24+W24 -> #REF! | AF24: =AC24+AD24+AE24 -> #REF! | AG24: =AF24-X24 -> #REF!
C25: 4 | D25: =#REF! -> #REF! | E25: =#REF! -> #REF! | F25: =#REF! -> #REF! | G25: =#REF! -> #REF! | H25: =#REF! -> #REF! | I25: =#REF! -> #REF! | J25: =#REF! -> #REF! | K25: =#REF! -> #REF! | ... Z25: =#REF! -> #REF! | AC25: =D25+E25+F25+G25 -> #REF! | AD25: =H25+I25+J25+K25+L25 -> #REF! | AE25: =M25+N25+O25+P25+Q25+R25+S25+T25+U25+V25+W25 -> #REF! | AF25: =AC25+AD25+AE25 -> #REF! | AG25: =AF25-X25 -> #REF!
B26: 2010 | C26: 1 | D26: =#REF! -> #REF! | E26: =#REF! -> #REF! | F26: =#REF! -> #REF! | G26: =#REF! -> #REF! | H26: =#REF! -> #REF! | I26: =#REF! -> #REF! | J26: =#REF! -> #REF! | K26: =#REF! -> #REF! | ... Z26: =#REF! -> #REF! | AC26: =D26+E26+F26+G26 -> #REF! | AD26: =H26+I26+J26+K26+L26 -> #REF! | AE26: =M26+N26+O26+P26+Q26+R26+S26+T26+U26+V26+W26 -> #REF! | AF26: =AC26+AD26+AE26 -> #REF! | AG26: =AF26-X26 -> #REF!
C27: 2 | D27: =#REF! -> #REF! | E27: =#REF! -> #REF! | F27: =#REF! -> #REF! | G27: =#REF! -> #REF! | H27: =#REF! -> #REF! | I27: =#REF! -> #REF! | J27: =#REF! -> #REF! | K27: =#REF! -> #REF! | ... Z27: =#REF! -> #REF! | AC27: =D27+E27+F27+G27 -> #REF! | AD27: =H27+I27+J27+K27+L27 -> #REF! | AE27: =M27+N27+O27+P27+Q27+R27+S27+T27+U27+V27+W27 -> #REF! | AF27: =AC27+AD27+AE27 -> #REF! | AG27: =AF27-X27 -> #REF!
C28: 3 | D28: =#REF! -> #REF! | E28: =#REF! -> #REF! | F28: =#REF! -> #REF! | G28: =#REF! -> #REF! | H28: =#REF! -> #REF! | I28: =#REF! -> #REF! | J28: =#REF! -> #REF! | K28: =#REF! -> #REF! | ... Z28: =#REF! -> #REF! | AC28: =D28+E28+F28+G28 -> #REF! | AD28: =H28+I28+J28+K28+L28 -> #REF! | AE28: =M28+N28+O28+P28+Q28+R28+S28+T28+U28+V28+W28 -> #REF! | AF28: =AC28+AD28+AE28 -> #REF! | AG28: =AF28-X28 -> #REF!
C29: 4 | D29: =#REF! -> #REF! | E29: =#REF! -> #REF! | F29: =#REF! -> #REF! | G29: =#REF! -> #REF! | H29: =#REF! -> #REF! | I29: =#REF! -> #REF! | J29: =#REF! -> #REF! | K29: =#REF! -> #REF! | ... Z29: =#REF! -> #REF! | AC29: =D29+E29+F29+G29 -> #REF! | AD29: =H29+I29+J29+K29+L29 -> #REF! | AE29: =M29+N29+O29+P29+Q29+R29+S29+T29+U29+V29+W29 -> #REF! | AF29: =AC29+AD29+AE29 -> #REF! | AG29: =AF29-X29 -> #REF!
B30: 2011 | C30: 1 | D30: =#REF! -> #REF! | E30: =#REF! -> #REF! | F30: =#REF! -> #REF! | G30: =#REF! -> #REF! | H30: =#REF! -> #REF! | I30: =#REF! -> #REF! | J30: =#REF! -> #REF! | K30: =#REF! -> #REF! | ... Z30: =#REF! -> #REF! | AC30: =D30+E30+F30+G30 -> #REF! | AD30: =H30+I30+J30+K30+L30 -> #REF! | AE30: =M30+N30+O30+P30+Q30+R30+S30+T30+U30+V30+W30 -> #REF! | AF30: =AC30+AD30+AE30 -> #REF! | AG30: =AF30-X30 -> #REF!
C31: 2 | D31: =#REF! -> #REF! | E31: =#REF! -> #REF! | F31: =#REF! -> #REF! | G31: =#REF! -> #REF! | H31: =#REF! -> #REF! | I31: =#REF! -> #REF! | J31: =#REF! -> #REF! | K31: =#REF! -> #REF! | ... Z31: =#REF! -> #REF! | AC31: =D31+E31+F31+G31 -> #REF! | AD31: =H31+I31+J31+K31+L31 -> #REF! | AE31: =M31+N31+O31+P31+Q31+R31+S31+T31+U31+V31+W31 -> #REF! | AF31: =AC31+AD31+AE31 -> #REF! | AG31: =AF31-X31 -> #REF!
C32: 3* | D32: =#REF! -> #REF! | E32: =#REF! -> #REF! | F32: =#REF! -> #REF! | G32: =#REF! -> #REF! | H32: =#REF! -> #REF! | I32: =#REF! -> #REF! | J32: =#REF! -> #REF! | K32: =#REF! -> #REF! | ... Z32: =#REF! -> #REF!
C33: 4* | D33: =#REF! -> #REF! | E33: =#REF! -> #REF! | F33: =#REF! -> #REF! | G33: =#REF! -> #REF! | H33: =#REF! -> #REF! | I33: =#REF! -> #REF! | J33: =#REF! -> #REF! | K33: =#REF! -> #REF! | ... Z33: =#REF! -> #REF!
B35: * provisional

Sheet T5
B1: Table 5 - Percentage change (quarter-on-quarter) Seasonal Adjusted Quarterly Gross Value Added by Activity at Constant 2006 Prices
D2: Agriculture Sector | H2: Industry Sector | M2: Services Sector
B3: Year | C3: Quarter | D3: Crops & Cocoa | E3: Livestock | F3: Forestry | G3: Fishing | H3: Mining and Quarrying | I3: Manufacturing | J3: Electricity | K3: Water & Sewerage | L3: Construction | M3: Trade; Repair Of Vehicles, Household Goods | N3: Hotels And Restaurants | O3: Transport & Storage | P3: Information & Communication | Q3: Financial & Insurance Activities | R3: Real Estate Activities | S3: Business & other Services Activities | T3: Public Administration | U3: Education | V3: Health | W3: Other Personal Service Activities | X3: Total Value Added | Y3: Net Taxes | Z3: GDP at Constant Prices | AC3: Agric | AD3: Ind | AE3: Serv | AF3: controle
B4: 2006
B10: 2006 | C10: 1 | AC10: =D10+E10+F10+G10 -> 0 | AD10: =H10+I10+J10+K10+L10 -> 0 | AE10: =M10+N10+O10+P10+Q10+R10+S10+T10+U10+V10+W10 -> 0
C11: 2 | D11: ='%QQSea Adjust'!C6 -> #REF! | E11: ='%QQSea Adjust'!D6 -> #REF! | F11: ='%QQSea Adjust'!E6 -> #REF! | G11: ='%QQSea Adjust'!F6 -> #REF! | H11: ='%QQSea Adjust'!G6 -> #REF! | I11: ='%QQSea Adjust'!H6 -> #REF! | J11: ='%QQSea Adjust'!I6 -> #REF! | K11: ='%QQSea Adjust'!J6 -> #REF! | ... Z11: ='%QQSea Adjust'!Y6 -> #REF! | AC11: ='T4'!AC11/'T4'!AC10*100-100 -> #REF! | AD11: ='T4'!AD11/'T4'!AD10*100-100 -> #REF! | AE11: ='T4'!AE11/'T4'!AE10*100-100 -> #REF!
C12: 3 | D12: ='%QQSea Adjust'!C7 -> #REF! | E12: ='%QQSea Adjust'!D7 -> #REF! | F12: ='%QQSea Adjust'!E7 -> #REF! | G12: ='%QQSea Adjust'!F7 -> #REF! | H12: ='%QQSea Adjust'!G7 -> #REF! | I12: ='%QQSea Adjust'!H7 -> #REF! | J12: ='%QQSea Adjust'!I7 -> #REF! | K12: ='%QQSea Adjust'!J7 -> #REF! | ... Z12: ='%QQSea Adjust'!Y7 -> #REF! | AC12: ='T4'!AC12/'T4'!AC11*100-100 -> #REF! | AD12: ='T4'!AD12/'T4'!AD11*100-100 -> #REF! | AE12: ='T4'!AE12/'T4'!AE11*100-100 -> #REF!
C13: 4 | D13: ='%QQSea Adjust'!C8 -> #REF! | E13: ='%QQSea Adjust'!D8 -> #REF! | F13: ='%QQSea Adjust'!E8 -> #REF! | G13: ='%QQSea Adjust'!F8 -> #REF! | H13: ='%QQSea Adjust'!G8 -> #REF! | I13: ='%QQSea Adjust'!H8 -> #REF! | J13: ='%QQSea Adjust'!I8 -> #REF! | K13: ='%QQSea Adjust'!J8 -> #REF! | ... Z13: ='%QQSea Adjust'!Y8 -> #REF! | AC13: ='T4'!AC13/'T4'!AC12*100-100 -> #REF! | AD13: ='T4'!AD13/'T4'!AD12*100-100 -> #REF! | AE13: ='T4'!AE13/'T4'!AE12*100-100 -> #REF!
B14: 2007 | C14: 1 | D14: ='%QQSea Adjust'!C9 -> #REF! | E14: ='%QQSea Adjust'!D9 -> #REF! | F14: ='%QQSea Adjust'!E9 -> #REF! | G14: ='%QQSea Adjust'!F9 -> #REF! | H14: ='%QQSea Adjust'!G9 -> #REF! | I14: ='%QQSea Adjust'!H9 -> #REF! | J14: ='%QQSea Adjust'!I9 -> #REF! | K14: ='%QQSea Adjust'!J9 -> #REF! | ... Z14: ='%QQSea Adjust'!Y9 -> #REF! | AC14: ='T4'!AC14/'T4'!AC13*100-100 -> #REF! | AD14: ='T4'!AD14/'T4'!AD13*100-100 -> #REF! | AE14: ='T4'!AE14/'T4'!AE13*100-100 -> #REF!
C15: 2 | D15: ='%QQSea Adjust'!C10 -> #REF! | E15: ='%QQSea Adjust'!D10 -> #REF! | F15: ='%QQSea Adjust'!E10 -> #REF! | G15: ='%QQSea Adjust'!F10 -> #REF! | H15: ='%QQSea Adjust'!G10 -> #REF! | I15: ='%QQSea Adjust'!H10 -> #REF! | J15: ='%QQSea Adjust'!I10 -> #REF! | K15: ='%QQSea Adjust'!J10 -> #REF! | ... Z15: ='%QQSea Adjust'!Y10 -> #REF! | AC15: ='T4'!AC15/'T4'!AC14*100-100 -> #REF! | AD15: ='T4'!AD15/'T4'!AD14*100-100 -> #REF! | AE15: ='T4'!AE15/'T4'!AE14*100-100 -> #REF!
C16: 3 | D16: ='%QQSea Adjust'!C11 -> #REF! | E16: ='%QQSea Adjust'!D11 -> #REF! | F16: ='%QQSea Adjust'!E11 -> #REF! | G16: ='%QQSea Adjust'!F11 -> #REF! | H16: ='%QQSea Adjust'!G11 -> #REF! | I16: ='%QQSea Adjust'!H11 -> #REF! | J16: ='%QQSea Adjust'!I11 -> #REF! | K16: ='%QQSea Adjust'!J11 -> #REF! | ... Z16: ='%QQSea Adjust'!Y11 -> #REF! | AC16: ='T4'!AC16/'T4'!AC15*100-100 -> #REF! | AD16: ='T4'!AD16/'T4'!AD15*100-100 -> #REF! | AE16: ='T4'!AE16/'T4'!AE15*100-100 -> #REF!
C17: 4 | D17: ='%QQSea Adjust'!C12 -> #REF! | E17: ='%QQSea Adjust'!D12 -> #REF! | F17: ='%QQSea Adjust'!E12 -> #REF! | G17: ='%QQSea Adjust'!F12 -> #REF! | H17: ='%QQSea Adjust'!G12 -> #REF! | I17: ='%QQSea Adjust'!H12 -> #REF! | J17: ='%QQSea Adjust'!I12 -> #REF! | K17: ='%QQSea Adjust'!J12 -> #REF! | ... Z17: ='%QQSea Adjust'!Y12 -> #REF! | AC17: ='T4'!AC17/'T4'!AC16*100-100 -> #REF! | AD17: ='T4'!AD17/'T4'!AD16*100-100 -> #REF! | AE17: ='T4'!AE17/'T4'!AE16*100-100 -> #REF!
B18: 2008 | C18: 1 | D18: ='%QQSea Adjust'!C13 -> #REF! | E18: ='%QQSea Adjust'!D13 -> #REF! | F18: ='%QQSea Adjust'!E13 -> #REF! | G18: ='%QQSea Adjust'!F13 -> #REF! | H18: ='%QQSea Adjust'!G13 -> #REF! | I18: ='%QQSea Adjust'!H13 -> #REF! | J18: ='%QQSea Adjust'!I13 -> #REF! | K18: ='%QQSea Adjust'!J13 -> #REF! | ... Z18: ='%QQSea Adjust'!Y13 -> #REF! | AC18: ='T4'!AC18/'T4'!AC17*100-100 -> #REF! | AD18: ='T4'!AD18/'T4'!AD17*100-100 -> #REF! | AE18: ='T4'!AE18/'T4'!AE17*100-100 -> #REF!
C19: 2 | D19: ='%QQSea Adjust'!C14 -> #REF! | E19: ='%QQSea Adjust'!D14 -> #REF! | F19: ='%QQSea Adjust'!E14 -> #REF! | G19: ='%QQSea Adjust'!F14 -> #REF! | H19: ='%QQSea Adjust'!G14 -> #REF! | I19: ='%QQSea Adjust'!H14 -> #REF! | J19: ='%QQSea Adjust'!I14 -> #REF! | K19: ='%QQSea Adjust'!J14 -> #REF! | ... Z19: ='%QQSea Adjust'!Y14 -> #REF! | AC19: ='T4'!AC19/'T4'!AC18*100-100 -> #REF! | AD19: ='T4'!AD19/'T4'!AD18*100-100 -> #REF! | AE19: ='T4'!AE19/'T4'!AE18*100-100 -> #REF!
C20: 3 | D20: ='%QQSea Adjust'!C15 -> #REF! | E20: ='%QQSea Adjust'!D15 -> #REF! | F20: ='%QQSea Adjust'!E15 -> #REF! | G20: ='%QQSea Adjust'!F15 -> #REF! | H20: ='%QQSea Adjust'!G15 -> #REF! | I20: ='%QQSea Adjust'!H15 -> #REF! | J20: ='%QQSea Adjust'!I15 -> #REF! | K20: ='%QQSea Adjust'!J15 -> #REF! | ... Z20: ='%QQSea Adjust'!Y15 -> #REF! | AC20: ='T4'!AC20/'T4'!AC19*100-100 -> #REF! | AD20: ='T4'!AD20/'T4'!AD19*100-100 -> #REF! | AE20: ='T4'!AE20/'T4'!AE19*100-100 -> #REF!
C21: 4 | D21: ='%QQSea Adjust'!C16 -> #REF! | E21: ='%QQSea Adjust'!D16 -> #REF! | F21: ='%QQSea Adjust'!E16 -> #REF! | G21: ='%QQSea Adjust'!F16 -> #REF! | H21: ='%QQSea Adjust'!G16 -> #REF! | I21: ='%QQSea Adjust'!H16 -> #REF! | J21: ='%QQSea Adjust'!I16 -> #REF! | K21: ='%QQSea Adjust'!J16 -> #REF! | ... Z21: ='%QQSea Adjust'!Y16 -> #REF! | AC21: ='T4'!AC21/'T4'!AC20*100-100 -> #REF! | AD21: ='T4'!AD21/'T4'!AD20*100-100 -> #REF! | AE21: ='T4'!AE21/'T4'!AE20*100-100 -> #REF!
B22: 2009 | C22: 1 | D22: ='%QQSea Adjust'!C17 -> #REF! | E22: ='%QQSea Adjust'!D17 -> #REF! | F22: ='%QQSea Adjust'!E17 -> #REF! | G22: ='%QQSea Adjust'!F17 -> #REF! | H22: ='%QQSea Adjust'!G17 -> #REF! | I22: ='%QQSea Adjust'!H17 -> #REF! | J22: ='%QQSea Adjust'!I17 -> #REF! | K22: ='%QQSea Adjust'!J17 -> #REF! | ... Z22: ='%QQSea Adjust'!Y17 -> #REF! | AC22: ='T4'!AC22/'T4'!AC21*100-100 -> #REF! | AD22: ='T4'!AD22/'T4'!AD21*100-100 -> #REF! | AE22: ='T4'!AE22/'T4'!AE21*100-100 -> #REF!
C23: 2 | D23: ='%QQSea Adjust'!C18 -> #REF! | E23: ='%QQSea Adjust'!D18 -> #REF! | F23: ='%QQSea Adjust'!E18 -> #REF! | G23: ='%QQSea Adjust'!F18 -> #REF! | H23: ='%QQSea Adjust'!G18 -> #REF! | I23: ='%QQSea Adjust'!H18 -> #REF! | J23: ='%QQSea Adjust'!I18 -> #REF! | K23: ='%QQSea Adjust'!J18 -> #REF! | ... Z23: ='%QQSea Adjust'!Y18 -> #REF! | AC23: ='T4'!AC23/'T4'!AC22*100-100 -> #REF! | AD23: ='T4'!AD23/'T4'!AD22*100-100 -> #REF! | AE23: ='T4'!AE23/'T4'!AE22*100-100 -> #REF!
C24: 3 | D24: ='%QQSea Adjust'!C19 -> #REF! | E24: ='%QQSea Adjust'!D19 -> #REF! | F24: ='%QQSea Adjust'!E19 -> #REF! | G24: ='%QQSea Adjust'!F19 -> #REF! | H24: ='%QQSea Adjust'!G19 -> #REF! | I24: ='%QQSea Adjust'!H19 -> #REF! | J24: ='%QQSea Adjust'!I19 -> #REF! | K24: ='%QQSea Adjust'!J19 -> #REF! | ... Z24: ='%QQSea Adjust'!Y19 -> #REF! | AC24: ='T4'!AC24/'T4'!AC23*100-100 -> #REF! | AD24: ='T4'!AD24/'T4'!AD23*100-100 -> #REF! | AE24: ='T4'!AE24/'T4'!AE23*100-100 -> #REF!
C25: 4 | D25: ='%QQSea Adjust'!C20 -> #REF! | E25: ='%QQSea Adjust'!D20 -> #REF! | F25: ='%QQSea Adjust'!E20 -> #REF! | G25: ='%QQSea Adjust'!F20 -> #REF! | H25: ='%QQSea Adjust'!G20 -> #REF! | I25: ='%QQSea Adjust'!H20 -> #REF! | J25: ='%QQSea Adjust'!I20 -> #REF! | K25: ='%QQSea Adjust'!J20 -> #REF! | ... Z25: ='%QQSea Adjust'!Y20 -> #REF! | AC25: ='T4'!AC25/'T4'!AC24*100-100 -> #REF! | AD25: ='T4'!AD25/'T4'!AD24*100-100 -> #REF! | AE25: ='T4'!AE25/'T4'!AE24*100-100 -> #REF!
B26: 2010 | C26: 1 | D26: ='%QQSea Adjust'!C21 -> #REF! | E26: ='%QQSea Adjust'!D21 -> #REF! | F26: ='%QQSea Adjust'!E21 -> #REF! | G26: ='%QQSea Adjust'!F21 -> #REF! | H26: ='%QQSea Adjust'!G21 -> #REF! | I26: ='%QQSea Adjust'!H21 -> #REF! | J26: ='%QQSea Adjust'!I21 -> #REF! | K26: ='%QQSea Adjust'!J21 -> #REF! | ... Z26: ='%QQSea Adjust'!Y21 -> #REF! | AC26: ='T4'!AC26/'T4'!AC25*100-100 -> #REF! | AD26: ='T4'!AD26/'T4'!AD25*100-100 -> #REF! | AE26: ='T4'!AE26/'T4'!AE25*100-100 -> #REF!
C27: 2 | D27: ='%QQSea Adjust'!C22 -> #REF! | E27: ='%QQSea Adjust'!D22 -> #REF! | F27: ='%QQSea Adjust'!E22 -> #REF! | G27: ='%QQSea Adjust'!F22 -> #REF! | H27: ='%QQSea Adjust'!G22 -> #REF! | I27: ='%QQSea Adjust'!H22 -> #REF! | J27: ='%QQSea Adjust'!I22 -> #REF! | K27: ='%QQSea Adjust'!J22 -> #REF! | ... Z27: ='%QQSea Adjust'!Y22 -> #REF! | AC27: ='T4'!AC27/'T4'!AC26*100-100 -> #REF! | AD27: ='T4'!AD27/'T4'!AD26*100-100 -> #REF! | AE27: ='T4'!AE27/'T4'!AE26*100-100 -> #REF!
C28: 3 | D28: ='%QQSea Adjust'!C23 -> #REF! | E28: ='%QQSea Adjust'!D23 -> #REF! | F28: ='%QQSea Adjust'!E23 -> #REF! | G28: ='%QQSea Adjust'!F23 -> #REF! | H28: ='%QQSea Adjust'!G23 -> #REF! | I28: ='%QQSea Adjust'!H23 -> #REF! | J28: ='%QQSea Adjust'!I23 -> #REF! | K28: ='%QQSea Adjust'!J23 -> #REF! | ... Z28: ='%QQSea Adjust'!Y23 -> #REF! | AC28: ='T4'!AC28/'T4'!AC27*100-100 -> #REF! | AD28: ='T4'!AD28/'T4'!AD27*100-100 -> #REF! | AE28: ='T4'!AE28/'T4'!AE27*100-100 -> #REF!
C29: 4 | D29: ='%QQSea Adjust'!C24 -> #REF! | E29: ='%QQSea Adjust'!D24 -> #REF! | F29: ='%QQSea Adjust'!E24 -> #REF! | G29: ='%QQSea Adjust'!F24 -> #REF! | H29: ='%QQSea Adjust'!G24 -> #REF! | I29: ='%QQSea Adjust'!H24 -> #REF! | J29: ='%QQSea Adjust'!I24 -> #REF! | K29: ='%QQSea Adjust'!J24 -> #REF! | ... Z29: ='%QQSea Adjust'!Y24 -> #REF! | AC29: ='T4'!AC29/'T4'!AC28*100-100 -> #REF! | AD29: ='T4'!AD29/'T4'!AD28*100-100 -> #REF! | AE29: ='T4'!AE29/'T4'!AE28*100-100 -> #REF!
B30: 2010 | C30: 1 | D30: ='%QQSea Adjust'!C25 -> #REF! | E30: ='%QQSea Adjust'!D25 -> #REF! | F30: ='%QQSea Adjust'!E25 -> #REF! | G30: ='%QQSea Adjust'!F25 -> #REF! | H30: ='%QQSea Adjust'!G25 -> #REF! | I30: ='%QQSea Adjust'!H25 -> #REF! | J30: ='%QQSea Adjust'!I25 -> #REF! | K30: ='%QQSea Adjust'!J25 -> #REF! | ... Z30: ='%QQSea Adjust'!Y25 -> #REF! | AC30: ='T4'!AC30/'T4'!AC29*100-100 -> #REF! | AD30: ='T4'!AD30/'T4'!AD29*100-100 -> #REF! | AE30: ='T4'!AE30/'T4'!AE29*100-100 -> #REF!
C31: 2 | D31: ='%QQSea Adjust'!C26 -> #REF! | E31: ='%QQSea Adjust'!D26 -> #REF! | F31: ='%QQSea Adjust'!E26 -> #REF! | G31: ='%QQSea Adjust'!F26 -> #REF! | H31: ='%QQSea Adjust'!G26 -> #REF! | I31: ='%QQSea Adjust'!H26 -> #REF! | J31: ='%QQSea Adjust'!I26 -> #REF! | K31: ='%QQSea Adjust'!J26 -> #REF! | ... Z31: ='%QQSea Adjust'!Y26 -> #REF!
C32: 3* | D32: ='%QQSea Adjust'!C27 -> #REF! | E32: ='%QQSea Adjust'!D27 -> #REF! | F32: ='%QQSea Adjust'!E27 -> #REF! | G32: ='%QQSea Adjust'!F27 -> #REF! | H32: ='%QQSea Adjust'!G27 -> #REF! | I32: ='%QQSea Adjust'!H27 -> #REF! | J32: ='%QQSea Adjust'!I27 -> #REF! | K32: ='%QQSea Adjust'!J27 -> #REF! | ... Z32: ='%QQSea Adjust'!Y27 -> #REF!
C33: 4 | D33: ='%QQSea Adjust'!C28 -> 0 | E33: ='%QQSea Adjust'!D28 -> 0 | F33: ='%QQSea Adjust'!E28 -> 0 | G33: ='%QQSea Adjust'!F28 -> 0 | H33: ='%QQSea Adjust'!G28 -> 0 | I33: ='%QQSea Adjust'!H28 -> 0 | J33: ='%QQSea Adjust'!I28 -> 0 | K33: ='%QQSea Adjust'!J28 -> 0 | ... Z33: ='%QQSea Adjust'!Y28 -> 0
B35: * provisional

Sheet T6
B1: Table 6 - Percentage Changes (Year-on-Year) in the Seasonal Adjusted Quarterly Value Added by Activity and Gross Domestic Product at Constant 2006 Prices
D2: Agriculture Sector | H2: Industry Sector | M2: Services Sector
B3: Year 1) | C3: Quarter 2) | D3: Crops & Cocoa | E3: Livestock | F3: Forestry | G3: Fishing | H3: Mining and Quarrying | I3: Manufacturing | J3: Electricity | K3: Water & Sewerage | L3: Construction | M3: Trade; Repair Of Vehicles, Household Goods | N3: Hotels And Restaurants | O3: Transport & Storage | P3: Information & Communication | Q3: Financial & Insurance Activities | R3: Real Estate Activities | S3: Business & other Services Activities | T3: Public Administration | U3: Education | V3: Health | W3: Other Personal Service Activities | X3: Total Value Added | Y3: Net Taxes | Z3: GDP at Constant Prices | AC3: Agric | AD3: Ind | AE3: Serv | AF3: controle
B4: 2006
B10: 2006 | C10: 1 | AC10: =D10+E10+F10+G10 -> 0 | AD10: =H10+I10+J10+K10+L10 -> 0 | AE10: =M10+N10+O10+P10+Q10+R10+S10+T10+U10+V10+W10 -> 0
C11: 2 | AC11: ='T4'!AC11/'T4'!AC10*100-100 -> #REF! | AD11: ='T4'!AD11/'T4'!AD10*100-100 -> #REF! | AE11: ='T4'!AE11/'T4'!AE10*100-100 -> #REF!
C12: 3
C13: 4
B14: 2007 | C14: 1 | D14: ='YY%4qsea adj'!C5 -> #REF! | E14: ='YY%4qsea adj'!D5 -> #REF! | F14: ='YY%4qsea adj'!E5 -> #REF! | G14: ='YY%4qsea adj'!F5 -> #REF! | H14: ='YY%4qsea adj'!G5 -> #REF! | I14: ='YY%4qsea adj'!H5 -> #REF! | J14: ='YY%4qsea adj'!I5 -> #REF! | K14: ='YY%4qsea adj'!J5 -> #REF! | ... Z14: ='YY%4qsea adj'!Y5 -> #REF! | AC14: ='T4'!AC14/'T4'!AC10*100-100 -> #REF! | AD14: ='T4'!AD14/'T4'!AD10*100-100 -> #REF! | AE14: ='T4'!AE14/'T4'!AE10*100-100 -> #REF!
C15: 2 | D15: ='YY%4qsea adj'!C6 -> #REF! | E15: ='YY%4qsea adj'!D6 -> #REF! | F15: ='YY%4qsea adj'!E6 -> #REF! | G15: ='YY%4qsea adj'!F6 -> #REF! | H15: ='YY%4qsea adj'!G6 -> #REF! | I15: ='YY%4qsea adj'!H6 -> #REF! | J15: ='YY%4qsea adj'!I6 -> #REF! | K15: ='YY%4qsea adj'!J6 -> #REF! | ... Z15: ='YY%4qsea adj'!Y6 -> #REF! | AC15: ='T4'!AC15/'T4'!AC11*100-100 -> #REF! | AD15: ='T4'!AD15/'T4'!AD11*100-100 -> #REF! | AE15: ='T4'!AE15/'T4'!AE11*100-100 -> #REF!
C16: 3 | D16: ='YY%4qsea adj'!C7 -> #REF! | E16: ='YY%4qsea adj'!D7 -> #REF! | F16: ='YY%4qsea adj'!E7 -> #REF! | G16: ='YY%4qsea adj'!F7 -> #REF! | H16: ='YY%4qsea adj'!G7 -> #REF! | I16: ='YY%4qsea adj'!H7 -> #REF! | J16: ='YY%4qsea adj'!I7 -> #REF! | K16: ='YY%4qsea adj'!J7 -> #REF! | ... Z16: ='YY%4qsea adj'!Y7 -> #REF! | AC16: ='T4'!AC16/'T4'!AC12*100-100 -> #REF! | AD16: ='T4'!AD16/'T4'!AD12*100-100 -> #REF! | AE16: ='T4'!AE16/'T4'!AE12*100-100 -> #REF!
C17: 4 | D17: ='YY%4qsea adj'!C8 -> #REF! | E17: ='YY%4qsea adj'!D8 -> #REF! | F17: ='YY%4qsea adj'!E8 -> #REF! | G17: ='YY%4qsea adj'!F8 -> #REF! | H17: ='YY%4qsea adj'!G8 -> #REF! | I17: ='YY%4qsea adj'!H8 -> #REF! | J17: ='YY%4qsea adj'!I8 -> #REF! | K17: ='YY%4qsea adj'!J8 -> #REF! | ... Z17: ='YY%4qsea adj'!Y8 -> #REF! | AC17: ='T4'!AC17/'T4'!AC13*100-100 -> #REF! | AD17: ='T4'!AD17/'T4'!AD13*100-100 -> #REF! | AE17: ='T4'!AE17/'T4'!AE13*100-100 -> #REF!
B18: 2008 | C18: 1 | D18: ='YY%4qsea adj'!C9 -> #REF! | E18: ='YY%4qsea adj'!D9 -> #REF! | F18: ='YY%4qsea adj'!E9 -> #REF! | G18: ='YY%4qsea adj'!F9 -> #REF! | H18: ='YY%4qsea adj'!G9 -> #REF! | I18: ='YY%4qsea adj'!H9 -> #REF! | J18: ='YY%4qsea adj'!I9 -> #REF! | K18: ='YY%4qsea adj'!J9 -> #REF! | ... Z18: ='YY%4qsea adj'!Y9 -> #REF! | AC18: ='T4'!AC18/'T4'!AC14*100-100 -> #REF! | AD18: ='T4'!AD18/'T4'!AD14*100-100 -> #REF! | AE18: ='T4'!AE18/'T4'!AE14*100-100 -> #REF!
C19: 2 | D19: ='YY%4qsea adj'!C10 -> #REF! | E19: ='YY%4qsea adj'!D10 -> #REF! | F19: ='YY%4qsea adj'!E10 -> #REF! | G19: ='YY%4qsea adj'!F10 -> #REF! | H19: ='YY%4qsea adj'!G10 -> #REF! | I19: ='YY%4qsea adj'!H10 -> #REF! | J19: ='YY%4qsea adj'!I10 -> #REF! | K19: ='YY%4qsea adj'!J10 -> #REF! | ... Z19: ='YY%4qsea adj'!Y10 -> #REF! | AC19: ='T4'!AC19/'T4'!AC15*100-100 -> #REF! | AD19: ='T4'!AD19/'T4'!AD15*100-100 -> #REF! | AE19: ='T4'!AE19/'T4'!AE15*100-100 -> #REF!
C20: 3 | D20: ='YY%4qsea adj'!C11 -> #REF! | E20: ='YY%4qsea adj'!D11 -> #REF! | F20: ='YY%4qsea adj'!E11 -> #REF! | G20: ='YY%4qsea adj'!F11 -> #REF! | H20: ='YY%4qsea adj'!G11 -> #REF! | I20: ='YY%4qsea adj'!H11 -> #REF! | J20: ='YY%4qsea adj'!I11 -> #REF! | K20: ='YY%4qsea adj'!J11 -> #REF! | ... Z20: ='YY%4qsea adj'!Y11 -> #REF! | AC20: ='T4'!AC20/'T4'!AC16*100-100 -> #REF! | AD20: ='T4'!AD20/'T4'!AD16*100-100 -> #REF! | AE20: ='T4'!AE20/'T4'!AE16*100-100 -> #REF!
C21: 4 | D21: ='YY%4qsea adj'!C12 -> #REF! | E21: ='YY%4qsea adj'!D12 -> #REF! | F21: ='YY%4qsea adj'!E12 -> #REF! | G21: ='YY%4qsea adj'!F12 -> #REF! | H21: ='YY%4qsea adj'!G12 -> #REF! | I21: ='YY%4qsea adj'!H12 -> #REF! | J21: ='YY%4qsea adj'!I12 -> #REF! | K21: ='YY%4qsea adj'!J12 -> #REF! | ... Z21: ='YY%4qsea adj'!Y12 -> #REF! | AC21: ='T4'!AC21/'T4'!AC17*100-100 -> #REF! | AD21: ='T4'!AD21/'T4'!AD17*100-100 -> #REF! | AE21: ='T4'!AE21/'T4'!AE17*100-100 -> #REF!
B22: 2009 | C22: 1 | D22: ='YY%4qsea adj'!C13 -> #REF! | E22: ='YY%4qsea adj'!D13 -> #REF! | F22: ='YY%4qsea adj'!E13 -> #REF! | G22: ='YY%4qsea adj'!F13 -> #REF! | H22: ='YY%4qsea adj'!G13 -> #REF! | I22: ='YY%4qsea adj'!H13 -> #REF! | J22: ='YY%4qsea adj'!I13 -> #REF! | K22: ='YY%4qsea adj'!J13 -> #REF! | ... Z22: ='YY%4qsea adj'!Y13 -> #REF! | AC22: ='T4'!AC22/'T4'!AC18*100-100 -> #REF! | AD22: ='T4'!AD22/'T4'!AD18*100-100 -> #REF! | AE22: ='T4'!AE22/'T4'!AE18*100-100 -> #REF!
C23: 2 | D23: ='YY%4qsea adj'!C14 -> #REF! | E23: ='YY%4qsea adj'!D14 -> #REF! | F23: ='YY%4qsea adj'!E14 -> #REF! | G23: ='YY%4qsea adj'!F14 -> #REF! | H23: ='YY%4qsea adj'!G14 -> #REF! | I23: ='YY%4qsea adj'!H14 -> #REF! | J23: ='YY%4qsea adj'!I14 -> #REF! | K23: ='YY%4qsea adj'!J14 -> #REF! | ... Z23: ='YY%4qsea adj'!Y14 -> #REF! | AC23: ='T4'!AC23/'T4'!AC19*100-100 -> #REF! | AD23: ='T4'!AD23/'T4'!AD19*100-100 -> #REF! | AE23: ='T4'!AE23/'T4'!AE19*100-100 -> #REF!
C24: 3 | D24: ='YY%4qsea adj'!C15 -> #REF! | E24: ='YY%4qsea adj'!D15 -> #REF! | F24: ='YY%4qsea adj'!E15 -> #REF! | G24: ='YY%4qsea adj'!F15 -> #REF! | H24: ='YY%4qsea adj'!G15 -> #REF! | I24: ='YY%4qsea adj'!H15 -> #REF! | J24: ='YY%4qsea adj'!I15 -> #REF! | K24: ='YY%4qsea adj'!J15 -> #REF! | ... Z24: ='YY%4qsea adj'!Y15 -> #REF! | AC24: ='T4'!AC24/'T4'!AC20*100-100 -> #REF! | AD24: ='T4'!AD24/'T4'!AD20*100-100 -> #REF! | AE24: ='T4'!AE24/'T4'!AE20*100-100 -> #REF!
C25: 4 | D25: ='YY%4qsea adj'!C16 -> #REF! | E25: ='YY%4qsea adj'!D16 -> #REF! | F25: ='YY%4qsea adj'!E16 -> #REF! | G25: ='YY%4qsea adj'!F16 -> #REF! | H25: ='YY%4qsea adj'!G16 -> #REF! | I25: ='YY%4qsea adj'!H16 -> #REF! | J25: ='YY%4qsea adj'!I16 -> #REF! | K25: ='YY%4qsea adj'!J16 -> #REF! | ... Z25: ='YY%4qsea adj'!Y16 -> #REF! | AC25: ='T4'!AC25/'T4'!AC21*100-100 -> #REF! | AD25: ='T4'!AD25/'T4'!AD21*100-100 -> #REF! | AE25: ='T4'!AE25/'T4'!AE21*100-100 -> #REF!
B26: 2010 | C26: 1 | D26: ='YY%4qsea adj'!C17 -> #REF! | E26: ='YY%4qsea adj'!D17 -> #REF! | F26: ='YY%4qsea adj'!E17 -> #REF! | G26: ='YY%4qsea adj'!F17 -> #REF! | H26: ='YY%4qsea adj'!G17 -> #REF! | I26: ='YY%4qsea adj'!H17 -> #REF! | J26: ='YY%4qsea adj'!I17 -> #REF! | K26: ='YY%4qsea adj'!J17 -> #REF! | ... Z26: ='YY%4qsea adj'!Y17 -> #REF! | AC26: ='T4'!AC26/'T4'!AC22*100-100 -> #REF! | AD26: ='T4'!AD26/'T4'!AD22*100-100 -> #REF! | AE26: ='T4'!AE26/'T4'!AE22*100-100 -> #REF!
C27: 2 | D27: ='YY%4qsea adj'!C18 -> #REF! | E27: ='YY%4qsea adj'!D18 -> #REF! | F27: ='YY%4qsea adj'!E18 -> #REF! | G27: ='YY%4qsea adj'!F18 -> #REF! | H27: ='YY%4qsea adj'!G18 -> #REF! | I27: ='YY%4qsea adj'!H18 -> #REF! | J27: ='YY%4qsea adj'!I18 -> #REF! | K27: ='YY%4qsea adj'!J18 -> #REF! | ... Z27: ='YY%4qsea adj'!Y18 -> #REF! | AC27: ='T4'!AC27/'T4'!AC23*100-100 -> #REF! | AD27: ='T4'!AD27/'T4'!AD23*100-100 -> #REF! | AE27: ='T4'!AE27/'T4'!AE23*100-100 -> #REF!
C28: 3 | D28: ='YY%4qsea adj'!C19 -> #REF! | E28: ='YY%4qsea adj'!D19 -> #REF! | F28: ='YY%4qsea adj'!E19 -> #REF! | G28: ='YY%4qsea adj'!F19 -> #REF! | H28: ='YY%4qsea adj'!G19 -> #REF! | I28: ='YY%4qsea adj'!H19 -> #REF! | J28: ='YY%4qsea adj'!I19 -> #REF! | K28: ='YY%4qsea adj'!J19 -> #REF! | ... Z28: ='YY%4qsea adj'!Y19 -> #REF! | AC28: ='T4'!AC28/'T4'!AC24*100-100 -> #REF! | AD28: ='T4'!AD28/'T4'!AD24*100-100 -> #REF! | AE28: ='T4'!AE28/'T4'!AE24*100-100 -> #REF!
C29: 4 | D29: ='YY%4qsea adj'!C20 -> #REF! | E29: ='YY%4qsea adj'!D20 -> #REF! | F29: ='YY%4qsea adj'!E20 -> #REF! | G29: ='YY%4qsea adj'!F20 -> #REF! | H29: ='YY%4qsea adj'!G20 -> #REF! | I29: ='YY%4qsea adj'!H20 -> #REF! | J29: ='YY%4qsea adj'!I20 -> #REF! | K29: ='YY%4qsea adj'!J20 -> #REF! | ... Z29: ='YY%4qsea adj'!Y20 -> #REF! | AC29: ='T4'!AC29/'T4'!AC25*100-100 -> #REF! | AD29: ='T4'!AD29/'T4'!AD25*100-100 -> #REF! | AE29: ='T4'!AE29/'T4'!AE25*100-100 -> #REF!
B30: 2011 | C30: 1 | D30: ='YY%4qsea adj'!C21 -> #REF! | E30: ='YY%4qsea adj'!D21 -> #REF! | F30: ='YY%4qsea adj'!E21 -> #REF! | G30: ='YY%4qsea adj'!F21 -> #REF! | H30: ='YY%4qsea adj'!G21 -> #REF! | I30: ='YY%4qsea adj'!H21 -> #REF! | J30: ='YY%4qsea adj'!I21 -> #REF! | K30: ='YY%4qsea adj'!J21 -> #REF! | ... Z30: ='YY%4qsea adj'!Y21 -> #REF! | AC30: ='T4'!AC30/'T4'!AC26*100-100 -> #REF! | AD30: ='T4'!AD30/'T4'!AD26*100-100 -> #REF! | AE30: ='T4'!AE30/'T4'!AE26*100-100 -> #REF!
C31: 2 | D31: ='YY%4qsea adj'!C22 -> #REF! | E31: ='YY%4qsea adj'!D22 -> #REF! | F31: ='YY%4qsea adj'!E22 -> #REF! | G31: ='YY%4qsea adj'!F22 -> #REF! | H31: ='YY%4qsea adj'!G22 -> #REF! | I31: ='YY%4qsea adj'!H22 -> #REF! | J31: ='YY%4qsea adj'!I22 -> #REF! | K31: ='YY%4qsea adj'!J22 -> #REF! | ... Z31: ='YY%4qsea adj'!Y22 -> #REF! | AC31: ='T4'!AC31/'T4'!AC27*100-100 -> #REF! | AD31: ='T4'!AD31/'T4'!AD27*100-100 -> #REF! | AE31: ='T4'!AE31/'T4'!AE27*100-100 -> #REF!
C32: 3* | D32: ='YY%4qsea adj'!C23 -> #REF! | E32: ='YY%4qsea adj'!D23 -> #REF! | F32: ='YY%4qsea adj'!E23 -> #REF! | G32: ='YY%4qsea adj'!F23 -> #REF! | H32: ='YY%4qsea adj'!G23 -> #REF! | I32: ='YY%4qsea adj'!H23 -> #REF! | J32: ='YY%4qsea adj'!I23 -> #REF! | K32: ='YY%4qsea adj'!J23 -> #REF! | ... Z32: ='YY%4qsea adj'!Y23 -> #REF!
C33: 4 | D33: ='YY%4qsea adj'!C24 -> 0 | E33: ='YY%4qsea adj'!D24 -> 0 | F33: ='YY%4qsea adj'!E24 -> 0 | G33: ='YY%4qsea adj'!F24 -> 0 | H33: ='YY%4qsea adj'!G24 -> 0 | I33: ='YY%4qsea adj'!H24 -> 0 | J33: ='YY%4qsea adj'!I24 -> 0 | K33: ='YY%4qsea adj'!J24 -> 0 | ... Z33: ='YY%4qsea adj'!Y24 -> 0
B35: * provisional
B36: 1) The percentage change is the growth rate for a given year compared with the previous year
B37: 2) The percentage change is the growth rate for a given quarter compared with the same quarter in the previous year

Sheet Sheet1
B2: not adjusted | E2: s.adjusted
B3: year-on-year change | C3: quarter-on-quarter change
B4: Y/Y | C4: Q/Q | E4: Y/Y | F4: Q/Q
A5: 07q1 | B5: ='T3'!Z14 -> #REF! | C5: ='T2'!Z14 -> #REF! | E5: ='T6'!Z14 -> #REF! | F5: ='T5'!Z14 -> #REF! | J5: 06q1
A6: 07q2 | B6: ='T3'!Z15 -> #REF! | C6: ='T2'!Z15 -> #REF! | E6: ='T6'!Z15 -> #REF! | F6: ='T5'!Z15 -> #REF! | J6: 06q2
A7: 07q3 | B7: ='T3'!Z16 -> #REF! | C7: ='T2'!Z16 -> #REF! | E7: ='T6'!Z16 -> #REF! | F7: ='T5'!Z16 -> #REF! | J7: 06q3
A8: 07q4 | B8: ='T3'!Z17 -> #REF! | C8: ='T2'!Z17 -> #REF! | E8: ='T6'!Z17 -> #REF! | F8: ='T5'!Z17 -> #REF! | J8: 06q4
A9: 08q1 | B9: ='T3'!Z18 -> #REF! | C9: ='T2'!Z18 -> #REF! | E9: ='T6'!Z18 -> #REF! | F9: ='T5'!Z18 -> #REF! | J9: 07q1
A10: 08q2 | B10: ='T3'!Z19 -> #REF! | C10: ='T2'!Z19 -> #REF! | E10: ='T6'!Z19 -> #REF! | F10: ='T5'!Z19 -> #REF! | J10: 07q2
A11: 08q3 | B11: ='T3'!Z20 -> #REF! | C11: ='T2'!Z20 -> #REF! | E11: ='T6'!Z20 -> #REF! | F11: ='T5'!Z20 -> #REF! | J11: 07q3
A12: 08q4 | B12: ='T3'!Z21 -> #REF! | C12: ='T2'!Z21 -> #REF! | E12: ='T6'!Z21 -> #REF! | F12: ='T5'!Z21 -> #REF! | J12: 07q4
A13: 09q1 | B13: ='T3'!Z22 -> #REF! | C13: ='T2'!Z22 -> #REF! | E13: ='T6'!Z22 -> #REF! | F13: ='T5'!Z22 -> #REF! | J13: 08q1
A14: 09q2 | B14: ='T3'!Z23 -> #REF! | C14: ='T2'!Z23 -> #REF! | E14: ='T6'!Z23 -> #REF! | F14: ='T5'!Z23 -> #REF! | J14: 08q2
A15: 09q3 | B15: ='T3'!Z24 -> #REF! | C15: ='T2'!Z24 -> #REF! | E15: ='T6'!Z24 -> #REF! | F15: ='T5'!Z24 -> #REF! | J15: 08q3
A16: 09q4 | B16: ='T3'!Z25 -> #REF! | C16: ='T2'!Z25 -> #REF! | E16: ='T6'!Z25 -> #REF! | F16: ='T5'!Z25 -> #REF! | J16: 08q4
... A22: 11q2 | B22: ='T3'!Z31 -> #REF! | C22: ='T2'!Z31 -> #REF! | E22: ='T6'!Z31 -> #REF! | F22: ='T5'!Z31 -> #REF! | J22: 10q2
A23: 11q3 | B23: ='T3'!Z32 -> #REF! | C23: ='T2'!Z32 -> #REF! | E23: ='T6'!Z32 -> #REF! | F23: ='T5'!Z32 -> #REF!
A24: 11q4 | B24: ='T3'!Z33 -> 0 | C24: ='T2'!Z33 -> 0 | E24: ='T6'!Z33 -> 0 | F24: ='T5'!Z33 -> 0
E25: Y/Y | F25: Q/Q | J25: 10q3
A26: 07q1 | E26: ='T6'!Z14 -> #REF! | F26: ='T5'!Z14 -> #REF! | J26: 10q4
A27: 07q2 | E27: ='T6'!Z15 -> #REF! | F27: ='T5'!Z15 -> #REF! | J27: 11q1
A28: 07q3 | E28: ='T6'!Z16 -> #REF! | F28: ='T5'!Z16 -> #REF! | J28: 11q2
A29: 07q4 | E29: ='T6'!Z17 -> #REF! | F29: ='T5'!Z17 -> #REF! | J29: 11q3
A30: 08q1 | E30: ='T6'!Z18 -> #REF! | F30: ='T5'!Z18 -> #REF! | J30: 11q4
A31: 08q2 | E31: ='T6'!Z19 -> #REF! | F31: ='T5'!Z19 -> #REF!
A32: 08q3 | E32: ='T6'!Z20 -> #REF! | F32: ='T5'!Z20 -> #REF!
A33: 08q4 | E33: ='T6'!Z21 -> #REF! | F33: ='T5'!Z21 -> #REF!
A34: 09q1 | E34: ='T6'!Z22 -> #REF! | F34: ='T5'!Z22 -> #REF!
A35: 09q2 | E35: ='T6'!Z23 -> #REF! | F35: ='T5'!Z23 -> #REF!
A36: 09q3 | E36: ='T6'!Z24 -> #REF! | F36: ='T5'!Z24 -> #REF!
A37: 09q4 | E37: ='T6'!Z25 -> #REF! | F37: ='T5'!Z25 -> #REF!
A38: 10q1 | E38: ='T6'!Z26 -> #REF! | F38: ='T5'!Z26 -> #REF!
A39: 10q2 | E39: ='T6'!Z27 -> #REF! | F39: ='T5'!Z27 -> #REF!
A40: 10q3 | E40: ='T6'!Z28 -> #REF! | F40: ='T5'!Z28 -> #REF!
A41: 10q4 | E41: ='T6'!Z29 -> #REF! | F41: ='T5'!Z29 -> #REF!
A42: 11q1 | E42: ='T6'!Z30 -> #REF! | F42: ='T5'!Z30 -> #REF!
A43: 11q2 | E43: ='T6'!Z31 -> #REF! | F43: ='T5'!Z31 -> #REF!
B44: Agric | C44: Industry | D44: Services | E44: Agric | F44: Industry | G44: Services
A45: 07q1 | B45: ='Current GDP_All'!#REF! -> #REF! | C45: ='Current GDP_All'!#REF! -> #REF! | D45: ='Current GDP_All'!#REF! -> #REF! | E45: =Tsum2!H9 -> #REF! | F45: =Tsum2!I9 -> #REF! | G45: =Tsum2!J9 -> #REF!
A46: 07q2 | B46: ='Current GDP_All'!#REF! -> #REF! | C46: ='Current GDP_All'!#REF! -> #REF! | D46: ='Current GDP_All'!#REF! -> #REF! | E46: =Tsum2!H10 -> #REF! | F46: =Tsum2!I10 -> #REF! | G46: =Tsum2!J10 -> #REF!
A47: 07q3 | B47: ='Current GDP_All'!#REF! -> #REF! | C47: ='Current GDP_All'!#REF! -> #REF! | D47: ='Current GDP_All'!#REF! -> #REF! | E47: =Tsum2!H11 -> #REF! | F47: =Tsum2!I11 -> #REF! | G47: =Tsum2!J11 -> #REF!
A48: 07q4 | B48: ='Current GDP_All'!#REF! -> #REF! | C48: ='Current GDP_All'!#REF! -> #REF! | D48: ='Current GDP_All'!#REF! -> #REF! | E48: =Tsum2!H12 -> #REF! | F48: =Tsum2!I12 -> #REF! | G48: =Tsum2!J12 -> #REF!
A49: 08q1 | B49: ='Current GDP_All'!#REF! -> #REF! | C49: ='Current GDP_All'!#REF! -> #REF! | D49: ='Current GDP_All'!#REF! -> #REF! | E49: =Tsum2!H13 -> #REF! | F49: =Tsum2!I13 -> #REF! | G49: =Tsum2!J13 -> #REF! | U49: Seasonally adjusted Value added growth rates by sectors (Quarter-on-quarter change in %)
A50: 08q2 | B50: ='Current GDP_All'!#REF! -> #REF! | C50: ='Current GDP_All'!#REF! -> #REF! | D50: ='Current GDP_All'!#REF! -> #REF! | E50: =Tsum2!H14 -> #REF! | F50: =Tsum2!I14 -> #REF! | G50: =Tsum2!J14 -> #REF!
A51: 08q3 | B51: ='Current GDP_All'!#REF! -> #REF! | C51: ='Current GDP_All'!#REF! -> #REF! | D51: ='Current GDP_All'!#REF! -> #REF! | E51: =Tsum2!H15 -> #REF! | F51: =Tsum2!I15 -> #REF! | G51: =Tsum2!J15 -> #REF!
A52: 08q4 | B52: ='Current GDP_All'!#REF! -> #REF! | C52: ='Current GDP_All'!#REF! -> #REF! | D52: ='Current GDP_All'!#REF! -> #REF! | E52: =Tsum2!H16 -> #REF! | F52: =Tsum2!I16 -> #REF! | G52: =Tsum2!J16 -> #REF!
A53: 09q1 | B53: ='Current GDP_All'!#REF! -> #REF! | C53: ='Current GDP_All'!#REF! -> #REF! | D53: ='Current GDP_All'!#REF! -> #REF! | E53: =Tsum2!H17 -> #REF! | F53: =Tsum2!I17 -> #REF! | G53: =Tsum2!J17 -> #REF!
A54: 09q2 | B54: ='Current GDP_All'!#REF! -> #REF! | C54: ='Current GDP_All'!#REF! -> #REF! | D54: ='Current GDP_All'!#REF! -> #REF! | E54: =Tsum2!H18 -> #REF! | F54: =Tsum2!I18 -> #REF! | G54: =Tsum2!J18 -> #REF!
A55: 09q3 | B55: ='Current GDP_All'!#REF! -> #REF! | C55: ='Current GDP_All'!#REF! -> #REF! | D55: ='Current GDP_All'!#REF! -> #REF! | E55: =Tsum2!H19 -> #REF! | F55: =Tsum2!I19 -> #REF! | G55: =Tsum2!J19 -> #REF!
A56: 09q4 | B56: ='Current GDP_All'!#REF! -> #REF! | C56: ='Current GDP_All'!#REF! -> #REF! | D56: ='Current GDP_All'!#REF! -> #REF! | E56: =Tsum2!H20 -> #REF! | F56: =Tsum2!I20 -> #REF! | G56: =Tsum2!J20 -> #REF!
A57: 10q1 | B57: ='Current GDP_All'!#REF! -> #REF! | C57: ='Current GDP_All'!#REF! -> #REF! | D57: ='Current GDP_All'!#REF! -> #REF! | E57: =Tsum2!H21 -> #REF! | F57: =Tsum2!I21 -> #REF! | G57: =Tsum2!J21 -> #REF!
A58: 10q2 | B58: ='Current GDP_All'!#REF! -> #REF! | C58: ='Current GDP_All'!#REF! -> #REF! | D58: ='Current GDP_All'!#REF! -> #REF! | E58: =Tsum2!H22 -> #REF! | F58: =Tsum2!I22 -> #REF! | G58: =Tsum2!J22 -> #REF!
A59: 10q3 | B59: ='Current GDP_All'!#REF! -> #REF! | C59: ='Current GDP_All'!#REF! -> #REF! | D59: ='Current GDP_All'!#REF! -> #REF! | E59: =Tsum2!H23 -> #REF! | F59: =Tsum2!I23 -> #REF! | G59: =Tsum2!J23 -> #REF!
A60: 10q4 | B60: ='Current GDP_All'!#REF! -> #REF! | C60: ='Current GDP_All'!#REF! -> #REF! | D60: ='Current GDP_All'!#REF! -> #REF! | E60: =Tsum2!H24 -> #REF! | F60: =Tsum2!I24 -> #REF! | G60: =Tsum2!J24 -> #REF!
A61: 11q1 | B61: ='Current GDP_All'!#REF! -> #REF! | C61: ='Current GDP_All'!#REF! -> #REF! | D61: ='Current GDP_All'!#REF! -> #REF! | E61: =Tsum2!H25 -> #REF! | F61: =Tsum2!I25 -> #REF! | G61: =Tsum2!J25 -> #REF!
A62: 11q2 | B62: ='Current GDP_All'!#REF! -> #REF! | C62: ='Current GDP_All'!#REF! -> #REF! | D62: ='Current GDP_All'!#REF! -> #REF! | E62: =Tsum2!H26 -> #REF! | F62: =Tsum2!I26 -> #REF! | G62: =Tsum2!J26 -> #REF!
B70: q-on-q change, GDP | C70: Agric | D70: Industry | E70: Services
A71: 07q1 | B71: ='T2'!Z14 -> #REF! | C71: ='T2'!AC14 -> #REF! | D71: ='T2'!AD14 -> #REF! | E71: ='T2'!AE14 -> #REF!
A72: 07q2 | B72: ='T2'!Z15 -> #REF! | C72: ='T2'!AC15 -> #REF! | D72: ='T2'!AD15 -> #REF! | E72: ='T2'!AE15 -> #REF!
A73: 07q3 | B73: ='T2'!Z16 -> #REF! | C73: ='T2'!AC16 -> #REF! | D73: ='T2'!AD16 -> #REF! | E73: ='T2'!AE16 -> #REF!
A74: 07q4 | B74: ='T2'!Z17 -> #REF! | C74: ='T2'!AC17 -> #REF! | D74: ='T2'!AD17 -> #REF! | E74: ='T2'!AE17 -> #REF!
A75: 08q1 | B75: ='T2'!Z18 -> #REF! | C75: ='T2'!AC18 -> #REF! | D75: ='T2'!AD18 -> #REF! | E75: ='T2'!AE18 -> #REF!
A76: 08q2 | B76: ='T2'!Z19 -> #REF! | C76: ='T2'!AC19 -> #REF! | D76: ='T2'!AD19 -> #REF! | E76: ='T2'!AE19 -> #REF!
A77: 08q3 | B77: ='T2'!Z20 -> #REF! | C77: ='T2'!AC20 -> #REF! | D77: ='T2'!AD20 -> #REF! | E77: ='T2'!AE20 -> #REF!
A78: 08q4 | B78: ='T2'!Z21 -> #REF! | C78: ='T2'!AC21 -> #REF! | D78: ='T2'!AD21 -> #REF! | E78: ='T2'!AE21 -> #REF!
A79: 09q1 | B79: ='T2'!Z22 -> #REF! | C79: ='T2'!AC22 -> #REF! | D79: ='T2'!AD22 -> #REF! | E79: ='T2'!AE22 -> #REF!
A80: 09q2 | B80: ='T2'!Z23 -> #REF! | C80: ='T2'!AC23 -> #REF! | D80: ='T2'!AD23 -> #REF! | E80: ='T2'!AE23 -> #REF!
A81: 09q3 | B81: ='T2'!Z24 -> #REF! | C81: ='T2'!AC24 -> #REF! | D81: ='T2'!AD24 -> #REF! | E81: ='T2'!AE24 -> #REF!
A82: 09q4 | B82: ='T2'!Z25 -> #REF! | C82: ='T2'!AC25 -> #REF! | D82: ='T2'!AD25 -> #REF! | E82: ='T2'!AE25 -> #REF!
... A87: 11q1 | B87: ='T2'!Z30 -> #REF! | C87: ='T2'!AC30 -> #REF! | D87: ='T2'!AD30 -> #REF! | E87: ='T2'!AE30 -> #REF!
A90: Q-on-Q change 01-2011
A91: Agric | B91: ='T2'!AC30 -> #REF!
A92: Industry | B92: ='T2'!AD30 -> #REF!
A93: Services | B93: ='T2'!AE30 -> #REF!
A94: Combined | B94: ='T2'!Z30 -> #REF!
AD97: Ghana Statistical Service (GSS)

Sheet qly growth rates
B1: Gross Value Added by Activity Constant 2006 Prices GHc Million
C2: Agriculture | G2: Industry
A3: Year | B3: Quarter | C3: Crops & Cocoa | D3: Livestock | E3: Forestry | F3: Fishing | G3: Mining and Quarrying | H3: Manufacturing | I3: Electricity | J3: Water & Sewerage | K3: Construction | L3: Trade; Repair Of Vehicles, Household Goods | M3: Hotels And Restaurants | N3: Transport & Storage | O3: Information & Communication | P3: Financial & Insurance Activities | Q3: Real Estate Activities | R3: Business & other Services Activities | S3: Public Administration | T3: Education | U3: Health | V3: Other Personal Service Activities | W3: GDP at basic prices | X3: Net Taxes | Y3: GDP at Constant Prices
A5: 2006 | B5: 1
B6: 2 | C6: =100*(#REF!/#REF!-1) -> #REF! | D6: =100*(#REF!/#REF!-1) -> #REF! | E6: =100*(#REF!/#REF!-1) -> #REF! | F6: =100*(#REF!/#REF!-1) -> #REF! | G6: =100*(#REF!/#REF!-1) -> #REF! | H6: =100*(#REF!/#REF!-1) -> #REF! | I6: =100*(#REF!/#REF!-1) -> #REF! | J6: =100*(#REF!/#REF!-1) -> #REF! | ... Y6: =100*(#REF!/#REF!-1) -> #REF!
B7: 3 | C7: =100*(#REF!/#REF!-1) -> #REF! | D7: =100*(#REF!/#REF!-1) -> #REF! | E7: =100*(#REF!/#REF!-1) -> #REF! | F7: =100*(#REF!/#REF!-1) -> #REF! | G7: =100*(#REF!/#REF!-1) -> #REF! | H7: =100*(#REF!/#REF!-1) -> #REF! | I7: =100*(#REF!/#REF!-1) -> #REF! | J7: =100*(#REF!/#REF!-1) -> #REF! | ... Y7: =100*(#REF!/#REF!-1) -> #REF!
B8: 4 | C8: =100*(#REF!/#REF!-1) -> #REF! | D8: =100*(#REF!/#REF!-1) -> #REF! | E8: =100*(#REF!/#REF!-1) -> #REF! | F8: =100*(#REF!/#REF!-1) -> #REF! | G8: =100*(#REF!/#REF!-1) -> #REF! | H8: =100*(#REF!/#REF!-1) -> #REF! | I8: =100*(#REF!/#REF!-1) -> #REF! | J8: =100*(#REF!/#REF!-1) -> #REF! | ... Y8: =100*(#REF!/#REF!-1) -> #REF!
A9: 2007 | B9: 1 | C9: =100*(#REF!/#REF!-1) -> #REF! | D9: =100*(#REF!/#REF!-1) -> #REF! | E9: =100*(#REF!/#REF!-1) -> #REF! | F9: =100*(#REF!/#REF!-1) -> #REF! | G9: =100*(#REF!/#REF!-1) -> #REF! | H9: =100*(#REF!/#REF!-1) -> #REF! | I9: =100*(#REF!/#REF!-1) -> #REF! | J9: =100*(#REF!/#REF!-1) -> #REF! | ... Y9: =100*(#REF!/#REF!-1) -> #REF!
B10: 2 | C10: =100*(#REF!/#REF!-1) -> #REF! | D10: =100*(#REF!/#REF!-1) -> #REF! | E10: =100*(#REF!/#REF!-1) -> #REF! | F10: =100*(#REF!/#REF!-1) -> #REF! | G10: =100*(#REF!/#REF!-1) -> #REF! | H10: =100*(#REF!/#REF!-1) -> #REF! | I10: =100*(#REF!/#REF!-1) -> #REF! | J10: =100*(#REF!/#REF!-1) -> #REF! | ... Y10: =100*(#REF!/#REF!-1) -> #REF!
B11: 3 | C11: =100*(#REF!/#REF!-1) -> #REF! | D11: =100*(#REF!/#REF!-1) -> #REF! | E11: =100*(#REF!/#REF!-1) -> #REF! | F11: =100*(#REF!/#REF!-1) -> #REF! | G11: =100*(#REF!/#REF!-1) -> #REF! | H11: =100*(#REF!/#REF!-1) -> #REF! | I11: =100*(#REF!/#REF!-1) -> #REF! | J11: =100*(#REF!/#REF!-1) -> #REF! | ... Y11: =100*(#REF!/#REF!-1) -> #REF!
B12: 4 | C12: =100*(#REF!/#REF!-1) -> #REF! | D12: =100*(#REF!/#REF!-1) -> #REF! | E12: =100*(#REF!/#REF!-1) -> #REF! | F12: =100*(#REF!/#REF!-1) -> #REF! | G12: =100*(#REF!/#REF!-1) -> #REF! | H12: =100*(#REF!/#REF!-1) -> #REF! | I12: =100*(#REF!/#REF!-1) -> #REF! | J12: =100*(#REF!/#REF!-1) -> #REF! | ... Y12: =100*(#REF!/#REF!-1) -> #REF!
A13: 2008 | B13: 1 | C13: =100*(#REF!/#REF!-1) -> #REF! | D13: =100*(#REF!/#REF!-1) -> #REF! | E13: =100*(#REF!/#REF!-1) -> #REF! | F13: =100*(#REF!/#REF!-1) -> #REF! | G13: =100*(#REF!/#REF!-1) -> #REF! | H13: =100*(#REF!/#REF!-1) -> #REF! | I13: =100*(#REF!/#REF!-1) -> #REF! | J13: =100*(#REF!/#REF!-1) -> #REF! | ... Y13: =100*(#REF!/#REF!-1) -> #REF!
B14: 2 | C14: =100*(#REF!/#REF!-1) -> #REF! | D14: =100*(#REF!/#REF!-1) -> #REF! | E14: =100*(#REF!/#REF!-1) -> #REF! | F14: =100*(#REF!/#REF!-1) -> #REF! | G14: =100*(#REF!/#REF!-1) -> #REF! | H14: =100*(#REF!/#REF!-1) -> #REF! | I14: =100*(#REF!/#REF!-1) -> #REF! | J14: =100*(#REF!/#REF!-1) -> #REF! | ... Y14: =100*(#REF!/#REF!-1) -> #REF!
B15: 3 | C15: =100*(#REF!/#REF!-1) -> #REF! | D15: =100*(#REF!/#REF!-1) -> #REF! | E15: =100*(#REF!/#REF!-1) -> #REF! | F15: =100*(#REF!/#REF!-1) -> #REF! | G15: =100*(#REF!/#REF!-1) -> #REF! | H15: =100*(#REF!/#REF!-1) -> #REF! | I15: =100*(#REF!/#REF!-1) -> #REF! | J15: =100*(#REF!/#REF!-1) -> #REF! | ... Y15: =100*(#REF!/#REF!-1) -> #REF!
B16: 4 | C16: =100*(#REF!/#REF!-1) -> #REF! | D16: =100*(#REF!/#REF!-1) -> #REF! | E16: =100*(#REF!/#REF!-1) -> #REF! | F16: =100*(#REF!/#REF!-1) -> #REF! | G16: =100*(#REF!/#REF!-1) -> #REF! | H16: =100*(#REF!/#REF!-1) -> #REF! | I16: =100*(#REF!/#REF!-1) -> #REF! | J16: =100*(#REF!/#REF!-1) -> #REF! | ... Y16: =100*(#REF!/#REF!-1) -> #REF!
A17: 2009 | B17: 1 | C17: =100*(#REF!/#REF!-1) -> #REF! | D17: =100*(#REF!/#REF!-1) -> #REF! | E17: =100*(#REF!/#REF!-1) -> #REF! | F17: =100*(#REF!/#REF!-1) -> #REF! | G17: =100*(#REF!/#REF!-1) -> #REF! | H17: =100*(#REF!/#REF!-1) -> #REF! | I17: =100*(#REF!/#REF!-1) -> #REF! | J17: =100*(#REF!/#REF!-1) -> #REF! | ... Y17: =100*(#REF!/#REF!-1) -> #REF!
B18: 2 | C18: =100*(#REF!/#REF!-1) -> #REF! | D18: =100*(#REF!/#REF!-1) -> #REF! | E18: =100*(#REF!/#REF!-1) -> #REF! | F18: =100*(#REF!/#REF!-1) -> #REF! | G18: =100*(#REF!/#REF!-1) -> #REF! | H18: =100*(#REF!/#REF!-1) -> #REF! | I18: =100*(#REF!/#REF!-1) -> #REF! | J18: =100*(#REF!/#REF!-1) -> #REF! | ... Y18: =100*(#REF!/#REF!-1) -> #REF!
B19: 3 | C19: =100*(#REF!/#REF!-1) -> #REF! | D19: =100*(#REF!/#REF!-1) -> #REF! | E19: =100*(#REF!/#REF!-1) -> #REF! | F19: =100*(#REF!/#REF!-1) -> #REF! | G19: =100*(#REF!/#REF!-1) -> #REF! | H19: =100*(#REF!/#REF!-1) -> #REF! | I19: =100*(#REF!/#REF!-1) -> #REF! | J19: =100*(#REF!/#REF!-1) -> #REF! | ... Y19: =100*(#REF!/#REF!-1) -> #REF!
B20: 4 | C20: =100*(#REF!/#REF!-1) -> #REF! | D20: =100*(#REF!/#REF!-1) -> #REF! | E20: =100*(#REF!/#REF!-1) -> #REF! | F20: =100*(#REF!/#REF!-1) -> #REF! | G20: =100*(#REF!/#REF!-1) -> #REF! | H20: =100*(#REF!/#REF!-1) -> #REF! | I20: =100*(#REF!/#REF!-1) -> #REF! | J20: =100*(#REF!/#REF!-1) -> #REF! | ... Y20: =100*(#REF!/#REF!-1) -> #REF!
A21: 2010 | B21: 1 | C21: =100*(#REF!/#REF!-1) -> #REF! | D21: =100*(#REF!/#REF!-1) -> #REF! | E21: =100*(#REF!/#REF!-1) -> #REF! | F21: =100*(#REF!/#REF!-1) -> #REF! | G21: =100*(#REF!/#REF!-1) -> #REF! | H21: =100*(#REF!/#REF!-1) -> #REF! | I21: =100*(#REF!/#REF!-1) -> #REF! | J21: =100*(#REF!/#REF!-1) -> #REF! | ... Y21: =100*(#REF!/#REF!-1) -> #REF!
B22: 2 | C22: =100*(#REF!/#REF!-1) -> #REF! | D22: =100*(#REF!/#REF!-1) -> #REF! | E22: =100*(#REF!/#REF!-1) -> #REF! | F22: =100*(#REF!/#REF!-1) -> #REF! | G22: =100*(#REF!/#REF!-1) -> #REF! | H22: =100*(#REF!/#REF!-1) -> #REF! | I22: =100*(#REF!/#REF!-1) -> #REF! | J22: =100*(#REF!/#REF!-1) -> #REF! | ... Y22: =100*(#REF!/#REF!-1) -> #REF!
B23: 3 | C23: =100*(#REF!/#REF!-1) -> #REF! | D23: =100*(#REF!/#REF!-1) -> #REF! | E23: =100*(#REF!/#REF!-1) -> #REF! | F23: =100*(#REF!/#REF!-1) -> #REF! | G23: =100*(#REF!/#REF!-1) -> #REF! | H23: =100*(#REF!/#REF!-1) -> #REF! | I23: =100*(#REF!/#REF!-1) -> #REF! | J23: =100*(#REF!/#REF!-1) -> #REF! | ... Y23: =100*(#REF!/#REF!-1) -> #REF!
B24: 4 | C24: =100*(#REF!/#REF!-1) -> #REF! | D24: =100*(#REF!/#REF!-1) -> #REF! | E24: =100*(#REF!/#REF!-1) -> #REF! | F24: =100*(#REF!/#REF!-1) -> #REF! | G24: =100*(#REF!/#REF!-1) -> #REF! | H24: =100*(#REF!/#REF!-1) -> #REF! | I24: =100*(#REF!/#REF!-1) -> #REF! | J24: =100*(#REF!/#REF!-1) -> #REF! | ... Y24: =100*(#REF!/#REF!-1) -> #REF!
A25: 2011 | B25: 1 | C25: =100*(#REF!/#REF!-1) -> #REF! | D25: =100*(#REF!/#REF!-1) -> #REF! | E25: =100*(#REF!/#REF!-1) -> #REF! | F25: =100*(#REF!/#REF!-1) -> #REF! | G25: =100*(#REF!/#REF!-1) -> #REF! | H25: =100*(#REF!/#REF!-1) -> #REF! | I25: =100*(#REF!/#REF!-1) -> #REF! | J25: =100*(#REF!/#REF!-1) -> #REF! | ... Y25: =100*(#REF!/#REF!-1) -> #REF!
B26: 2 | C26: =100*(#REF!/#REF!-1) -> #REF! | D26: =100*(#REF!/#REF!-1) -> #REF! | E26: =100*(#REF!/#REF!-1) -> #REF! | F26: =100*(#REF!/#REF!-1) -> #REF! | G26: =100*(#REF!/#REF!-1) -> #REF! | H26: =100*(#REF!/#REF!-1) -> #REF! | I26: =100*(#REF!/#REF!-1) -> #REF! | J26: =100*(#REF!/#REF!-1) -> #REF! | ... Y26: =100*(#REF!/#REF!-1) -> #REF!
B27: 3 | C27: =100*(#REF!/#REF!-1) -> #REF! | D27: =100*(#REF!/#REF!-1) -> #REF! | E27: =100*(#REF!/#REF!-1) -> #REF! | F27: =100*(#REF!/#REF!-1) -> #REF! | G27: =100*(#REF!/#REF!-1) -> #REF! | H27: =100*(#REF!/#REF!-1) -> #REF! | I27: =100*(#REF!/#REF!-1) -> #REF! | J27: =100*(#REF!/#REF!-1) -> #REF! | ... Y27: =100*(#REF!/#REF!-1) -> #REF!
B28: 4

Sheet YYgrowthrates
B1: Gross Value Added by Activity Constant 2006 Prices - Growth Rates
C2: Agriculture | G2: Industry
A3: Year | B3: Quarter | C3: Crops & Cocoa | D3: Livestock | E3: Forestry | F3: Fishing | G3: Mining and Quarrying | H3: Manufacturing | I3: Electricity | J3: Water & Sewerage | K3: Construction | L3: Trade; Repair Of Vehicles, Household Goods | M3: Hotels And Restaurants | N3: Transport & Storage | O3: Information & Communication | P3: Financial & Insurance Activities | Q3: Real Estate Activities | R3: Business & other Services Activities | S3: Public Administration | T3: Education | U3: Health | V3: Other Personal Service Activities | W3: GDP at basic prices | X3: Net Taxes | Y3: GDP at Constant Prices
A4: 2007 | C4: =(#REF!/#REF!-1)*100 -> #REF! | D4: =(#REF!/#REF!-1)*100 -> #REF! | E4: =(#REF!/#REF!-1)*100 -> #REF! | F4: =(#REF!/#REF!-1)*100 -> #REF! | G4: =(#REF!/#REF!-1)*100 -> #REF! | H4: =(#REF!/#REF!-1)*100 -> #REF! | I4: =(#REF!/#REF!-1)*100 -> #REF! | J4: =(#REF!/#REF!-1)*100 -> #REF! | ... Y4: =(#REF!/#REF!-1)*100 -> #REF!
A5: 2008 | C5: =(#REF!/#REF!-1)*100 -> #REF! | D5: =(#REF!/#REF!-1)*100 -> #REF! | E5: =(#REF!/#REF!-1)*100 -> #REF! | F5: =(#REF!/#REF!-1)*100 -> #REF! | G5: =(#REF!/#REF!-1)*100 -> #REF! | H5: =(#REF!/#REF!-1)*100 -> #REF! | I5: =(#REF!/#REF!-1)*100 -> #REF! | J5: =(#REF!/#REF!-1)*100 -> #REF! | ... Y5: =(#REF!/#REF!-1)*100 -> #REF!
A6: 2009 | C6: =(#REF!/#REF!-1)*100 -> #REF! | D6: =(#REF!/#REF!-1)*100 -> #REF! | E6: =(#REF!/#REF!-1)*100 -> #REF! | F6: =(#REF!/#REF!-1)*100 -> #REF! | G6: =(#REF!/#REF!-1)*100 -> #REF! | H6: =(#REF!/#REF!-1)*100 -> #REF! | I6: =(#REF!/#REF!-1)*100 -> #REF! | J6: =(#REF!/#REF!-1)*100 -> #REF! | ... Y6: =(#REF!/#REF!-1)*100 -> #REF!
A7: 2010 | C7: =(#REF!/#REF!-1)*100 -> #REF! | D7: =(#REF!/#REF!-1)*100 -> #REF! | E7: =(#REF!/#REF!-1)*100 -> #REF! | F7: =(#REF!/#REF!-1)*100 -> #REF! | G7: =(#REF!/#REF!-1)*100 -> #REF! | H7: =(#REF!/#REF!-1)*100 -> #REF! | I7: =(#REF!/#REF!-1)*100 -> #REF! | J7: =(#REF!/#REF!-1)*100 -> #REF! | ... Y7: =(#REF!/#REF!-1)*100 -> #REF!
A9: 2007 | B9: 1 | C9: =(#REF!/#REF!-1)*100 -> #REF! | D9: =(#REF!/#REF!-1)*100 -> #REF! | E9: =(#REF!/#REF!-1)*100 -> #REF! | F9: =(#REF!/#REF!-1)*100 -> #REF! | G9: =(#REF!/#REF!-1)*100 -> #REF! | H9: =(#REF!/#REF!-1)*100 -> #REF! | I9: =(#REF!/#REF!-1)*100 -> #REF! | J9: =(#REF!/#REF!-1)*100 -> #REF! | ... Y9: =(#REF!/#REF!-1)*100 -> #REF!
B10: 2 | C10: =(#REF!/#REF!-1)*100 -> #REF! | D10: =(#REF!/#REF!-1)*100 -> #REF! | E10: =(#REF!/#REF!-1)*100 -> #REF! | F10: =(#REF!/#REF!-1)*100 -> #REF! | G10: =(#REF!/#REF!-1)*100 -> #REF! | H10: =(#REF!/#REF!-1)*100 -> #REF! | I10: =(#REF!/#REF!-1)*100 -> #REF! | J10: =(#REF!/#REF!-1)*100 -> #REF! | ... Y10: =(#REF!/#REF!-1)*100 -> #REF!
B11: 3 | C11: =(#REF!/#REF!-1)*100 -> #REF! | D11: =(#REF!/#REF!-1)*100 -> #REF! | E11: =(#REF!/#REF!-1)*100 -> #REF! | F11: =(#REF!/#REF!-1)*100 -> #REF! | G11: =(#REF!/#REF!-1)*100 -> #REF! | H11: =(#REF!/#REF!-1)*100 -> #REF! | I11: =(#REF!/#REF!-1)*100 -> #REF! | J11: =(#REF!/#REF!-1)*100 -> #REF! | ... Y11: =(#REF!/#REF!-1)*100 -> #REF!
B12: 4 | C12: =(#REF!/#REF!-1)*100 -> #REF! | D12: =(#REF!/#REF!-1)*100 -> #REF! | E12: =(#REF!/#REF!-1)*100 -> #REF! | F12: =(#REF!/#REF!-1)*100 -> #REF! | G12: =(#REF!/#REF!-1)*100 -> #REF! | H12: =(#REF!/#REF!-1)*100 -> #REF! | I12: =(#REF!/#REF!-1)*100 -> #REF! | J12: =(#REF!/#REF!-1)*100 -> #REF! | ... Y12: =(#REF!/#REF!-1)*100 -> #REF!
A13: 2008 | B13: 1 | C13: =(#REF!/#REF!-1)*100 -> #REF! | D13: =(#REF!/#REF!-1)*100 -> #REF! | E13: =(#REF!/#REF!-1)*100 -> #REF! | F13: =(#REF!/#REF!-1)*100 -> #REF! | G13: =(#REF!/#REF!-1)*100 -> #REF! | H13: =(#REF!/#REF!-1)*100 -> #REF! | I13: =(#REF!/#REF!-1)*100 -> #REF! | J13: =(#REF!/#REF!-1)*100 -> #REF! | ... Y13: =(#REF!/#REF!-1)*100 -> #REF!
B14: 2 | C14: =(#REF!/#REF!-1)*100 -> #REF! | D14: =(#REF!/#REF!-1)*100 -> #REF! | E14: =(#REF!/#REF!-1)*100 -> #REF! | F14: =(#REF!/#REF!-1)*100 -> #REF! | G14: =(#REF!/#REF!-1)*100 -> #REF! | H14: =(#REF!/#REF!-1)*100 -> #REF! | I14: =(#REF!/#REF!-1)*100 -> #REF! | J14: =(#REF!/#REF!-1)*100 -> #REF! | ... Y14: =(#REF!/#REF!-1)*100 -> #REF!
B15: 3 | C15: =(#REF!/#REF!-1)*100 -> #REF! | D15: =(#REF!/#REF!-1)*100 -> #REF! | E15: =(#REF!/#REF!-1)*100 -> #REF! | F15: =(#REF!/#REF!-1)*100 -> #REF! | G15: =(#REF!/#REF!-1)*100 -> #REF! | H15: =(#REF!/#REF!-1)*100 -> #REF! | I15: =(#REF!/#REF!-1)*100 -> #REF! | J15: =(#REF!/#REF!-1)*100 -> #REF! | ... Y15: =(#REF!/#REF!-1)*100 -> #REF!
B16: 4 | C16: =(#REF!/#REF!-1)*100 -> #REF! | D16: =(#REF!/#REF!-1)*100 -> #REF! | E16: =(#REF!/#REF!-1)*100 -> #REF! | F16: =(#REF!/#REF!-1)*100 -> #REF! | G16: =(#REF!/#REF!-1)*100 -> #REF! | H16: =(#REF!/#REF!-1)*100 -> #REF! | I16: =(#REF!/#REF!-1)*100 -> #REF! | J16: =(#REF!/#REF!-1)*100 -> #REF! | ... Y16: =(#REF!/#REF!-1)*100 -> #REF!
A17: 2009 | B17: 1 | C17: =(#REF!/#REF!-1)*100 -> #REF! | D17: =(#REF!/#REF!-1)*100 -> #REF! | E17: =(#REF!/#REF!-1)*100 -> #REF! | F17: =(#REF!/#REF!-1)*100 -> #REF! | G17: =(#REF!/#REF!-1)*100 -> #REF! | H17: =(#REF!/#REF!-1)*100 -> #REF! | I17: =(#REF!/#REF!-1)*100 -> #REF! | J17: =(#REF!/#REF!-1)*100 -> #REF! | ... Y17: =(#REF!/#REF!-1)*100 -> #REF!
B18: 2 | C18: =(#REF!/#REF!-1)*100 -> #REF! | D18: =(#REF!/#REF!-1)*100 -> #REF! | E18: =(#REF!/#REF!-1)*100 -> #REF! | F18: =(#REF!/#REF!-1)*100 -> #REF! | G18: =(#REF!/#REF!-1)*100 -> #REF! | H18: =(#REF!/#REF!-1)*100 -> #REF! | I18: =(#REF!/#REF!-1)*100 -> #REF! | J18: =(#REF!/#REF!-1)*100 -> #REF! | ... Y18: =(#REF!/#REF!-1)*100 -> #REF!
B19: 3 | C19: =(#REF!/#REF!-1)*100 -> #REF! | D19: =(#REF!/#REF!-1)*100 -> #REF! | E19: =(#REF!/#REF!-1)*100 -> #REF! | F19: =(#REF!/#REF!-1)*100 -> #REF! | G19: =(#REF!/#REF!-1)*100 -> #REF! | H19: =(#REF!/#REF!-1)*100 -> #REF! | I19: =(#REF!/#REF!-1)*100 -> #REF! | J19: =(#REF!/#REF!-1)*100 -> #REF! | ... Y19: =(#REF!/#REF!-1)*100 -> #REF!
B20: 4 | C20: =(#REF!/#REF!-1)*100 -> #REF! | D20: =(#REF!/#REF!-1)*100 -> #REF! | E20: =(#REF!/#REF!-1)*100 -> #REF! | F20: =(#REF!/#REF!-1)*100 -> #REF! | G20: =(#REF!/#REF!-1)*100 -> #REF! | H20: =(#REF!/#REF!-1)*100 -> #REF! | I20: =(#REF!/#REF!-1)*100 -> #REF! | J20: =(#REF!/#REF!-1)*100 -> #REF! | ... Y20: =(#REF!/#REF!-1)*100 -> #REF!
A21: 2010 | B21: 1 | C21: =(#REF!/#REF!-1)*100 -> #REF! | D21: =(#REF!/#REF!-1)*100 -> #REF! | E21: =(#REF!/#REF!-1)*100 -> #REF! | F21: =(#REF!/#REF!-1)*100 -> #REF! | G21: =(#REF!/#REF!-1)*100 -> #REF! | H21: =(#REF!/#REF!-1)*100 -> #REF! | I21: =(#REF!/#REF!-1)*100 -> #REF! | J21: =(#REF!/#REF!-1)*100 -> #REF! | ... Y21: =(#REF!/#REF!-1)*100 -> #REF!
B22: 2 | C22: =(#REF!/#REF!-1)*100 -> #REF! | D22: =(#REF!/#REF!-1)*100 -> #REF! | E22: =(#REF!/#REF!-1)*100 -> #REF! | F22: =(#REF!/#REF!-1)*100 -> #REF! | G22: =(#REF!/#REF!-1)*100 -> #REF! | H22: =(#REF!/#REF!-1)*100 -> #REF! | I22: =(#REF!/#REF!-1)*100 -> #REF! | J22: =(#REF!/#REF!-1)*100 -> #REF! | ... Y22: =(#REF!/#REF!-1)*100 -> #REF!
B23: 3 | C23: =(#REF!/#REF!-1)*100 -> #REF! | D23: =(#REF!/#REF!-1)*100 -> #REF! | E23: =(#REF!/#REF!-1)*100 -> #REF! | F23: =(#REF!/#REF!-1)*100 -> #REF! | G23: =(#REF!/#REF!-1)*100 -> #REF! | H23: =(#REF!/#REF!-1)*100 -> #REF! | I23: =(#REF!/#REF!-1)*100 -> #REF! | J23: =(#REF!/#REF!-1)*100 -> #REF! | ... Y23: =(#REF!/#REF!-1)*100 -> #REF!
B24: 4 | C24: =(#REF!/#REF!-1)*100 -> #REF! | D24: =(#REF!/#REF!-1)*100 -> #REF! | E24: =(#REF!/#REF!-1)*100 -> #REF! | F24: =(#REF!/#REF!-1)*100 -> #REF! | G24: =(#REF!/#REF!-1)*100 -> #REF! | H24: =(#REF!/#REF!-1)*100 -> #REF! | I24: =(#REF!/#REF!-1)*100 -> #REF! | J24: =(#REF!/#REF!-1)*100 -> #REF! | ... Y24: =(#REF!/#REF!-1)*100 -> #REF!
A25: 2011 | B25: 1 | C25: =(#REF!/#REF!-1)*100 -> #REF! | D25: =(#REF!/#REF!-1)*100 -> #REF! | E25: =(#REF!/#REF!-1)*100 -> #REF! | F25: =(#REF!/#REF!-1)*100 -> #REF! | G25: =(#REF!/#REF!-1)*100 -> #REF! | H25: =(#REF!/#REF!-1)*100 -> #REF! | I25: =(#REF!/#REF!-1)*100 -> #REF! | J25: =(#REF!/#REF!-1)*100 -> #REF! | ... Y25: =(#REF!/#REF!-1)*100 -> #REF!
B26: 2 | C26: =(#REF!/#REF!-1)*100 -> #REF! | D26: =(#REF!/#REF!-1)*100 -> #REF! | E26: =(#REF!/#REF!-1)*100 -> #REF! | F26: =(#REF!/#REF!-1)*100 -> #REF! | G26: =(#REF!/#REF!-1)*100 -> #REF! | H26: =(#REF!/#REF!-1)*100 -> #REF! | I26: =(#REF!/#REF!-1)*100 -> #REF! | J26: =(#REF!/#REF!-1)*100 -> #REF! | ... Y26: =(#REF!/#REF!-1)*100 -> #REF!
B27: 3 | C27: =(#REF!/#REF!-1)*100 -> #REF! | D27: =(#REF!/#REF!-1)*100 -> #REF! | E27: =(#REF!/#REF!-1)*100 -> #REF! | F27: =(#REF!/#REF!-1)*100 -> #REF! | G27: =(#REF!/#REF!-1)*100 -> #REF! | H27: =(#REF!/#REF!-1)*100 -> #REF! | I27: =(#REF!/#REF!-1)*100 -> #REF! | J27: =(#REF!/#REF!-1)*100 -> #REF! | ... Y27: =(#REF!/#REF!-1)*100 -> #REF!
B28: 4

Sheet %QQSea Adjust
A1: Table 4 - | B1: Percentage change Seasonal Adjusted Gross Value Added by Activity at Constant 2006 Prices
C2: Agriculture Sector | G2: Industry Sector | L2: Services Sector
A3: Year | B3: Quarter | C3: Crops & Cocoa | D3: Livestock | E3: Forestry | F3: Fishing | G3: Mining and Quarrying | H3: Manufacturing | I3: Electricity | J3: Water & Sewerage | K3: Construction | L3: Trade; Repair Of Vehicles, Household Goods | M3: Hotels And Restaurants | N3: Transport & Storage | O3: Information & Communication | P3: Financial & Insurance Activities | Q3: Real Estate Activities | R3: Business & other Services Activities | S3: Public Administration | T3: Education | U3: Health | V3: Other Personal Service Activities | W3: GDP at basic prices | X3: Net Taxes | Y3: GDP at Constant Prices
A5: 2006 | B5: 1
B6: 2 | C6: =100*(#REF!/#REF!-1) -> #REF! | D6: =100*(#REF!/#REF!-1) -> #REF! | E6: =100*(#REF!/#REF!-1) -> #REF! | F6: =100*(#REF!/#REF!-1) -> #REF! | G6: =100*(#REF!/#REF!-1) -> #REF! | H6: =100*(#REF!/#REF!-1) -> #REF! | I6: =100*(#REF!/#REF!-1) -> #REF! | J6: =100*(#REF!/#REF!-1) -> #REF! | ... Y6: =100*(#REF!/#REF!-1) -> #REF!
B7: 3 | C7: =100*(#REF!/#REF!-1) -> #REF! | D7: =100*(#REF!/#REF!-1) -> #REF! | E7: =100*(#REF!/#REF!-1) -> #REF! | F7: =100*(#REF!/#REF!-1) -> #REF! | G7: =100*(#REF!/#REF!-1) -> #REF! | H7: =100*(#REF!/#REF!-1) -> #REF! | I7: =100*(#REF!/#REF!-1) -> #REF! | J7: =100*(#REF!/#REF!-1) -> #REF! | ... Y7: =100*(#REF!/#REF!-1) -> #REF!
B8: 4 | C8: =100*(#REF!/#REF!-1) -> #REF! | D8: =100*(#REF!/#REF!-1) -> #REF! | E8: =100*(#REF!/#REF!-1) -> #REF! | F8: =100*(#REF!/#REF!-1) -> #REF! | G8: =100*(#REF!/#REF!-1) -> #REF! | H8: =100*(#REF!/#REF!-1) -> #REF! | I8: =100*(#REF!/#REF!-1) -> #REF! | J8: =100*(#REF!/#REF!-1) -> #REF! | ... Y8: =100*(#REF!/#REF!-1) -> #REF!
A9: 2007 | B9: 1 | C9: =100*(#REF!/#REF!-1) -> #REF! | D9: =100*(#REF!/#REF!-1) -> #REF! | E9: =100*(#REF!/#REF!-1) -> #REF! | F9: =100*(#REF!/#REF!-1) -> #REF! | G9: =100*(#REF!/#REF!-1) -> #REF! | H9: =100*(#REF!/#REF!-1) -> #REF! | I9: =100*(#REF!/#REF!-1) -> #REF! | J9: =100*(#REF!/#REF!-1) -> #REF! | ... Y9: =100*(#REF!/#REF!-1) -> #REF!
B10: 2 | C10: =100*(#REF!/#REF!-1) -> #REF! | D10: =100*(#REF!/#REF!-1) -> #REF! | E10: =100*(#REF!/#REF!-1) -> #REF! | F10: =100*(#REF!/#REF!-1) -> #REF! | G10: =100*(#REF!/#REF!-1) -> #REF! | H10: =100*(#REF!/#REF!-1) -> #REF! | I10: =100*(#REF!/#REF!-1) -> #REF! | J10: =100*(#REF!/#REF!-1) -> #REF! | ... Y10: =100*(#REF!/#REF!-1) -> #REF!
B11: 3 | C11: =100*(#REF!/#REF!-1) -> #REF! | D11: =100*(#REF!/#REF!-1) -> #REF! | E11: =100*(#REF!/#REF!-1) -> #REF! | F11: =100*(#REF!/#REF!-1) -> #REF! | G11: =100*(#REF!/#REF!-1) -> #REF! | H11: =100*(#REF!/#REF!-1) -> #REF! | I11: =100*(#REF!/#REF!-1) -> #REF! | J11: =100*(#REF!/#REF!-1) -> #REF! | ... Y11: =100*(#REF!/#REF!-1) -> #REF!
B12: 4 | C12: =100*(#REF!/#REF!-1) -> #REF! | D12: =100*(#REF!/#REF!-1) -> #REF! | E12: =100*(#REF!/#REF!-1) -> #REF! | F12: =100*(#REF!/#REF!-1) -> #REF! | G12: =100*(#REF!/#REF!-1) -> #REF! | H12: =100*(#REF!/#REF!-1) -> #REF! | I12: =100*(#REF!/#REF!-1) -> #REF! | J12: =100*(#REF!/#REF!-1) -> #REF! | ... Y12: =100*(#REF!/#REF!-1) -> #REF!
A13: 2008 | B13: 1 | C13: =100*(#REF!/#REF!-1) -> #REF! | D13: =100*(#REF!/#REF!-1) -> #REF! | E13: =100*(#REF!/#REF!-1) -> #REF! | F13: =100*(#REF!/#REF!-1) -> #REF! | G13: =100*(#REF!/#REF!-1) -> #REF! | H13: =100*(#REF!/#REF!-1) -> #REF! | I13: =100*(#REF!/#REF!-1) -> #REF! | J13: =100*(#REF!/#REF!-1) -> #REF! | ... Y13: =100*(#REF!/#REF!-1) -> #REF!
B14: 2 | C14: =100*(#REF!/#REF!-1) -> #REF! | D14: =100*(#REF!/#REF!-1) -> #REF! | E14: =100*(#REF!/#REF!-1) -> #REF! | F14: =100*(#REF!/#REF!-1) -> #REF! | G14: =100*(#REF!/#REF!-1) -> #REF! | H14: =100*(#REF!/#REF!-1) -> #REF! | I14: =100*(#REF!/#REF!-1) -> #REF! | J14: =100*(#REF!/#REF!-1) -> #REF! | ... Y14: =100*(#REF!/#REF!-1) -> #REF!
B15: 3 | C15: =100*(#REF!/#REF!-1) -> #REF! | D15: =100*(#REF!/#REF!-1) -> #REF! | E15: =100*(#REF!/#REF!-1) -> #REF! | F15: =100*(#REF!/#REF!-1) -> #REF! | G15: =100*(#REF!/#REF!-1) -> #REF! | H15: =100*(#REF!/#REF!-1) -> #REF! | I15: =100*(#REF!/#REF!-1) -> #REF! | J15: =100*(#REF!/#REF!-1) -> #REF! | ... Y15: =100*(#REF!/#REF!-1) -> #REF!
B16: 4 | C16: =100*(#REF!/#REF!-1) -> #REF! | D16: =100*(#REF!/#REF!-1) -> #REF! | E16: =100*(#REF!/#REF!-1) -> #REF! | F16: =100*(#REF!/#REF!-1) -> #REF! | G16: =100*(#REF!/#REF!-1) -> #REF! | H16: =100*(#REF!/#REF!-1) -> #REF! | I16: =100*(#REF!/#REF!-1) -> #REF! | J16: =100*(#REF!/#REF!-1) -> #REF! | ... Y16: =100*(#REF!/#REF!-1) -> #REF!
A17: 2009 | B17: 1 | C17: =100*(#REF!/#REF!-1) -> #REF! | D17: =100*(#REF!/#REF!-1) -> #REF! | E17: =100*(#REF!/#REF!-1) -> #REF! | F17: =100*(#REF!/#REF!-1) -> #REF! | G17: =100*(#REF!/#REF!-1) -> #REF! | H17: =100*(#REF!/#REF!-1) -> #REF! | I17: =100*(#REF!/#REF!-1) -> #REF! | J17: =100*(#REF!/#REF!-1) -> #REF! | ... Y17: =100*(#REF!/#REF!-1) -> #REF!
B18: 2 | C18: =100*(#REF!/#REF!-1) -> #REF! | D18: =100*(#REF!/#REF!-1) -> #REF! | E18: =100*(#REF!/#REF!-1) -> #REF! | F18: =100*(#REF!/#REF!-1) -> #REF! | G18: =100*(#REF!/#REF!-1) -> #REF! | H18: =100*(#REF!/#REF!-1) -> #REF! | I18: =100*(#REF!/#REF!-1) -> #REF! | J18: =100*(#REF!/#REF!-1) -> #REF! | ... Y18: =100*(#REF!/#REF!-1) -> #REF!
B19: 3 | C19: =100*(#REF!/#REF!-1) -> #REF! | D19: =100*(#REF!/#REF!-1) -> #REF! | E19: =100*(#REF!/#REF!-1) -> #REF! | F19: =100*(#REF!/#REF!-1) -> #REF! | G19: =100*(#REF!/#REF!-1) -> #REF! | H19: =100*(#REF!/#REF!-1) -> #REF! | I19: =100*(#REF!/#REF!-1) -> #REF! | J19: =100*(#REF!/#REF!-1) -> #REF! | ... Y19: =100*(#REF!/#REF!-1) -> #REF!
B20: 4 | C20: =100*(#REF!/#REF!-1) -> #REF! | D20: =100*(#REF!/#REF!-1) -> #REF! | E20: =100*(#REF!/#REF!-1) -> #REF! | F20: =100*(#REF!/#REF!-1) -> #REF! | G20: =100*(#REF!/#REF!-1) -> #REF! | H20: =100*(#REF!/#REF!-1) -> #REF! | I20: =100*(#REF!/#REF!-1) -> #REF! | J20: =100*(#REF!/#REF!-1) -> #REF! | ... Y20: =100*(#REF!/#REF!-1) -> #REF!
A21: 2010 | B21: 1 | C21: =100*(#REF!/#REF!-1) -> #REF! | D21: =100*(#REF!/#REF!-1) -> #REF! | E21: =100*(#REF!/#REF!-1) -> #REF! | F21: =100*(#REF!/#REF!-1) -> #REF! | G21: =100*(#REF!/#REF!-1) -> #REF! | H21: =100*(#REF!/#REF!-1) -> #REF! | I21: =100*(#REF!/#REF!-1) -> #REF! | J21: =100*(#REF!/#REF!-1) -> #REF! | ... Y21: =100*(#REF!/#REF!-1) -> #REF!
B22: 2 | C22: =100*(#REF!/#REF!-1) -> #REF! | D22: =100*(#REF!/#REF!-1) -> #REF! | E22: =100*(#REF!/#REF!-1) -> #REF! | F22: =100*(#REF!/#REF!-1) -> #REF! | G22: =100*(#REF!/#REF!-1) -> #REF! | H22: =100*(#REF!/#REF!-1) -> #REF! | I22: =100*(#REF!/#REF!-1) -> #REF! | J22: =100*(#REF!/#REF!-1) -> #REF! | ... Y22: =100*(#REF!/#REF!-1) -> #REF!
B23: 3 | C23: =100*(#REF!/#REF!-1) -> #REF! | D23: =100*(#REF!/#REF!-1) -> #REF! | E23: =100*(#REF!/#REF!-1) -> #REF! | F23: =100*(#REF!/#REF!-1) -> #REF! | G23: =100*(#REF!/#REF!-1) -> #REF! | H23: =100*(#REF!/#REF!-1) -> #REF! | I23: =100*(#REF!/#REF!-1) -> #REF! | J23: =100*(#REF!/#REF!-1) -> #REF! | ... Y23: =100*(#REF!/#REF!-1) -> #REF!
B24: 4 | C24: =100*(#REF!/#REF!-1) -> #REF! | D24: =100*(#REF!/#REF!-1) -> #REF! | E24: =100*(#REF!/#REF!-1) -> #REF! | F24: =100*(#REF!/#REF!-1) -> #REF! | G24: =100*(#REF!/#REF!-1) -> #REF! | H24: =100*(#REF!/#REF!-1) -> #REF! | I24: =100*(#REF!/#REF!-1) -> #REF! | J24: =100*(#REF!/#REF!-1) -> #REF! | ... Y24: =100*(#REF!/#REF!-1) -> #REF!
A25: 2011 | B25: 1 | C25: =100*(#REF!/#REF!-1) -> #REF! | D25: =100*(#REF!/#REF!-1) -> #REF! | E25: =100*(#REF!/#REF!-1) -> #REF! | F25: =100*(#REF!/#REF!-1) -> #REF! | G25: =100*(#REF!/#REF!-1) -> #REF! | H25: =100*(#REF!/#REF!-1) -> #REF! | I25: =100*(#REF!/#REF!-1) -> #REF! | J25: =100*(#REF!/#REF!-1) -> #REF! | ... Y25: =100*(#REF!/#REF!-1) -> #REF!
B26: 2 | C26: =100*(#REF!/#REF!-1) -> #REF! | D26: =100*(#REF!/#REF!-1) -> #REF! | E26: =100*(#REF!/#REF!-1) -> #REF! | F26: =100*(#REF!/#REF!-1) -> #REF! | G26: =100*(#REF!/#REF!-1) -> #REF! | H26: =100*(#REF!/#REF!-1) -> #REF! | I26: =100*(#REF!/#REF!-1) -> #REF! | J26: =100*(#REF!/#REF!-1) -> #REF! | ... Y26: =100*(#REF!/#REF!-1) -> #REF!
B27: 3 | C27: =100*(#REF!/#REF!-1) -> #REF! | D27: =100*(#REF!/#REF!-1) -> #REF! | E27: =100*(#REF!/#REF!-1) -> #REF! | F27: =100*(#REF!/#REF!-1) -> #REF! | G27: =100*(#REF!/#REF!-1) -> #REF! | H27: =100*(#REF!/#REF!-1) -> #REF! | I27: =100*(#REF!/#REF!-1) -> #REF! | J27: =100*(#REF!/#REF!-1) -> #REF! | ... Y27: =100*(#REF!/#REF!-1) -> #REF!
B28: 4

Sheet YY%4qsea adj
B1: Gross Value Added by Activity Constant 2006 Prices - Growth Rates
C2: Agriculture | G2: Industry
A3: Year | B3: Quarter | C3: Crops & Cocoa | D3: Livestock | E3: Forestry | F3: Fishing | G3: Mining and Quarrying | H3: Manufacturing | I3: Electricity | J3: Water & Sewerage | K3: Construction | L3: Trade; Repair Of Vehicles, Household Goods | M3: Hotels And Restaurants | N3: Transport & Storage | O3: Information & Communication | P3: Financial & Insurance Activities | Q3: Real Estate Activities | R3: Business & other Services Activities | S3: Public Administration | T3: Education | U3: Health | V3: Other Personal Service Activities | W3: GDP at basic prices | X3: Net Taxes | Y3: GDP at Constant Prices
A5: 2007 | B5: 1 | C5: =100*(#REF!/#REF!-1) -> #REF! | D5: =100*(#REF!/#REF!-1) -> #REF! | E5: =100*(#REF!/#REF!-1) -> #REF! | F5: =100*(#REF!/#REF!-1) -> #REF! | G5: =100*(#REF!/#REF!-1) -> #REF! | H5: =100*(#REF!/#REF!-1) -> #REF! | I5: =100*(#REF!/#REF!-1) -> #REF! | J5: =100*(#REF!/#REF!-1) -> #REF! | ... Y5: =100*(#REF!/#REF!-1) -> #REF!
B6: 2 | C6: =100*(#REF!/#REF!-1) -> #REF! | D6: =100*(#REF!/#REF!-1) -> #REF! | E6: =100*(#REF!/#REF!-1) -> #REF! | F6: =100*(#REF!/#REF!-1) -> #REF! | G6: =100*(#REF!/#REF!-1) -> #REF! | H6: =100*(#REF!/#REF!-1) -> #REF! | I6: =100*(#REF!/#REF!-1) -> #REF! | J6: =100*(#REF!/#REF!-1) -> #REF! | ... Y6: =100*(#REF!/#REF!-1) -> #REF!
B7: 3 | C7: =100*(#REF!/#REF!-1) -> #REF! | D7: =100*(#REF!/#REF!-1) -> #REF! | E7: =100*(#REF!/#REF!-1) -> #REF! | F7: =100*(#REF!/#REF!-1) -> #REF! | G7: =100*(#REF!/#REF!-1) -> #REF! | H7: =100*(#REF!/#REF!-1) -> #REF! | I7: =100*(#REF!/#REF!-1) -> #REF! | J7: =100*(#REF!/#REF!-1) -> #REF! | ... Y7: =100*(#REF!/#REF!-1) -> #REF!
B8: 4 | C8: =100*(#REF!/#REF!-1) -> #REF! | D8: =100*(#REF!/#REF!-1) -> #REF! | E8: =100*(#REF!/#REF!-1) -> #REF! | F8: =100*(#REF!/#REF!-1) -> #REF! | G8: =100*(#REF!/#REF!-1) -> #REF! | H8: =100*(#REF!/#REF!-1) -> #REF! | I8: =100*(#REF!/#REF!-1) -> #REF! | J8: =100*(#REF!/#REF!-1) -> #REF! | ... Y8: =100*(#REF!/#REF!-1) -> #REF!
A9: 2008 | B9: 1 | C9: =100*(#REF!/#REF!-1) -> #REF! | D9: =100*(#REF!/#REF!-1) -> #REF! | E9: =100*(#REF!/#REF!-1) -> #REF! | F9: =100*(#REF!/#REF!-1) -> #REF! | G9: =100*(#REF!/#REF!-1) -> #REF! | H9: =100*(#REF!/#REF!-1) -> #REF! | I9: =100*(#REF!/#REF!-1) -> #REF! | J9: =100*(#REF!/#REF!-1) -> #REF! | ... Y9: =100*(#REF!/#REF!-1) -> #REF!
B10: 2 | C10: =100*(#REF!/#REF!-1) -> #REF! | D10: =100*(#REF!/#REF!-1) -> #REF! | E10: =100*(#REF!/#REF!-1) -> #REF! | F10: =100*(#REF!/#REF!-1) -> #REF! | G10: =100*(#REF!/#REF!-1) -> #REF! | H10: =100*(#REF!/#REF!-1) -> #REF! | I10: =100*(#REF!/#REF!-1) -> #REF! | J10: =100*(#REF!/#REF!-1) -> #REF! | ... Y10: =100*(#REF!/#REF!-1) -> #REF!
B11: 3 | C11: =100*(#REF!/#REF!-1) -> #REF! | D11: =100*(#REF!/#REF!-1) -> #REF! | E11: =100*(#REF!/#REF!-1) -> #REF! | F11: =100*(#REF!/#REF!-1) -> #REF! | G11: =100*(#REF!/#REF!-1) -> #REF! | H11: =100*(#REF!/#REF!-1) -> #REF! | I11: =100*(#REF!/#REF!-1) -> #REF! | J11: =100*(#REF!/#REF!-1) -> #REF! | ... Y11: =100*(#REF!/#REF!-1) -> #REF!
B12: 4 | C12: =100*(#REF!/#REF!-1) -> #REF! | D12: =100*(#REF!/#REF!-1) -> #REF! | E12: =100*(#REF!/#REF!-1) -> #REF! | F12: =100*(#REF!/#REF!-1) -> #REF! | G12: =100*(#REF!/#REF!-1) -> #REF! | H12: =100*(#REF!/#REF!-1) -> #REF! | I12: =100*(#REF!/#REF!-1) -> #REF! | J12: =100*(#REF!/#REF!-1) -> #REF! | ... Y12: =100*(#REF!/#REF!-1) -> #REF!
A13: 2009 | B13: 1 | C13: =100*(#REF!/#REF!-1) -> #REF! | D13: =100*(#REF!/#REF!-1) -> #REF! | E13: =100*(#REF!/#REF!-1) -> #REF! | F13: =100*(#REF!/#REF!-1) -> #REF! | G13: =100*(#REF!/#REF!-1) -> #REF! | H13: =100*(#REF!/#REF!-1) -> #REF! | I13: =100*(#REF!/#REF!-1) -> #REF! | J13: =100*(#REF!/#REF!-1) -> #REF! | ... Y13: =100*(#REF!/#REF!-1) -> #REF!
B14: 2 | C14: =100*(#REF!/#REF!-1) -> #REF! | D14: =100*(#REF!/#REF!-1) -> #REF! | E14: =100*(#REF!/#REF!-1) -> #REF! | F14: =100*(#REF!/#REF!-1) -> #REF! | G14: =100*(#REF!/#REF!-1) -> #REF! | H14: =100*(#REF!/#REF!-1) -> #REF! | I14: =100*(#REF!/#REF!-1) -> #REF! | J14: =100*(#REF!/#REF!-1) -> #REF! | ... Y14: =100*(#REF!/#REF!-1) -> #REF!
B15: 3 | C15: =100*(#REF!/#REF!-1) -> #REF! | D15: =100*(#REF!/#REF!-1) -> #REF! | E15: =100*(#REF!/#REF!-1) -> #REF! | F15: =100*(#REF!/#REF!-1) -> #REF! | G15: =100*(#REF!/#REF!-1) -> #REF! | H15: =100*(#REF!/#REF!-1) -> #REF! | I15: =100*(#REF!/#REF!-1) -> #REF! | J15: =100*(#REF!/#REF!-1) -> #REF! | ... Y15: =100*(#REF!/#REF!-1) -> #REF!
B16: 4 | C16: =100*(#REF!/#REF!-1) -> #REF! | D16: =100*(#REF!/#REF!-1) -> #REF! | E16: =100*(#REF!/#REF!-1) -> #REF! | F16: =100*(#REF!/#REF!-1) -> #REF! | G16: =100*(#REF!/#REF!-1) -> #REF! | H16: =100*(#REF!/#REF!-1) -> #REF! | I16: =100*(#REF!/#REF!-1) -> #REF! | J16: =100*(#REF!/#REF!-1) -> #REF! | ... Y16: =100*(#REF!/#REF!-1) -> #REF!
A17: 2010 | B17: 1 | C17: =100*(#REF!/#REF!-1) -> #REF! | D17: =100*(#REF!/#REF!-1) -> #REF! | E17: =100*(#REF!/#REF!-1) -> #REF! | F17: =100*(#REF!/#REF!-1) -> #REF! | G17: =100*(#REF!/#REF!-1) -> #REF! | H17: =100*(#REF!/#REF!-1) -> #REF! | I17: =100*(#REF!/#REF!-1) -> #REF! | J17: =100*(#REF!/#REF!-1) -> #REF! | ... Y17: =100*(#REF!/#REF!-1) -> #REF!
B18: 2 | C18: =100*(#REF!/#REF!-1) -> #REF! | D18: =100*(#REF!/#REF!-1) -> #REF! | E18: =100*(#REF!/#REF!-1) -> #REF! | F18: =100*(#REF!/#REF!-1) -> #REF! | G18: =100*(#REF!/#REF!-1) -> #REF! | H18: =100*(#REF!/#REF!-1) -> #REF! | I18: =100*(#REF!/#REF!-1) -> #REF! | J18: =100*(#REF!/#REF!-1) -> #REF! | ... Y18: =100*(#REF!/#REF!-1) -> #REF!
B19: 3 | C19: =100*(#REF!/#REF!-1) -> #REF! | D19: =100*(#REF!/#REF!-1) -> #REF! | E19: =100*(#REF!/#REF!-1) -> #REF! | F19: =100*(#REF!/#REF!-1) -> #REF! | G19: =100*(#REF!/#REF!-1) -> #REF! | H19: =100*(#REF!/#REF!-1) -> #REF! | I19: =100*(#REF!/#REF!-1) -> #REF! | J19: =100*(#REF!/#REF!-1) -> #REF! | ... Y19: =100*(#REF!/#REF!-1) -> #REF!
B20: 4 | C20: =100*(#REF!/#REF!-1) -> #REF! | D20: =100*(#REF!/#REF!-1) -> #REF! | E20: =100*(#REF!/#REF!-1) -> #REF! | F20: =100*(#REF!/#REF!-1) -> #REF! | G20: =100*(#REF!/#REF!-1) -> #REF! | H20: =100*(#REF!/#REF!-1) -> #REF! | I20: =100*(#REF!/#REF!-1) -> #REF! | J20: =100*(#REF!/#REF!-1) -> #REF! | ... Y20: =100*(#REF!/#REF!-1) -> #REF!
A21: 2011 | B21: 1 | C21: =100*(#REF!/#REF!-1) -> #REF! | D21: =100*(#REF!/#REF!-1) -> #REF! | E21: =100*(#REF!/#REF!-1) -> #REF! | F21: =100*(#REF!/#REF!-1) -> #REF! | G21: =100*(#REF!/#REF!-1) -> #REF! | H21: =100*(#REF!/#REF!-1) -> #REF! | I21: =100*(#REF!/#REF!-1) -> #REF! | J21: =100*(#REF!/#REF!-1) -> #REF! | ... Y21: =100*(#REF!/#REF!-1) -> #REF!
B22: 2 | C22: =100*(#REF!/#REF!-1) -> #REF! | D22: =100*(#REF!/#REF!-1) -> #REF! | E22: =100*(#REF!/#REF!-1) -> #REF! | F22: =100*(#REF!/#REF!-1) -> #REF! | G22: =100*(#REF!/#REF!-1) -> #REF! | H22: =100*(#REF!/#REF!-1) -> #REF! | I22: =100*(#REF!/#REF!-1) -> #REF! | J22: =100*(#REF!/#REF!-1) -> #REF! | ... Y22: =100*(#REF!/#REF!-1) -> #REF!
B23: 3 | C23: =100*(#REF!/#REF!-1) -> #REF! | D23: =100*(#REF!/#REF!-1) -> #REF! | E23: =100*(#REF!/#REF!-1) -> #REF! | F23: =100*(#REF!/#REF!-1) -> #REF! | G23: =100*(#REF!/#REF!-1) -> #REF! | H23: =100*(#REF!/#REF!-1) -> #REF! | I23: =100*(#REF!/#REF!-1) -> #REF! | J23: =100*(#REF!/#REF!-1) -> #REF! | ... Y23: =100*(#REF!/#REF!-1) -> #REF!
B24: 4

Sheet graphs
A1: not adjusted | AD1: adjusted
B2: Crops & Cocoa | C2: Livestock | D2: Forestry | E2: Fishing | F2: Mining and Quarrying | G2: Manufacturing | H2: Electricity | I2: Water & Sewerage | J2: Construction | K2: Trade; Repair Of Vehicles, Household Goods | L2: Hotels And Restaurants | M2: Transport & Storage | N2: Information & Communication | O2: Financial & Insurance Activities | P2: Real Estate Activities | Q2: Business & other Services Activities | R2: Public Administration | S2: Education | T2: Health | U2: Other Personal Service Activities | V2: GDP at basic prices | W2: Net Taxes | X2: GDP at Constant Prices | Z2: Agric | AA2: Industry | AB2: Services | AD2: =B2 -> Crops & Cocoa | AE2: =C2 -> Livestock | AF2: =D2 -> Forestry | AG2: =E2 -> Fishing | AH2: =F2 -> Mining and Quarrying | AI2: =G2 -> Manufacturing | AJ2: =H2 -> Electricity | AK2: =I2 -> Water & Sewerage | ... AZ2: =X2 -> GDP at Constant Prices | BB2: Agric | BC2: Industry | BD2: Services
A3: 2006-01 | B3: 609.0558 | C3: 100.47076 | D3: 129.68677 | E3: 98.581844 | F3: 112.369 | G3: 412.73537 | H3: 37.848132 | I3: 54.190928 | J3: 247.38157 | K3: 275.27246 | L3: 198.39947 | M3: 609.08019 | N3: 121.72576 | O3: 112.54336 | P3: 97.85 | Q3: 134.80522 | R3: 217.35653 | S3: 163.95252 | T3: 62.421321 | U3: 119.87612 | V3: 3915.6031 | W3: 171.9387 | X3: 4087.5418 | Z3: =SUM(B3:E3) -> 937.79518 | AA3: =SUM(F3:J3) -> 864.525 | AB3: =SUM(K3:U3) -> 2113.2829 | AD3: 979 | AE3: 97 | AF3: 179 | AG3: 118 | AH3: 115 | AI3: 419 | AJ3: 37 | AK3: 54 | AL3: 240 | AM3: 276 | AN3: 190 | AO3: 570 | AP3: 118 | AQ3: 113 | AR3: 97 | AS3: 128 | AT3: 216 | AU3: 163 | AV3: 63 | AW3: 112 | AX3: 4284 | AY3: 184 | AZ3: 4410 | BB3: =SUM(AD3:AG3) -> 1373 | BC3: =SUM(AH3:AL3) -> 865 | BD3: =SUM(AM3:AW3) -> 2046
A4: 2006-02 | B4: 330.01712 | C4: 85.512172 | D4: 204.04796 | E4: 85.242242 | F4: 106.03986 | G4: 436.18658 | H4: 37.492435 | I4: 56.042662 | J4: 248.51998 | K4: 272.37388 | L4: 212.7635 | M4: 551.43953 | N4: 112.69264 | O4: 121.53546 | P4: 97.85 | Q4: 134.62405 | R4: 216.62439 | S4: 163.35396 | T4: 62.432642 | U4: 325.6884 | V4: 3860.4795 | W4: 207.27711 | X4: 4067.7566 | Z4: =SUM(B4:E4) -> 704.8195 | AA4: =SUM(F4:J4) -> 884.28152 | AB4: =SUM(K4:U4) -> 2271.3784 | AD4: 909 | AE4: 104 | AF4: 186 | AG4: 97 | AH4: 106 | AI4: 446 | AJ4: 37 | AK4: 57 | AL4: 235 | AM4: 279 | AN4: 211 | AO4: 578 | AP4: 115 | AQ4: 154 | AR4: 98 | AS4: 132 | AT4: 215 | AU4: 162 | AV4: 62 | AW4: 286 | AX4: 4469 | AY4: 214 | AZ4: 4634 | BB4: =SUM(AD4:AG4) -> 1296 | BC4: =SUM(AH4:AL4) -> 881 | BD4: =SUM(AM4:AW4) -> 2292
A5: 2006-03 | B5: 1356.0077 | C5: 80.450758 | D5: 202.06717 | E5: 146.56621 | F5: 137.86021 | G5: 474.39157 | H5: 34.427036 | I5: 57.222219 | J5: 249.0891 | K5: 278.01451 | L5: 236.39703 | M5: 610.43656 | N5: 119.82264 | O5: 129.31008 | P5: 97.85 | Q5: 117.79614 | R5: 215.15893 | S5: 162.1562 | T5: 62.455661 | U5: 109.01423 | V5: 4876.4939 | W5: 196.61867 | X5: 5073.1126 | Z5: =SUM(B5:E5) -> 1785.0918 | AA5: =SUM(F5:J5) -> 952.99012 | AB5: =SUM(K5:U5) -> 2138.412 | AD5: 920 | AE5: 110 | AF5: 185 | AG5: 118 | AH5: 134 | AI5: 483 | AJ5: 37 | AK5: 57 | AL5: 255 | AM5: 284 | AN5: 246 | AO5: 605 | AP5: 122 | AQ5: 114 | AR5: 98 | AS5: 129 | AT5: 216 | AU5: 163 | AV5: 62 | AW5: 115 | AX5: 4453 | AY5: 207 | AZ5: 4710 | BB5: =SUM(AD5:AG5) -> 1333 | BC5: =SUM(AH5:AL5) -> 966 | BD5: =SUM(AM5:AW5) -> 2154
A6: 2006-04 | B6: 1498.6194 | C6: 170.66631 | D6: 200.1981 | E6: 117.90971 | F6: 141.13093 | G6: 500.18648 | H6: 32.932397 | I6: 56.944191 | J6: 271.2838 | K6: 315.03915 | L6: 246.54 | M6: 586.24373 | N6: 128.75896 | O6: 109.51111 | P6: 97.85 | Q6: 135.27459 | R6: 212.96015 | S6: 165.53733 | T6: 62.490376 | U6: 107.02125 | V6: 5157.0979 | W6: 319.56552 | X6: 5476.6634 | Z6: =SUM(B6:E6) -> 1987.3935 | AA6: =SUM(F6:J6) -> 1002.4778 | AB6: =SUM(K6:U6) -> 2167.2266 | AD6: 972 | AE6: 121 | AF6: 184 | AG6: 114 | AH6: 141 | AI6: 474 | AJ6: 32 | AK6: 56 | AL6: 291 | AM6: 300 | AN6: 250 | AO6: 605 | AP6: 127 | AQ6: 101 | AR6: 99 | AS6: 134 | AT6: 215 | AU6: 167 | AV6: 62 | AW6: 127 | AX6: 4572 | AY6: 277 | AZ6: 4899 | BB6: =SUM(AD6:AG6) -> 1391 | BC6: =SUM(AH6:AL6) -> 994 | BD6: =SUM(AM6:AW6) -> 2187
A7: 2007-01 | B7: 575.58938 | C7: 108.0076 | D7: 127.63035 | E7: 82.276489 | F7: 135.7785 | G7: 438.20746 | H7: 34.793066 | I7: 56.498809 | J7: 325.58907 | K7: 293.15984 | L7: 224.3571 | M7: 659.93488 | N7: 125.62806 | O7: 133.78871 | P7: 100.1984 | Q7: 137.47032 | R7: 236.91164 | S7: 174.83779 | T7: 62.661863 | U7: 193.36126 | V7: 4226.6806 | W7: 317.33352 | X7: 4544.0141 | Z7: =SUM(B7:E7) -> 893.50382 | AA7: =SUM(F7:J7) -> 990.86692 | AB7: =SUM(K7:U7) -> 2342.3099 | AD7: 925 | AE7: 105 | AF7: 176 | AG7: 98 | AH7: 139 | AI7: 445 | AJ7: 34 | AK7: 56 | AL7: 315 | AM7: 294 | AN7: 214 | AO7: 617 | AP7: 122 | AQ7: 134 | AR7: 99 | AS7: 130 | AT7: 235 | AU7: 174 | AV7: 63 | AW7: 180 | AX7: 4555 | AY7: 340 | AZ7: 4898 | BB7: =SUM(AD7:AG7) -> 1304 | BC7: =SUM(AH7:AL7) -> 989 | BD7: =SUM(AM7:AW7) -> 2262
A8: 2007-02 | B8: 333.66665 | C8: 91.074897 | D8: 193.06373 | E8: 84.595683 | F8: 129.74797 | G8: 451.68599 | H8: 27.301738 | I8: 55.433645 | J8: 355.18158 | K8: 282.45565 | L8: 223.55082 | M8: 643.01771 | N8: 128.73655 | O8: 127.78138 | P8: 100.1984 | Q8: 135.74328 | R8: 238.10966 | S8: 178.15773 | T8: 65.487447 | U8: 193.2609 | V8: 4038.2514 | W8: 322.96227 | X8: 4361.2137 | Z8: =SUM(B8:E8) -> 702.40096 | AA8: =SUM(F8:J8) -> 1019.3509 | AB8: =SUM(K8:U8) -> 2316.4995 | AD8: 918 | AE8: 111 | AF8: 176 | AG8: 96 | AH8: 130 | AI8: 461 | AJ8: 27 | AK8: 56 | AL8: 335 | AM8: 290 | AN8: 223 | AO8: 674 | AP8: 132 | AQ8: 164 | AR8: 100 | AS8: 133 | AT8: 237 | AU8: 177 | AV8: 66 | AW8: 169 | AX8: 4675 | AY8: 334 | AZ8: 4974 | BB8: =SUM(AD8:AG8) -> 1301 | BC8: =SUM(AH8:AL8) -> 1009 | BD8: =SUM(AM8:AW8) -> 2365
A9: 2007-03 | B9: 1380.4138 | C9: 84.790926 | D9: 192.4306 | E9: 138.27722 | F9: 136.20964 | G9: 427.18654 | H9: 25.340071 | I9: 55.993075 | J9: 326.29944 | K9: 288.25343 | L9: 203.35972 | M9: 630.25328 | N9: 124.43789 | O9: 150.10712 | P9: 100.1984 | Q9: 122.92961 | R9: 240.26366 | S9: 180.56642 | T9: 65.893068 | U9: 174.63103 | V9: 5047.8349 | W9: 315.08639 | X9: 5362.9213 | Z9: =SUM(B9:E9) -> 1795.9125 | AA9: =SUM(F9:J9) -> 971.02877 | AB9: =SUM(K9:U9) -> 2280.8936 | AD9: 937 | AE9: 116 | AF9: 176 | AG9: 111 | AH9: 133 | AI9: 435 | AJ9: 28 | AK9: 56 | AL9: 334 | AM9: 294 | AN9: 211 | AO9: 625 | AP9: 127 | AQ9: 132 | AR9: 100 | AS9: 134 | AT9: 241 | AU9: 181 | AV9: 66 | AW9: 185 | AX9: 4622 | AY9: 332 | AZ9: 4975 | BB9: =SUM(AD9:AG9) -> 1340 | BC9: =SUM(AH9:AL9) -> 986 | BD9: =SUM(AM9:AW9) -> 2296
A10: 2007-04 | B10: 1452.9302 | C10: 173.92658 | D10: 192.77532 | E10: 110.65061 | F10: 129.86388 | G10: 484.22 | H10: 30.765125 | I10: 59.074471 | J10: 244.49182 | K10: 338.73108 | L10: 265.33237 | M10: 640.19413 | N10: 123.9975 | O10: 148.12279 | P10: 100.1984 | Q10: 146.55679 | R10: 244.31505 | S10: 186.93805 | T10: 65.257623 | U10: 159.04682 | V10: 5297.3886 | W10: 348.01782 | X10: 5645.4064 | Z10: =SUM(B10:E10) -> 1930.2827 | AA10: =SUM(F10:J10) -> 948.4153 | AB10: =SUM(K10:U10) -> 2418.6906 | AD10: 942 | AE10: 123 | AF10: 178 | AG10: 107 | AH10: 130 | AI10: 459 | AJ10: 30 | AK10: 58 | AL10: 262 | AM10: 324 | AN10: 271 | AO10: 661 | AP10: 123 | AQ10: 137 | AR10: 101 | AS10: 146 | AT10: 247 | AU10: 188 | AV10: 65 | AW10: 189 | AX10: 4741 | AY10: 302 | AZ10: 5053 | BB10: =SUM(AD10:AG10) -> 1350 | BC10: =SUM(AH10:AL10) -> 939 | BD10: =SUM(AM10:AW10) -> 2452
A11: 2008-01 | B11: 608.6499 | C11: 130.40922 | D11: 127.91005 | E11: 91.463976 | F11: 129.83433 | G11: 475.64816 | H11: 33.404619 | I11: 57.945379 | J11: 433.94207 | K11: 312.01943 | L11: 286.68681 | M11: 709.7171 | N11: 145.24478 | O11: 150.1036 | P11: 102.60316 | Q11: 133.31828 | R11: 256.84794 | S11: 195.19664 | T11: 63.779926 | U11: 211.75371 | V11: 4656.4791 | W11: 287.26728 | X11: 4943.7464 | Z11: =SUM(B11:E11) -> 958.43314 | AA11: =SUM(F11:J11) -> 1130.7746 | AB11: =SUM(K11:U11) -> 2567.2714 | AD11: 979 | AE11: 126 | AF11: 177 | AG11: 109 | AH11: 139 | AI11: 483 | AJ11: 32 | AK11: 58 | AL11: 420 | AM11: 312 | AN11: 271 | AO11: 664 | AP11: 141 | AQ11: 148 | AR11: 102 | AS11: 126 | AT11: 255 | AU11: 194 | AV11: 64 | AW11: 197 | AX11: 4997 | AY11: 308 | AZ11: 5322 | BB11: =SUM(AD11:AG11) -> 1391 | BC11: =SUM(AH11:AL11) -> 1132 | BD11: =SUM(AM11:AW11) -> 2474
A12: 2008-02 | B12: 375.03964 | C12: 100.7386 | D12: 185.65793 | E12: 117.22377 | F12: 138.33286 | G12: 448.23824 | H12: 35.294189 | I12: 55.752994 | J12: 447.45745 | K12: 325.30615 | L12: 258.62655 | M12: 630.62294 | N12: 146.08755 | O12: 90.571258 | P12: 102.60316 | Q12: 127.8669 | R12: 265.68937 | S12: 201.4231 | T12: 64.056559 | U12: 200.71002 | V12: 4317.2992 | W12: 299.04368 | X12: 4616.3429 | Z12: =SUM(B12:E12) -> 778.65993 | AA12: =SUM(F12:J12) -> 1125.0757 | AB12: =SUM(K12:U12) -> 2413.5636 | AD12: 1028 | AE12: 123 | AF12: 170 | AG12: 133 | AH12: 130 | AI12: 458 | AJ12: 35 | AK12: 56 | AL12: 423 | AM12: 334 | AN12: 261 | AO12: 661 | AP12: 149 | AQ12: 119 | AR12: 102 | AS12: 126 | AT12: 264 | AU12: 200 | AV12: 64 | AW12: 176 | AX12: 5012 | AY12: 309 | AZ12: 5277 | BB12: =SUM(AD12:AG12) -> 1454 | BC12: =SUM(AH12:AL12) -> 1102 | BD12: =SUM(AM12:AW12) -> 2456
A13: 2008-03 | B13: 1514.3567 | C13: 88.889268 | D13: 186.10934 | E13: 153.98887 | F13: 138.31037 | G13: 456.19343 | H13: 32.936821 | I13: 56.086822 | J13: 430.66882 | K13: 340.39435 | L13: 231.42349 | M13: 700.15434 | N13: 153.78579 | O13: 213.05864 | P13: 102.60316 | Q13: 143.01554 | R13: 274.42326 | S13: 207.68837 | T13: 69.870573 | U13: 189.02053 | V13: 5682.9785 | W13: 301.17671 | X13: 5984.1552 | Z13: =SUM(B13:E13) -> 1943.3442 | AA13: =SUM(F13:J13) -> 1114.1963 | AB13: =SUM(K13:U13) -> 2625.438 | AD13: 1029 | AE13: 121 | AF13: 170 | AG13: 124 | AH13: 133 | AI13: 465 | AJ13: 36 | AK13: 56 | AL13: 441 | AM13: 347 | AN13: 237 | AO13: 694 | AP13: 156 | AQ13: 186 | AR13: 103 | AS13: 156 | AT13: 276 | AU13: 208 | AV13: 70 | AW13: 200 | AX13: 5208 | AY13: 318 | AZ13: 5543 | BB13: =SUM(AD13:AG13) -> 1444 | BC13: =SUM(AH13:AL13) -> 1131 | BD13: =SUM(AM13:AW13) -> 2633
A14: 2008-04 | B14: 1566.4538 | C14: 161.06292 | D14: 182.72268 | E14: 125.32339 | F14: 137.92244 | G14: 487.92017 | H14: 39.464371 | I14: 59.114805 | J14: 427.39609 | K14: 339.18007 | L14: 222.96315 | M14: 631.40562 | N14: 155.78188 | O14: 166.36651 | P14: 102.60316 | Q14: 128.59928 | R14: 284.83943 | S14: 209.99189 | T14: 73.092943 | U14: 184.81574 | V14: 5687.0203 | W14: 360.81233 | X14: 6047.8326 | Z14: =SUM(B14:E14) -> 2035.5628 | AA14: =SUM(F14:J14) -> 1151.8179 | AB14: =SUM(K14:U14) -> 2499.6397 | AD14: 1015 | AE14: 114 | AF14: 168 | AG14: 121 | AH14: 130 | AI14: 463 | AJ14: 38 | AK14: 58 | AL14: 459 | AM14: 325 | AN14: 230 | AO14: 652 | AP14: 154 | AQ14: 155 | AR14: 104 | AS14: 128 | AT14: 288 | AU14: 212 | AV14: 73 | AW14: 219 | AX14: 5106 | AY14: 313 | AZ14: 5419 | BB14: =SUM(AD14:AG14) -> 1418 | BC14: =SUM(AH14:AL14) -> 1148 | BD14: =SUM(AM14:AW14) -> 2540
... A23: 2011-01 | B23: 1133.7557 | C23: 126.66069 | D23: 122.65034 | E23: 96.814519 | F23: 374.91379 | G23: 523.62663 | H23: 41.426842 | I23: 65.077599 | J23: 602.10657 | K23: 393.79997 | L23: 261.46034 | M23: 896.22317 | N23: 211.16718 | O23: 183.47606 | P23: 110.16931 | Q23: 201.06322 | R23: 312.18282 | S23: 246.87057 | T23: 96.009834 | U23: 272.70407 | V23: 6272.1592 | W23: 388.1745 | X23: 6660.3337 | Z23: =SUM(B23:E23) -> 1479.8813 | AA23: =SUM(F23:J23) -> 1607.1514 | AB23: =SUM(K23:U23) -> 3185.1265 | AD23: 1814 | AE23: 123 | AF23: 171 | AG23: 116 | AH23: 379 | AI23: 535 | AJ23: 40 | AK23: 65 | AL23: 584 | AM23: 392 | AN23: 240 | AO23: 839 | AP23: 206 | AQ23: 180 | AR23: 109 | AS23: 185 | AT23: 311 | AU23: 246 | AV23: 96 | AW23: 256 | AX23: 6887 | AY23: 410 | AZ23: 7100 | BB23: =SUM(AD23:AG23) -> 2224 | BC23: =SUM(AH23:AL23) -> 1603 | BD23: =SUM(AM23:AW23) -> 3060
A24: 2011-02
A25: 2011-03
A26: 2011-04

Sheet Sheet11
A2: Seasonally adjusted Value added growth rates by sectors (Quarter-on-quarter change in %)

Sheet Sheet2

Sheet Current GDP_All
A1: Appendix 1- Quarterly Value Added and Gross Domestic Product at Current Prices by Economic Activity and Respective Sectoral Distribution
A2: Year | B2: Quarter | C2: Value Added (GHc Million) | K2: % of GDP (@ basic prices)
C3: Agriculture | D3: Industry | E3: Services | F3: Total Value Added (GDP_@_basic prices) | G3: Net indirect Taxes | H3: Total (GDP_in purchaser's_value) | I3: ow InformalGDP in purchaser's value | J3: Total Non-Oil (GDP in purchaser's_value) | K3: Agriculture | L3: Industry | M3: Services | N3: Total Value Added (GDP_@_basic prices) | O3: ow Informal GDP in purchaser's value
A4: 2006_Q1 | C4: 1809.9572 | D4: 2517.9879 | E4: 2441.5909 | F4: 6769.5361 | G4: 281.85998 | H4: 7051.3961 | I4: 4219.2333 | J4: 7051.3961 | K4: 26.736799 | L4: 37.195871 | M4: 36.06733 | N4: 100 | O4: 59.835433
A5: 2006_Q2 | C5: 1057.7242 | D5: 2589.86 | E5: 2423.4875 | F5: 6071.0717 | G5: 338.63742 | H5: 6409.7092 | I5: 3457.7945 | J5: 6409.7092 | K5: 17.422364 | L5: 42.659024 | M5: 39.918612 | N5: 100 | O5: 53.946199
A6: 2006_Q3 | C6: 1829.5752 | D6: 2572.4353 | E6: 2515.3405 | F6: 6917.351 | G6: 325.4776 | H6: 7242.8286 | I6: 4211.623 | J6: 7242.8286 | K6: 26.449073 | L6: 37.188156 | M6: 36.362771 | N6: 100 | O6: 58.148871
A7: 2006_Q4 | C7: 2235.4562 | D7: 2304.0212 | E7: 2704.7976 | F7: 7244.2749 | G7: 386.0896 | H7: 7630.3645 | I7: 4577.1027 | J7: 7630.3645 | K7: 30.858246 | L7: 31.804717 | M7: 37.337037 | N7: 100 | O7: 59.985374
A8: 2007_Q1 | C8: 2064.8749 | D8: 2995.6024 | E8: 2646.227 | F8: 7706.7042 | G8: 537.91552 | H8: 8244.6198 | I8: 4483.4885 | J8: 8244.6198 | K8: 26.793229 | L8: 38.870083 | M8: 34.336688 | N8: 100 | O8: 54.38078
A9: 2007_Q2 | C9: 1261.1086 | D9: 3015.2215 | E9: 2616.1654 | F9: 6892.4955 | G9: 486.23552 | H9: 7378.731 | I9: 3657.9901 | J9: 7378.731 | K9: 18.296836 | L9: 43.746441 | M9: 37.956723 | N9: 100 | O9: 49.574785
A10: 2007_Q3 | C10: 2193.3219 | D10: 2900.2811 | E10: 3024.2829 | F10: 8117.8859 | G10: 461.74849 | H10: 8579.6344 | I10: 4555.8795 | J10: 8579.6344 | K10: 27.018388 | L10: 35.727049 | M10: 37.254563 | N10: 100 | O10: 53.101092
A11: 2007_Q4 | C11: 2538.3426 | D11: 2639.7977 | E11: 4246.9867 | F11: 9425.127 | G11: 459.71897 | H11: 9884.846 | I11: 4859.5895 | J11: 9884.846 | K11: 26.931654 | L11: 28.008086 | M11: 45.06026 | N11: 100 | O11: 49.162015
A12: 2008_Q1 | C12: 3339.5032 | D12: 3709.685 | E12: 3507.0405 | F12: 10556.229 | G12: 573.58002 | H12: 11129.809 | I12: 5771.8679 | J12: 11129.809 | K12: 31.635381 | L12: 35.142143 | M12: 33.222475 | N12: 100 | O12: 51.859542
A13: 2008_Q2 | C13: 1507.5491 | D13: 3543.1356 | E13: 3488.2659 | F13: 8538.9506 | G13: 566.95453 | H13: 9105.9052 | I13: 3900.266 | J13: 9105.9052 | K13: 17.65497 | L13: 41.493806 | M13: 40.851225 | N13: 100 | O13: 42.832271
A14: 2008_Q3 | C14: 2827.2157 | D14: 3423.388 | E14: 4602.0899 | F14: 10852.694 | G14: 667.7695 | H14: 11520.463 | I14: 5192.9743 | J14: 11520.463 | K14: 26.05082 | L14: 31.544132 | M14: 42.405047 | N14: 100 | O14: 45.07609
A15: 2008_Q4 | C15: 3542.1241 | D15: 3230.7512 | E15: 4490.3334 | F15: 11263.209 | G15: 445.97046 | H15: 11709.179 | I15: 5892.2886 | J15: 11709.179 | K15: 31.448624 | L15: 28.68411 | M15: 39.867266 | N15: 100 | O15: 50.321962
... A85: 2026_Q2** | C85: 73380.364 | D85: 115496.64 | E85: 160221.23 | F85: 349098.23 | G85: 22972.277 | H85: 372070.51 | I85: 26514.888 | J85: 359743.64 | K85: 21.019976 | L85: 33.08428 | M85: 45.895744 | N85: 100 | O85: 7.1263074
A86: *revised | C86: ** provisional

Sheet Current GDP_Agric
B1: Appendix 2 - Agriculture: Value Added by activity at Current Prices
B2: Year | C2: Value Added (GHc Million)
C3: Crops & Cocoa | D3: Cocoa | E3: Livestock | F3: Forestry & Logging | G3: Fishing | H3: Total Value Added | I3: ow informal
B4: 2006_Q1 | C4: 1259.2158 | D4: 169.6954 | E4: 245.12971 | F4: 157.76478 | G4: 147.84699 | H4: 1809.9572 | I4: 1652.1925
B5: 2006_Q2 | C5: 515.30791 | D5: 170.86547 | E5: 219.35813 | F5: 173.66214 | G5: 149.39603 | H5: 1057.7242 | I5: 884.06208
B6: 2006_Q3 | C6: 1246.2897 | D6: 175.65361 | E6: 220.70896 | F6: 191.30474 | G6: 171.27179 | H6: 1829.5752 | I6: 1638.2705
B7: 2006_Q4 | C7: 1451.9683 | D7: 187.98125 | E7: 407.9319 | F7: 211.45038 | G7: 164.10557 | H7: 2235.4562 | I7: 2024.0058
B8: 2007_Q1 | C8: 1465.6541 | D8: 175.04093 | E8: 271.29655 | F8: 190.24946 | G8: 137.67481 | H8: 2064.8749 | I8: 1874.6254
B9: 2007_Q2 | C9: 609.33144 | D9: 180.44223 | E9: 248.42939 | F9: 214.53523 | G9: 188.81251 | H9: 1261.1086 | I9: 1046.5733
B10: 2007_Q3 | C10: 1488.25 | D10: 191.85394 | E10: 255.17656 | F10: 240.75695 | G10: 209.13837 | H10: 2193.3219 | I10: 1952.5649
